time_divider/src/time_divider.v
module time_divider 
#(parameter ratio=4) //分频比
(
    input i_CLK, //输入时钟信号
    input i_RST, //同步重置信号高电平有效
    output reg o_CLK //输出时钟信号
);
    integer c;
    integer target=ratio/2;
    initial begin
        o_CLK=0;
        c=0;
    end
    always @(posedge i_CLK) begin
        if(i_RST==1) begin
            c=0;
            o_CLK=0;
        end
        else begin
            c=c+1;
        end
        if(c==target) begin
            o_CLK=~o_CLK;
            c=0;
        end
    end
endmodule

time_divider/src/time_divider_tb.v
module time_divider_tb (
);
    reg i_CLK; //input clock signal
    reg i_RST; //rest signal->enables when high
    wire o_CLK;
    time_divider #(10) divider (.i_CLK(i_CLK),.i_RST(i_RST),.o_CLK(o_CLK));
    initial begin   
        $dumpfile("./build/wave.vcd");  // 指定VCD文件的名字为wave.vcd，仿真信息将记录到此文件
        $dumpvars(0, time_divider_tb);  // 指定层次数为0，则tb_code 模块及其下面各层次的所有信号将被记录
        #10000 $finish;
    end
    initial begin
        i_RST<=0; //归零复位信号
        i_CLK<=0;
    end
    integer i;
    initial begin
        for (i = 0;i<100 ;i=i+1 ) begin
            #5
            i_CLK=~i_CLK;
        end
    end
endmodule

program_template/build/wave.vcd
$date
	Tue Dec 28 09:06:09 2021
$end
$version
	Icarus Verilog
$end
$timescale
	1s
$end
$scope module time_divider_tb $end
$var wire 1 ! o_CLK $end
$var reg 1 " i_CLK $end
$var reg 1 # i_RST $end
$var integer 32 $ i [31:0] $end
$scope module divider $end
$var wire 1 " i_CLK $end
$var wire 1 # i_RST $end
$var reg 1 ! o_CLK $end
$var integer 32 % c [31:0] $end
$var integer 32 & target [31:0] $end
$upscope $end
$upscope $end
$enddefinitions $end
#0
$dumpvars
b101 &
b0 %
b0 $
0#
0"
0!
$end
#5
b1 %
b1 $
1"
#10
b10 $
0"
#15
b10 %
b11 $
1"
#20
b100 $
0"
#25
b11 %
b101 $
1"
#30
b110 $
0"
#35
b100 %
b111 $
1"
#40
b1000 $
0"
#45
1!
b0 %
b1001 $
1"
#50
b1010 $
0"
#55
b1 %
b1011 $
1"
#60
b1100 $
0"
#65
b10 %
b1101 $
1"
#70
b1110 $
0"
#75
b11 %
b1111 $
1"
#80
b10000 $
0"
#85
b100 %
b10001 $
1"
#90
b10010 $
0"
#95
0!
b0 %
b10011 $
1"
#100
b10100 $
0"
#105
b1 %
b10101 $
1"
#110
b10110 $
0"
#115
b10 %
b10111 $
1"
#120
b11000 $
0"
#125
b11 %
b11001 $
1"
#130
b11010 $
0"
#135
b100 %
b11011 $
1"
#140
b11100 $
0"
#145
1!
b0 %
b11101 $
1"
#150
b11110 $
0"
#155
b1 %
b11111 $
1"
#160
b100000 $
0"
#165
b10 %
b100001 $
1"
#170
b100010 $
0"
#175
b11 %
b100011 $
1"
#180
b100100 $
0"
#185
b100 %
b100101 $
1"
#190
b100110 $
0"
#195
0!
b0 %
b100111 $
1"
#200
b101000 $
0"
#205
b1 %
b101001 $
1"
#210
b101010 $
0"
#215
b10 %
b101011 $
1"
#220
b101100 $
0"
#225
b11 %
b101101 $
1"
#230
b101110 $
0"
#235
b100 %
b101111 $
1"
#240
b110000 $
0"
#245
1!
b0 %
b110001 $
1"
#250
b110010 $
0"
#255
b1 %
b110011 $
1"
#260
b110100 $
0"
#265
b10 %
b110101 $
1"
#270
b110110 $
0"
#275
b11 %
b110111 $
1"
#280
b111000 $
0"
#285
b100 %
b111001 $
1"
#290
b111010 $
0"
#295
0!
b0 %
b111011 $
1"
#300
b111100 $
0"
#305
b1 %
b111101 $
1"
#310
b111110 $
0"
#315
b10 %
b111111 $
1"
#320
b1000000 $
0"
#325
b11 %
b1000001 $
1"
#330
b1000010 $
0"
#335
b100 %
b1000011 $
1"
#340
b1000100 $
0"
#345
1!
b0 %
b1000101 $
1"
#350
b1000110 $
0"
#355
b1 %
b1000111 $
1"
#360
b1001000 $
0"
#365
b10 %
b1001001 $
1"
#370
b1001010 $
0"
#375
b11 %
b1001011 $
1"
#380
b1001100 $
0"
#385
b100 %
b1001101 $
1"
#390
b1001110 $
0"
#395
0!
b0 %
b1001111 $
1"
#400
b1010000 $
0"
#405
b1 %
b1010001 $
1"
#410
b1010010 $
0"
#415
b10 %
b1010011 $
1"
#420
b1010100 $
0"
#425
b11 %
b1010101 $
1"
#430
b1010110 $
0"
#435
b100 %
b1010111 $
1"
#440
b1011000 $
0"
#445
1!
b0 %
b1011001 $
1"
#450
b1011010 $
0"
#455
b1 %
b1011011 $
1"
#460
b1011100 $
0"
#465
b10 %
b1011101 $
1"
#470
b1011110 $
0"
#475
b11 %
b1011111 $
1"
#480
b1100000 $
0"
#485
b100 %
b1100001 $
1"
#490
b1100010 $
0"
#495
0!
b0 %
b1100011 $
1"
#500
b1100100 $
0"
