VGA_test/vga_pineball/src/vga_driver.v
//the vga driver to display the data
module vga_driver
#(
	// VGA_1024_768_60fps_65MHz
	// Horizontal Parameter	( Pixel )
	parameter	H_DISP 	=	11'd1024, 
	parameter	H_FRONT	=	11'd24,	 
	parameter	H_SYNC 	=	11'd136,  
	parameter	H_BACK 	=	11'd160,   
	parameter	H_TOTAL	=	11'd1344, 
	// Virtical Parameter	( Line ) 
	parameter	V_DISP 	=	10'd768,  					
	parameter	V_FRONT	=	10'd3,   
	parameter	V_SYNC 	=	10'd6,    
	parameter	V_BACK 	=	10'd29,   
	parameter	V_TOTAL	=	10'd806  
)
(  	
	input			clk_vga,	// clock of 25MHz
	input			rst_n,     	// reset signal
	
	input	[11:0]	vga_data,
	output	[11:0]	vga_rgb,	// return the displayed colors to the connection
	output	reg		vga_hs,		// VGA管脚 行同步
	output	reg		vga_vs,		// VGA管脚 场同步
	
	output	[9:0]	vga_xpos,	// the X-axis of the pixel
	output	[9:0]	vga_ypos	// the Y-axis of the pixel
);	

//------------------------------------------
// 行同步信号发生器
reg [10:0] hcnt; 
always @ (posedge clk_vga or negedge rst_n)
begin
	if (!rst_n) begin
		hcnt <= 0;
		// $display("%h",vcnt);
	end
	else
		begin
        if (hcnt < H_TOTAL-1'b1)			
            hcnt <= hcnt + 1'b1;
        else
            hcnt <= 0;
		end
end 

always@(posedge clk_vga or negedge rst_n)
begin
	if(!rst_n)
		vga_hs <= 1;
	else
		begin
        if( (hcnt >= H_DISP+H_FRONT-1'b1) && (hcnt < H_DISP+H_FRONT+H_SYNC-1'b1) )
            vga_hs <= 0;       
        else
            vga_hs <= 1;
		end
end

//------------------------------------------
// 场同步信号发生器
reg [9:0] vcnt;
always @ (posedge clk_vga or negedge rst_n)
begin
	if (!rst_n) begin
		vcnt <= 0;
		// $display("%h",vcnt);
	end
	else
		begin
		if(hcnt == H_DISP-1)
			begin
			if (vcnt < V_TOTAL-1'b1)			
				vcnt <= vcnt+1'b1;
			else
				vcnt <= 0;   
			end 
		else
			vcnt <= vcnt;
		end
end

always @ (posedge clk_vga or negedge rst_n) 
begin
	if(!rst_n)
		vga_vs <= 1;
	else
		begin
		if( (vcnt >= V_DISP+V_FRONT-1'b1) && (vcnt < V_DISP+V_FRONT+V_SYNC-1'b1) )
            vga_vs <= 0;        
        else
            vga_vs <= 1;		
		end
end

//------------------------------------------
assign	vga_xpos = (hcnt < H_DISP) ? hcnt[9:0]+1'b1 : 10'd0;
assign	vga_ypos = (vcnt < V_DISP) ? vcnt[9:0]+1'b1 : 10'd0;
assign	vga_rgb 	= 	((hcnt < H_DISP) && (vcnt < V_DISP)) ? vga_data : 12'd0;

endmodule

comprehensive/src/vga_display.v
/*************************************************
*	Module Name		:	vga_display.v		   
*	Engineer		:	Crazy Bingo
*	Target Device	:	EP2C35F672C6N
*	Tool versions	:	Quartus II 11.0
*	Create Date		:	2011-6-26
*	Revision		:	v1.0
*	Description		:   	
**************************************************/
module vga_display
#(
	parameter	H_DISP 	=	10'd640,
	parameter	V_DISP 	=	10'd480 
)
(
	input				clk, 
	input   			rst_n, 

	input		[9:0]	vga_xpos, 
	input 		[9:0] 	vga_ypos,
	output 	reg	[11:0] 	vga_data
);

localparam RED     	=	12'hF00;  //F00
localparam GREEN     = 	12'h0F0;  //0F0
localparam BLUE      = 	12'h00F;  
localparam WHITE     = 	12'hFFF;  
localparam BLACK     = 	12'h000;  
localparam YELLOW    = 	12'h0FF;  
localparam CYAN      = 	12'haaa;  
localparam ROYAL     = 	12'hFF0;  
      
always@(posedge clk or negedge rst_n)
begin
	if(!rst_n)
		vga_data <= 12'h0;
	else
		begin
		if	(vga_xpos >= 0 && vga_xpos < (H_DISP>>3))
			vga_data <= RED;
		else if(vga_xpos >= (H_DISP>>3)*1 && vga_xpos < (H_DISP>>3)*2)
			vga_data <= GREEN;
		else if(vga_xpos >= (H_DISP>>3)*2 && vga_xpos < (H_DISP>>3)*3)
			vga_data <= BLUE;
		else if(vga_xpos >= (H_DISP>>3)*3 && vga_xpos < (H_DISP>>3)*4)
			vga_data <= WHITE;
		else if(vga_xpos >= (H_DISP>>3)*4 && vga_xpos < (H_DISP>>3)*5)
			vga_data <= BLACK;
		else if(vga_xpos >= (H_DISP>>3)*5 && vga_xpos < (H_DISP>>3)*6)
			vga_data <= YELLOW;
		else if(vga_xpos >= (H_DISP>>3)*6 && vga_xpos < (H_DISP>>3)*7)
			vga_data <= CYAN;
		else// if(vga_xpos >= (H_DISP<<3)*7 && vga_xpos < (H_DISP<<3)*8)
			vga_data <= ROYAL;
		end
end

//wire	[19:0]	vga_result = vga_xpos * vga_ypos;
//always@(posedge clk or negedge rst_n)
//begin
//	if(!rst_n)
//		vga_data <= 16'h0;
//	else
//		vga_data = vga_result[15:0];
//end


endmodule

VGA_test/my_vga_test/src/time_divider_advanced.v
`timescale 1ns/1ps
/***************************************
晶振频率 fc = 100MHz
输出频率 fo = 1kHz（根据需要可以设为任意值）
控制参数 K  = (fo*2^N)/fc = 2791728742
参数 N = 2^32,(32为计数器的位宽)
****************************************/
module div(
    input clk,
    input rst,
    output reg clk_out
    );

    reg [31:0] cnt;

always @(posedge clk or posedge rst) 
    if(rst)
        cnt <= 0;
    else
        cnt <= cnt + 32'd1073741824;  //计数器步长K

always @(posedge clk or posedge rst)
    if(rst)
        clk_out <= 1'b0;
    else if(cnt < 32'h7FFF_FFFF)
        clk_out <= 1'b0;
    else
        clk_out <= 1'b1;

endmodule

VGA_test/my_vga_test/src/top.v
module top (
    input 			clk, //外部时钟
	input 			rst_n, //低电平复位信号
	
	//vga interface
	output			vga_adv_clk, 
	output			vga_blank_n, 
	output			vga_sync_n,
	
	output			vga_hs,    
	output			vga_vs,    
	output	[11:0]	vga_rgb
);
    wire	clk_vga;
    wire	sys_rst_n;
    assign	vga_adv_clk	=	~clk_vga;
    assign	vga_blank_n = 	1'b1;		
    assign	vga_sync_n 	= 	1'b0;	
    // `define	VGA_1024_768_60FPS_65MHz 
    `define VGA_640_480_60FPS_25MHz
`ifdef	VGA_640_480_60FPS_25MHz
	parameter	DUTY_CYCLE		=	50;
	parameter	DIVIDE_DATA		=	2;
	parameter	MULTIPLY_DATA	=	1;
	parameter	H_DISP	=	11'd640;
	parameter	H_FRONT	=	11'd16; 
	parameter	H_SYNC 	=	11'd96;  
	parameter	H_BACK 	=	11'd48;   
	parameter	H_TOTAL	=	11'd800; 	
	parameter	V_DISP 	=	10'd480;  					
	parameter	V_FRONT	=	10'd10;  
	parameter	V_SYNC 	=	10'd2;   
	parameter	V_BACK 	=	10'd33;   
	parameter	V_TOTAL	=	10'd525;
`endif
	
`ifdef VGA_800_600_72FPS_50MHz
	parameter	DUTY_CYCLE		=	50;
	parameter	DIVIDE_DATA		=	1;
	parameter	MULTIPLY_DATA	=	1;
	parameter	H_DISP 	=	11'd800; 
	parameter	H_FRONT	=	11'd56; 
	parameter	H_SYNC 	=	11'd120;  
	parameter	H_BACK 	=	11'd64;  
	parameter	H_TOTAL	=	11'd1040; 
	parameter	V_DISP 	=	10'd600; 					
	parameter	V_FRONT	=	10'd37;  
	parameter	V_SYNC 	=	10'd6;   
	parameter	V_BACK 	=	10'd23;   
	parameter	V_TOTAL	=	10'd666;
`endif
	
`ifdef	VGA_1024_768_60FPS_65MHz
	parameter	DUTY_CYCLE		=	50;
	parameter	DIVIDE_DATA		=	10;
	parameter	MULTIPLY_DATA	=	13;
	parameter	H_DISP 	=	11'd1024; 
	parameter	H_FRONT	=	11'd24;	 
	parameter	H_SYNC 	=	11'd136;  
	parameter	H_BACK 	=	11'd160;   
	parameter	H_TOTAL	=	11'd1344; 
	parameter	V_DISP 	=	10'd768; 					
	parameter	V_FRONT	=	10'd3; 
	parameter	V_SYNC 	=	10'd6;    
	parameter	V_BACK 	=	10'd29;   
	parameter	V_TOTAL	=	10'd806;
`endif
//-----------------------------
//vga display instantiation
    wire	[9:0]	vga_xpos;
    wire	[9:0]	vga_ypos;
    wire	[11:0]	vga_data;
//generate clock of 65MHz for vga
div div_inst(.clk(clk),.rst(~rst_n),.clk_out(clk_vga));
//generate vga data based on the pos data
vga_display 
#(
	.H_DISP 	(H_DISP),
	.V_DISP 	(V_DISP) 
)
vga_display_inst
(
	.clk		(clk_vga), 
	.rst_n		(rst_n), 

	.vga_xpos	(vga_xpos), 
	.vga_ypos	(vga_ypos),
	.vga_data	(vga_data)
);

//----------------------------
//vga driver instantiation
vga_driver
#
(
	.H_DISP 	(H_DISP), 	
	.H_FRONT	(H_FRONT),	
	.H_SYNC 	(H_SYNC), 	
	.H_BACK 	(H_BACK), 	
	.H_TOTAL	(H_TOTAL),	
	.V_DISP 	(V_DISP), 					
	.V_FRONT	(V_FRONT),	 
	.V_SYNC 	(V_SYNC), 	
	.V_BACK 	(V_BACK), 	
	.V_TOTAL	(V_TOTAL)
)
vga_driver_inst
(  	
	.clk_vga	(clk_vga),	
	.rst_n		(rst_n),     
	
	.vga_data	(vga_data),
	.vga_rgb	(vga_rgb),	
	.vga_hs		(vga_hs),	
	.vga_vs		(vga_vs),	
	
	.vga_xpos	(vga_xpos),	
	.vga_ypos	(vga_ypos)	
);
endmodule

VGA_test/my_vga_test/src/top_tb.v
module top_tb (
);
    reg 			clk; //外部时钟
    reg 			rst_n; //低电平复位信号
    //vga interface
    wire			vga_adv_clk; 
    wire			vga_blank_n; 
    wire			vga_sync_n;
    wire			vga_hs;    
    wire			vga_vs;    
    wire	[11:0]	vga_rgb;
    top inst(
        .clk(clk),
        .rst_n(rst_n),
        .vga_adv_clk(vga_adv_clk),
        .vga_blank_n(vga_blank_n),
        .vga_sync_n(vga_sync_n),
        .vga_hs(vga_hs),
        .vga_vs(vga_vs),
        .vga_rgb(vga_rgb)
        );
    initial	begin
        clk=0;
        rst_n=1;
        #5
        rst_n=0;
        #5
        rst_n=1;
    end
    integer i;
    initial begin
        for (i = 0;i<100 ;i=i+1 ) begin
            #5
            clk=0;
            #5
            clk=1;
        end
    end
    initial begin
        $dumpfile("./build/wave.vcd");  // 指定VCD文件的名字为wave.vcd，仿真信息将记录到此文件
        $dumpvars(0, top_tb);  // 指定层次数为0，则tb_code 模块及其下面各层次的所有信号将被记录
        #10000 $finish;
    end
endmodule

VGA_test/my_vga_test/build/wave.vcd
$date
	Sat Jan  1 15:58:04 2022
$end
$version
	Icarus Verilog
$end
$timescale
	1ps
$end
$scope module top_tb $end
$var wire 1 ! vga_blank_n $end
$var wire 1 " vga_sync_n $end
$var wire 1 # vga_vs $end
$var wire 12 $ vga_rgb [11:0] $end
$var wire 1 % vga_hs $end
$var wire 1 & vga_adv_clk $end
$var reg 1 ' clk $end
$var reg 1 ( rst_n $end
$var integer 32 ) i [31:0] $end
$scope module inst $end
$var wire 1 ' clk $end
$var wire 1 ( rst_n $end
$var wire 1 & vga_adv_clk $end
$var wire 1 ! vga_blank_n $end
$var wire 1 " vga_sync_n $end
$var wire 10 * vga_ypos [9:0] $end
$var wire 10 + vga_xpos [9:0] $end
$var wire 1 # vga_vs $end
$var wire 12 , vga_rgb [11:0] $end
$var wire 1 % vga_hs $end
$var wire 12 - vga_data [11:0] $end
$var wire 1 . clk_vga $end
$scope module div_inst $end
$var wire 1 ' clk $end
$var wire 1 / rst $end
$var reg 1 . clk_out $end
$var reg 32 0 cnt [31:0] $end
$upscope $end
$scope module vga_display_inst $end
$var wire 1 . clk $end
$var wire 1 ( rst_n $end
$var wire 10 1 vga_ypos [9:0] $end
$var wire 10 2 vga_xpos [9:0] $end
$var reg 12 3 vga_data [11:0] $end
$upscope $end
$scope module vga_driver_inst $end
$var wire 1 . clk_vga $end
$var wire 1 ( rst_n $end
$var wire 12 4 vga_data [11:0] $end
$var wire 10 5 vga_ypos [9:0] $end
$var wire 10 6 vga_xpos [9:0] $end
$var wire 12 7 vga_rgb [11:0] $end
$var reg 11 8 hcnt [10:0] $end
$var reg 10 9 vcnt [9:0] $end
$var reg 1 % vga_hs $end
$var reg 1 # vga_vs $end
$upscope $end
$upscope $end
$upscope $end
$enddefinitions $end
#0
$dumpvars
bx 9
bx 8
bx 7
bx 6
bx 5
bx 4
bx 3
bx 2
bx 1
bx 0
0/
x.
bx -
bx ,
bx +
bx *
b0 )
1(
0'
x&
x%
bx $
x#
0"
1!
$end
#5000
1&
b0 $
b0 ,
b0 7
b1 +
b1 2
b1 6
b1 *
b1 1
b1 5
b0 0
0.
b0 -
b0 3
b0 4
b0 8
1%
b0 9
1#
1/
0(
#10000
b10100110011001100110011001100110 0
0/
b1 )
1'
1(
#15000
0'
#20000
b10 +
b10 2
b10 6
b111100000000 $
b111100000000 ,
b111100000000 7
b1 8
b111100000000 -
b111100000000 3
b111100000000 4
0&
b1001100110011001100110011001100 0
1.
b10 )
1'
#25000
0'
#30000
1&
0.
b11110011001100110011001100110010 0
b11 )
1'
#35000
0'
#40000
b11 +
b11 2
b11 6
b10 8
0&
b10011001100110011001100110011000 0
1.
b100 )
1'
#45000
0'
#50000
b111111111111111111111111111110 0
b101 )
1'
#55000
0'
#60000
1&
b11100110011001100110011001100100 0
0.
b110 )
1'
#65000
0'
#70000
b100 +
b100 2
b100 6
b11 8
0&
1.
b10001100110011001100110011001010 0
b111 )
1'
#75000
0'
#80000
b110011001100110011001100110000 0
b1000 )
1'
#85000
0'
#90000
1&
0.
b11011001100110011001100110010110 0
b1001 )
1'
#95000
0'
#100000
b101 +
b101 2
b101 6
b100 8
0&
b1111111111111111111111111111100 0
1.
b1010 )
1'
#105000
0'
#110000
1&
0.
b100110011001100110011001100010 0
b1011 )
1'
#115000
0'
#120000
b11001100110011001100110011001000 0
b1100 )
1'
#125000
0'
#130000
b110 +
b110 2
b110 6
b101 8
0&
1.
b1110011001100110011001100101110 0
b1101 )
1'
#135000
0'
#140000
1&
b11001100110011001100110010100 0
0.
b1110 )
1'
#145000
0'
#150000
b10111111111111111111111111111010 0
b1111 )
1'
#155000
0'
#160000
b111 +
b111 2
b111 6
b110 8
0&
b1100110011001100110011001100000 0
1.
b10000 )
1'
#165000
0'
#170000
1&
0.
b1100110011001100110011000110 0
b10001 )
1'
#175000
0'
#180000
b10110011001100110011001100101100 0
b10010 )
1'
#185000
0'
#190000
b1000 +
b1000 2
b1000 6
b111 8
0&
1.
b1011001100110011001100110010010 0
b10011 )
1'
#195000
0'
#200000
1&
b11111111111111111111111111111000 0
0.
b10100 )
1'
#205000
0'
#210000
b1001 +
b1001 2
b1001 6
b1000 8
0&
1.
b10100110011001100110011001011110 0
b10101 )
1'
#215000
0'
#220000
b1001100110011001100110011000100 0
b10110 )
1'
#225000
0'
#230000
1&
0.
b11110011001100110011001100101010 0
b10111 )
1'
#235000
0'
#240000
b1010 +
b1010 2
b1010 6
b1001 8
0&
b10011001100110011001100110010000 0
1.
b11000 )
1'
#245000
0'
#250000
b111111111111111111111111110110 0
b11001 )
1'
#255000
0'
#260000
1&
b11100110011001100110011001011100 0
0.
b11010 )
1'
#265000
0'
#270000
b1011 +
b1011 2
b1011 6
b1010 8
0&
1.
b10001100110011001100110011000010 0
b11011 )
1'
#275000
0'
#280000
b110011001100110011001100101000 0
b11100 )
1'
#285000
0'
#290000
1&
0.
b11011001100110011001100110001110 0
b11101 )
1'
#295000
0'
#300000
b1100 +
b1100 2
b1100 6
b1011 8
0&
b1111111111111111111111111110100 0
1.
b11110 )
1'
#305000
0'
#310000
1&
0.
b100110011001100110011001011010 0
b11111 )
1'
#315000
0'
#320000
b11001100110011001100110011000000 0
b100000 )
1'
#325000
0'
#330000
b1101 +
b1101 2
b1101 6
b1100 8
0&
1.
b1110011001100110011001100100110 0
b100001 )
1'
#335000
0'
#340000
1&
b11001100110011001100110001100 0
0.
b100010 )
1'
#345000
0'
#350000
b10111111111111111111111111110010 0
b100011 )
1'
#355000
0'
#360000
b1110 +
b1110 2
b1110 6
b1101 8
0&
b1100110011001100110011001011000 0
1.
b100100 )
1'
#365000
0'
#370000
1&
0.
b1100110011001100110010111110 0
b100101 )
1'
#375000
0'
#380000
b10110011001100110011001100100100 0
b100110 )
1'
#385000
0'
#390000
b1111 +
b1111 2
b1111 6
b1110 8
0&
1.
b1011001100110011001100110001010 0
b100111 )
1'
#395000
0'
#400000
1&
b11111111111111111111111111110000 0
0.
b101000 )
1'
#405000
0'
#410000
b10000 +
b10000 2
b10000 6
b1111 8
0&
1.
b10100110011001100110011001010110 0
b101001 )
1'
#415000
0'
#420000
b1001100110011001100110010111100 0
b101010 )
1'
#425000
0'
#430000
1&
0.
b11110011001100110011001100100010 0
b101011 )
1'
#435000
0'
#440000
b10001 +
b10001 2
b10001 6
b10000 8
0&
b10011001100110011001100110001000 0
1.
b101100 )
1'
#445000
0'
#450000
b111111111111111111111111101110 0
b101101 )
1'
#455000
0'
#460000
1&
b11100110011001100110011001010100 0
0.
b101110 )
1'
#465000
0'
#470000
b10010 +
b10010 2
b10010 6
b10001 8
0&
1.
b10001100110011001100110010111010 0
b101111 )
1'
#475000
0'
#480000
b110011001100110011001100100000 0
b110000 )
1'
#485000
0'
#490000
1&
0.
b11011001100110011001100110000110 0
b110001 )
1'
#495000
0'
#500000
b10011 +
b10011 2
b10011 6
b10010 8
0&
b1111111111111111111111111101100 0
1.
b110010 )
1'
#505000
0'
#510000
1&
0.
b100110011001100110011001010010 0
b110011 )
1'
#515000
0'
#520000
b11001100110011001100110010111000 0
b110100 )
1'
#525000
0'
#530000
b10100 +
b10100 2
b10100 6
b10011 8
0&
1.
b1110011001100110011001100011110 0
b110101 )
1'
#535000
0'
#540000
1&
b11001100110011001100110000100 0
0.
b110110 )
1'
#545000
0'
#550000
b10111111111111111111111111101010 0
b110111 )
1'
#555000
0'
#560000
b10101 +
b10101 2
b10101 6
b10100 8
0&
b1100110011001100110011001010000 0
1.
b111000 )
1'
#565000
0'
#570000
1&
0.
b1100110011001100110010110110 0
b111001 )
1'
#575000
0'
#580000
b10110011001100110011001100011100 0
b111010 )
1'
#585000
0'
#590000
b10110 +
b10110 2
b10110 6
b10101 8
0&
1.
b1011001100110011001100110000010 0
b111011 )
1'
#595000
0'
#600000
1&
b11111111111111111111111111101000 0
0.
b111100 )
1'
#605000
0'
#610000
b10111 +
b10111 2
b10111 6
b10110 8
0&
1.
b10100110011001100110011001001110 0
b111101 )
1'
#615000
0'
#620000
b1001100110011001100110010110100 0
b111110 )
1'
#625000
0'
#630000
1&
0.
b11110011001100110011001100011010 0
b111111 )
1'
#635000
0'
#640000
b11000 +
b11000 2
b11000 6
b10111 8
0&
b10011001100110011001100110000000 0
1.
b1000000 )
1'
#645000
0'
#650000
b111111111111111111111111100110 0
b1000001 )
1'
#655000
0'
#660000
1&
b11100110011001100110011001001100 0
0.
b1000010 )
1'
#665000
0'
#670000
b11001 +
b11001 2
b11001 6
b11000 8
0&
1.
b10001100110011001100110010110010 0
b1000011 )
1'
#675000
0'
#680000
b110011001100110011001100011000 0
b1000100 )
1'
#685000
0'
#690000
1&
0.
b11011001100110011001100101111110 0
b1000101 )
1'
#695000
0'
#700000
b11010 +
b11010 2
b11010 6
b11001 8
0&
b1111111111111111111111111100100 0
1.
b1000110 )
1'
#705000
0'
#710000
1&
0.
b100110011001100110011001001010 0
b1000111 )
1'
#715000
0'
#720000
b11001100110011001100110010110000 0
b1001000 )
1'
#725000
0'
#730000
b11011 +
b11011 2
b11011 6
b11010 8
0&
1.
b1110011001100110011001100010110 0
b1001001 )
1'
#735000
0'
#740000
1&
b11001100110011001100101111100 0
0.
b1001010 )
1'
#745000
0'
#750000
b10111111111111111111111111100010 0
b1001011 )
1'
#755000
0'
#760000
b11100 +
b11100 2
b11100 6
b11011 8
0&
b1100110011001100110011001001000 0
1.
b1001100 )
1'
#765000
0'
#770000
1&
0.
b1100110011001100110010101110 0
b1001101 )
1'
#775000
0'
#780000
b10110011001100110011001100010100 0
b1001110 )
1'
#785000
0'
#790000
b11101 +
b11101 2
b11101 6
b11100 8
0&
1.
b1011001100110011001100101111010 0
b1001111 )
1'
#795000
0'
#800000
1&
b11111111111111111111111111100000 0
0.
b1010000 )
1'
#805000
0'
#810000
b11110 +
b11110 2
b11110 6
b11101 8
0&
1.
b10100110011001100110011001000110 0
b1010001 )
1'
#815000
0'
#820000
b1001100110011001100110010101100 0
b1010010 )
1'
#825000
0'
#830000
1&
0.
b11110011001100110011001100010010 0
b1010011 )
1'
#835000
0'
#840000
b11111 +
b11111 2
b11111 6
b11110 8
0&
b10011001100110011001100101111000 0
1.
b1010100 )
1'
#845000
0'
#850000
b111111111111111111111111011110 0
b1010101 )
1'
#855000
0'
#860000
1&
b11100110011001100110011001000100 0
0.
b1010110 )
1'
#865000
0'
#870000
b100000 +
b100000 2
b100000 6
b11111 8
0&
1.
b10001100110011001100110010101010 0
b1010111 )
1'
#875000
0'
#880000
b110011001100110011001100010000 0
b1011000 )
1'
#885000
0'
#890000
1&
0.
b11011001100110011001100101110110 0
b1011001 )
1'
#895000
0'
#900000
b100001 +
b100001 2
b100001 6
b100000 8
0&
b1111111111111111111111111011100 0
1.
b1011010 )
1'
#905000
0'
#910000
1&
0.
b100110011001100110011001000010 0
b1011011 )
1'
#915000
0'
#920000
b11001100110011001100110010101000 0
b1011100 )
1'
#925000
0'
#930000
b100010 +
b100010 2
b100010 6
b100001 8
0&
1.
b1110011001100110011001100001110 0
b1011101 )
1'
#935000
0'
#940000
1&
b11001100110011001100101110100 0
0.
b1011110 )
1'
#945000
0'
#950000
b10111111111111111111111111011010 0
b1011111 )
1'
#955000
0'
#960000
b100011 +
b100011 2
b100011 6
b100010 8
0&
b1100110011001100110011001000000 0
1.
b1100000 )
1'
#965000
0'
#970000
1&
0.
b1100110011001100110010100110 0
b1100001 )
1'
#975000
0'
#980000
b10110011001100110011001100001100 0
b1100010 )
1'
#985000
0'
#990000
b100100 +
b100100 2
b100100 6
b100011 8
0&
1.
b1011001100110011001100101110010 0
b1100011 )
1'
#995000
0'
#1000000
1&
b11111111111111111111111111011000 0
0.
b1100100 )
1'
