kb_controller/src/kb_driver.v
module kb_driver1
(
    //control signals
    // input i_clk, //clock for driver
    input i_rst_n, //reset when signal is low
    //ps 2 interface
    input i_data, //ps2 data,lowest bit first
    input i_sclk, //ps2 clk,use negedge to trigger
    //driver interface
    output o_done,//high for a clk cycle, signaling a Byte of data is received
    output reg [7:0]o_frame_data //the datared
);
    //registers definitions
    reg [3:0] read_cnt; //counter of the clk
    
    //combinational circuits
    assign o_done=(read_cnt>=4'd9)?4'b1:4'b0;

    always @(negedge i_sclk or i_rst_n) begin
        if(!i_rst_n) begin
            read_cnt <= 4'b0;
            o_frame_data <= 8'b0;
        end
        else begin
            if(read_cnt==4'b0)begin
                //start flag
                if(i_data==0) begin
                    read_cnt<=read_cnt+4'b1;
                end
            end
            else if(read_cnt>=4'b1&&read_cnt<=4'd8)begin
                //data frame
                o_frame_data[read_cnt-4'b1]=i_data;
                read_cnt<=read_cnt+4'b1;
            end
            else begin
                //reset when read is done
                read_cnt<=4'b0;
            end
        end
    end
endmodule

kb_controller/src/kb_driver_tb.v
module kb_driver1_tb ();
    reg i_rst_n; //reset when signal is low
    //ps 2 interface
    reg i_data; //ps2 data;lowest bit first
    reg i_sclk; //ps2 clk;use negedge to trigger
    //driver interface
    wire o_done;//high for a clk cycle; signaling a Byte of data is received
    wire [7:0]o_frame_data; //the datared
    
    //initialize
    initial begin
        i_sclk=1;
        i_data=0;
        //reset
        i_rst_n=1;
        #5
        i_rst_n=0;
        #5
        i_rst_n=1;
    end
    //test start
    integer i;
    initial begin
        for (i=0;i<100 ;i=i+1)begin
            #5
            i_sclk=0;
            #5
            i_sclk=1;
            if(i>=20 && i<=23) begin
                i_data=1;
            end
            else if(i>=25&&i<=27)begin
                i_data=0;
            end
        end
    end
    //implementation
    kb_driver1 inst(
        .i_rst_n(i_rst_n),
        .i_data(i_data),
        .i_sclk(i_sclk),
        .o_done(o_done),
        .o_frame_data(o_frame_data)
    );
    initial begin   
        $dumpfile("./build/wave.vcd");  // 指定VCD文件的名字为wave.vcd，仿真信息将记录到此文件
        $dumpvars(0, kb_driver1_tb);  // 指定层次数为0，则tb_code 模块及其下面各层次的所有信号将被记录
        #10000 $finish;
    end
endmodule

kb_controller/build/wave.vcd
$date
	Sun Jan  2 14:46:22 2022
$end
$version
	Icarus Verilog
$end
$timescale
	1s
$end
$scope module kb_driver1_tb $end
$var wire 8 ! o_frame_data [7:0] $end
$var wire 1 " o_done $end
$var reg 1 # i_data $end
$var reg 1 $ i_rst_n $end
$var reg 1 % i_sclk $end
$var integer 32 & i [31:0] $end
$scope module inst $end
$var wire 1 # i_data $end
$var wire 1 $ i_rst_n $end
$var wire 1 % i_sclk $end
$var wire 1 " o_done $end
$var reg 8 ' o_frame_data [7:0] $end
$var reg 4 ( read_cnt [3:0] $end
$upscope $end
$upscope $end
$enddefinitions $end
#0
$dumpvars
b0 (
bx '
b0 &
1%
1$
0#
0"
bx !
$end
#5
b0 !
b0 '
0%
0$
#10
b1 (
b1 &
1%
1$
#15
b10 (
0%
#20
b10 &
1%
#25
b11 (
0%
#30
b11 &
1%
#35
b100 (
0%
#40
b100 &
1%
#45
b101 (
0%
#50
b101 &
1%
#55
b110 (
0%
#60
b110 &
1%
#65
b111 (
0%
#70
b111 &
1%
#75
b1000 (
0%
#80
b1000 &
1%
#85
1"
b1001 (
0%
#90
b1001 &
1%
#95
0"
b0 (
0%
#100
b1010 &
1%
#105
b1 (
0%
#110
b1011 &
1%
#115
b10 (
0%
#120
b1100 &
1%
#125
b11 (
0%
#130
b1101 &
1%
#135
b100 (
0%
#140
b1110 &
1%
#145
b101 (
0%
#150
b1111 &
1%
#155
b110 (
0%
#160
b10000 &
1%
#165
b111 (
0%
#170
b10001 &
1%
#175
b1000 (
0%
#180
b10010 &
1%
#185
1"
b1001 (
0%
#190
b10011 &
1%
#195
0"
b0 (
0%
#200
b10100 &
1%
#205
b1 (
0%
#210
b10101 &
1#
1%
#215
b10 (
b1 !
b1 '
0%
#220
b10110 &
1%
#225
b11 (
b11 !
b11 '
0%
#230
b10111 &
1%
#235
b100 (
b111 !
b111 '
0%
#240
b11000 &
1%
#245
b101 (
b1111 !
b1111 '
0%
#250
b11001 &
1%
#255
b110 (
b11111 !
b11111 '
0%
#260
b11010 &
0#
1%
#265
b111 (
0%
#270
b11011 &
1%
#275
b1000 (
0%
#280
b11100 &
1%
#285
1"
b1001 (
0%
#290
b11101 &
1%
#295
0"
b0 (
0%
#300
b11110 &
1%
#305
b1 (
0%
#310
b11111 &
1%
#315
b10 (
b11110 !
b11110 '
0%
#320
b100000 &
1%
#325
b11 (
b11100 !
b11100 '
0%
#330
b100001 &
1%
#335
b100 (
b11000 !
b11000 '
0%
#340
b100010 &
1%
#345
b101 (
b10000 !
b10000 '
0%
#350
b100011 &
1%
#355
b110 (
b0 !
b0 '
0%
#360
b100100 &
1%
#365
b111 (
0%
#370
b100101 &
1%
#375
b1000 (
0%
#380
b100110 &
1%
#385
1"
b1001 (
0%
#390
b100111 &
1%
#395
0"
b0 (
0%
#400
b101000 &
1%
#405
b1 (
0%
#410
b101001 &
1%
#415
b10 (
0%
#420
b101010 &
1%
#425
b11 (
0%
#430
b101011 &
1%
#435
b100 (
0%
#440
b101100 &
1%
#445
b101 (
0%
#450
b101101 &
1%
#455
b110 (
0%
#460
b101110 &
1%
#465
b111 (
0%
#470
b101111 &
1%
#475
b1000 (
0%
#480
b110000 &
1%
#485
1"
b1001 (
0%
#490
b110001 &
1%
#495
0"
b0 (
0%
#500
b110010 &
1%
#505
b1 (
0%
#510
b110011 &
1%
#515
b10 (
0%
#520
b110100 &
1%
#525
b11 (
0%
#530
b110101 &
1%
#535
b100 (
0%
#540
b110110 &
1%
#545
b101 (
0%
#550
b110111 &
1%
#555
b110 (
0%
#560
b111000 &
1%
#565
b111 (
0%
#570
b111001 &
1%
#575
b1000 (
0%
#580
b111010 &
1%
#585
1"
b1001 (
0%
#590
b111011 &
1%
#595
0"
b0 (
0%
#600
b111100 &
1%
#605
b1 (
0%
#610
b111101 &
1%
#615
b10 (
0%
#620
b111110 &
1%
#625
b11 (
0%
#630
b111111 &
1%
#635
b100 (
0%
#640
b1000000 &
1%
#645
b101 (
0%
#650
b1000001 &
1%
#655
b110 (
0%
#660
b1000010 &
1%
#665
b111 (
0%
#670
b1000011 &
1%
#675
b1000 (
0%
#680
b1000100 &
1%
#685
1"
b1001 (
0%
#690
b1000101 &
1%
#695
0"
b0 (
0%
#700
b1000110 &
1%
#705
b1 (
0%
#710
b1000111 &
1%
#715
b10 (
0%
#720
b1001000 &
1%
#725
b11 (
0%
#730
b1001001 &
1%
#735
b100 (
0%
#740
b1001010 &
1%
#745
b101 (
0%
#750
b1001011 &
1%
#755
b110 (
0%
#760
b1001100 &
1%
#765
b111 (
0%
#770
b1001101 &
1%
#775
b1000 (
0%
#780
b1001110 &
1%
#785
1"
b1001 (
0%
#790
b1001111 &
1%
#795
0"
b0 (
0%
#800
b1010000 &
1%
#805
b1 (
0%
#810
b1010001 &
1%
#815
b10 (
0%
#820
b1010010 &
1%
#825
b11 (
0%
#830
b1010011 &
1%
#835
b100 (
0%
#840
b1010100 &
1%
#845
b101 (
0%
#850
b1010101 &
1%
#855
b110 (
0%
#860
b1010110 &
1%
#865
b111 (
0%
#870
b1010111 &
1%
#875
b1000 (
0%
#880
b1011000 &
1%
#885
1"
b1001 (
0%
#890
b1011001 &
1%
#895
0"
b0 (
0%
#900
b1011010 &
1%
#905
b1 (
0%
#910
b1011011 &
1%
#915
b10 (
0%
#920
b1011100 &
1%
#925
b11 (
0%
#930
b1011101 &
1%
#935
b100 (
0%
#940
b1011110 &
1%
#945
b101 (
0%
#950
b1011111 &
1%
#955
b110 (
0%
#960
b1100000 &
1%
#965
b111 (
0%
#970
b1100001 &
1%
#975
b1000 (
0%
#980
b1100010 &
1%
#985
1"
b1001 (
0%
#990
b1100011 &
1%
#995
0"
b0 (
0%
#1000
b1100100 &
1%
