counter_overflow/src/counter_overflow.v
//一个递增计数器，达到指定的上限会置高溢出信号并停止计时
module counter_overflow
#(parameter COUNTER_BITS=32) //计数器位数
(
    input i_CLK, //输入时钟信号
    input [COUNTER_BITS-1:0] i_LIM, //上限
    input i_RST, //异步复位信号，上升沿有效
    output reg o_OVERFLOW //若超过上限，维持高电平
);
    reg [COUNTER_BITS-1:0] c;
    initial begin
        c=0; //clear
        o_OVERFLOW=0;
    end
    //异步复位
    always @(posedge i_RST) begin
        c=0;
        o_OVERFLOW=0;
    end
    always @(posedge i_CLK) begin
        if(o_OVERFLOW==0) begin
            c=c+1;
            if(c==i_LIM) begin
                o_OVERFLOW=1;
            end
            else begin
                o_OVERFLOW=0;
            end
        end
        else begin
            c={COUNTER_BITS{1'bz}};
        end
    end
endmodule

counter_overflow/src/counter_overflow_tb.v
module counter_overflow_tb 
#(parameter COUNTER_BITS=32)
(
);
reg i_CLK; //输入时钟信号
reg [COUNTER_BITS-1:0] i_LIM; //上限
reg i_RST; //异步复位信号，上升沿有效
wire o_OVERFLOW; //若超过上限，维持高电平
    initial begin   
        $dumpfile("./build/wave.vcd");  // 指定VCD文件的名字为wave.vcd，仿真信息将记录到此文件
        $dumpvars(0, counter_overflow_tb);  // 指定层次数为0，则tb_code 模块及其下面各层次的所有信号将被记录
        #10000 $finish;
    end
    counter_overflow cnt(.i_CLK(i_CLK),.i_LIM(i_LIM),.i_RST(i_RST),.o_OVERFLOW(o_OVERFLOW));
    initial begin
        i_RST<=0; //归零复位信号
        i_CLK<=0;
        i_LIM=5;
    end
    integer i;
    initial begin
        //计数测试
        for (i = 0;i<15 ;i=i+1 ) begin
            #5
            i_CLK=~i_CLK;
        end
        //复位测试
        i_RST=1;
        #5
        i_RST=0;
        for (i = 0;i<6 ;i=i+1 ) begin
            #5
            i_CLK=~i_CLK;
        end
        //中部复位测试
        i_RST=1;
        #5
        i_RST=0;
        for (i = 0;i<15 ;i=i+1 ) begin
            #5
            i_CLK=~i_CLK;
        end
    end
endmodule

counter_overflow/build/wave.vcd
$date
	Tue Dec 28 09:57:26 2021
$end
$version
	Icarus Verilog
$end
$timescale
	1s
$end
$scope module counter_overflow_tb $end
$var wire 1 ! o_OVERFLOW $end
$var reg 1 " i_CLK $end
$var reg 32 # i_LIM [31:0] $end
$var reg 1 $ i_RST $end
$var integer 32 % i [31:0] $end
$scope module cnt $end
$var wire 1 " i_CLK $end
$var wire 32 & i_LIM [31:0] $end
$var wire 1 $ i_RST $end
$var reg 32 ' c [31:0] $end
$var reg 1 ! o_OVERFLOW $end
$upscope $end
$upscope $end
$enddefinitions $end
#0
$dumpvars
b0 '
b101 &
b0 %
0$
b101 #
0"
0!
$end
#5
b1 '
b1 %
1"
#10
b10 %
0"
#15
b10 '
b11 %
1"
#20
b100 %
0"
#25
b11 '
b101 %
1"
#30
b110 %
0"
#35
b100 '
b111 %
1"
#40
b1000 %
0"
#45
1!
b101 '
b1001 %
1"
#50
b1010 %
0"
#55
bz '
b1011 %
1"
#60
b1100 %
0"
#65
b1101 %
1"
#70
b1110 %
0"
#75
0!
b0 '
1$
b1111 %
1"
#80
b0 %
0$
#85
b1 %
0"
#90
b1 '
b10 %
1"
#95
b11 %
0"
#100
b10 '
b100 %
1"
#105
b101 %
0"
#110
b0 '
1$
b110 %
1"
#115
b0 %
0$
#120
b1 %
0"
#125
b1 '
b10 %
1"
#130
b11 %
0"
#135
b10 '
b100 %
1"
#140
b101 %
0"
#145
b11 '
b110 %
1"
#150
b111 %
0"
#155
b100 '
b1000 %
1"
#160
b1001 %
0"
#165
1!
b101 '
b1010 %
1"
#170
b1011 %
0"
#175
bz '
b1100 %
1"
#180
b1101 %
0"
#185
b1110 %
1"
#190
b1111 %
0"
