program_control_1/src/time_divider.v
module time_divider 
#(parameter ratio=10000000) //分频比 100M=1e8  1e8/100000=1e3HZ->1ms
(
    input i_CLK, //输入时钟信号
    input i_RST, //同步重置信号高电平有效
    output reg o_CLK //输出时钟信号
);
    integer c;
    integer target=ratio/2;
    initial begin
        o_CLK=0;
        c=0;
    end
    always @(posedge i_CLK) begin
        if(i_RST==1) begin
            c=0;
            o_CLK=0;
        end
        else begin
            c=c+1;
        end
        if(c==target) begin
            o_CLK=~o_CLK;
            c=0;
        end
    end
endmodule

program_control_1/src/counter_overflow.v
//一个递增计数器，达到指定的上限会置高溢出信号并停止计时
module counter_overflow
#(parameter COUNTER_BITS=32) //计数器位数
(
    input i_CLK, //输入时钟信号
    input [COUNTER_BITS-1:0] i_LIM, //上限
    input i_RST, //异步复位信号，上升沿有效
    output reg o_OVERFLOW //若超过上限，维持高电平
);
    reg [COUNTER_BITS-1:0] c;
    initial begin
        c=0; //clear
        o_OVERFLOW=0;
    end
    always @(posedge i_CLK or posedge i_RST) begin
        //异步复位
        if(i_RST == 1) begin
            c<=0;
            o_OVERFLOW<=0;
        end
        else begin
            if(o_OVERFLOW==0) begin
                c=c+1;
                if(c>i_LIM) begin
                    o_OVERFLOW<=1;
                end
                else begin
                    o_OVERFLOW<=0;
                end
            end
            // else begin
            //     c<={COUNTER_BITS{1'bz}};
            // end
        end
    end
endmodule

program_control_1/src/program_control_1.v
//本module实现一个能够反复跳变的led
module program_control_1
(
    input i_CLK, //输入时钟信号,上升沿同步
    input i_RST, //同步复位信号
    output reg o_CTR //跳变输出
);
    //基本参数设置
    parameter state_rst=2'b00; //重置计数器
    parameter state_wait=2'b01; //等待计数器溢出
    parameter state_change=2'b10; //修改跳变值
    parameter delay_time=1000; //等待时间参数
    //内部寄存器定义
    reg [1:0]current_state;
    reg counter_reset;
    //内部线网定义
    wire c_overflow;
    wire clk_slow;
    //初始化
    initial begin
        //外部线初始化
        o_CTR=1'b0;
        //内部寄存器初始化
        current_state=2'b00;
        counter_reset=2'b00;
    end
    //组合逻辑
    counter_overflow counter(.i_CLK(clk_slow),.i_LIM(delay_time),.i_RST(counter_reset),.o_OVERFLOW(c_overflow));
    time_divider inst(.i_CLK(i_CLK),.i_RST(1'b0),.o_CLK(clk_slow));
    //时序逻辑
    //主状态机，负责控制状态转换
    always @(posedge clk_slow or negedge clk_slow or posedge i_RST) begin
        //复位信号检测
        if(i_RST==1) begin
            //内部寄存器初始化
            current_state<=2'b00;
            counter_reset<=2'b00;
        end
        //非复位，正常工作
        else begin
            if(clk_slow==1) begin
                //时钟上升沿
                case (current_state)
                    //复位态，复位计数器
                    state_rst:
                    begin
                        counter_reset<=1;
                        current_state <= state_wait;
                    end
                    //等待态，等待overflow
                    state_wait:
                    begin
                        if(c_overflow==1) begin
                            current_state<=state_change;
                        end
                        // else begin
                            
                        // end
                    end
                    state_change:
                    begin
                        // o_CTR<=~o_CTR;
                        current_state<=state_rst;
                    end
                    default:
                    //出现异常，进行复位
                    current_state<=state_rst; 
                endcase
            end
            else begin
                //时钟下降沿
                if(counter_reset==1) begin
                    counter_reset<=0;
                end
                // else begin
                //     // o_CTR<=o_CTR;
                // end
            end
        end
    end
    //输出进行修改
    always @(current_state or i_RST) begin
        if(i_RST==1) begin
            //外部线初始化
            o_CTR<=1'b0;
        end
        else begin
            case (current_state)
                state_change:
                    o_CTR<=~o_CTR; 
            endcase
        end
    end
endmodule

program_control_1/src/program_control_1_tb.v
`timescale 1ps/1ps
module program_control_1_tb (
);
    //引脚定义
    reg i_CLK; //输入时钟信号;上升沿同步
    reg i_RST; //同步复位信号
    wire o_CTR; //跳变输出
    wire o_slow;
    //迭代变量定义
    integer i;
    // program_control_1 pc1(.i_CLK(i_CLK),.i_RST(i_RST),.o_CTR(o_CTR),.clk_slow(o_slow));
    program_control_1 pc1(.i_CLK(i_CLK),.i_RST(i_RST),.o_CTR(o_CTR));
    //复位信号
    initial begin
        i_CLK=0;
        i_RST=1; //进行复位
        i_CLK=1;
        i_CLK=0;
    end
    // 进行test
    initial begin
        #5
        i_RST=0; //复位复位信号，开始正常工作
        for (i = 0;i<10000 ;i=i+1 ) begin
            #5
            i_CLK=~i_CLK;
        end
    end

    // use the top module to test
    // initial begin   
    //     $dumpfile("./build/wave.vcd");  // 指定VCD文件的名字为wave.vcd，仿真信息将记录到此文件
    //     $dumpvars(0, program_control_1_tb);  // 指定层次数为0，则tb_code 模块及其下面各层次的有信号将被记
    //     #100000 $finish;
    // end
endmodule

program_control_1/build/wave.vcd
$date
	Fri Dec 31 17:22:11 2021
$end
$version
	Icarus Verilog
$end
$timescale
	1ps
$end
$scope module program_control_1_tb $end
$var wire 1 ! o_slow $end
$var wire 1 " o_CTR $end
$var reg 1 # i_CLK $end
$var reg 1 $ i_RST $end
$var integer 32 % i [31:0] $end
$scope module pc1 $end
$var wire 1 # i_CLK $end
$var wire 1 $ i_RST $end
$var wire 1 ! clk_slow $end
$var wire 1 & c_overflow $end
$var reg 1 ' counter_reset $end
$var reg 2 ( current_state [1:0] $end
$var reg 1 " o_CTR $end
$scope module counter $end
$var wire 32 ) i_LIM [31:0] $end
$var wire 1 ' i_RST $end
$var wire 1 ! i_CLK $end
$var reg 32 * c [31:0] $end
$var reg 1 & o_OVERFLOW $end
$upscope $end
$scope module inst $end
$var wire 1 # i_CLK $end
$var wire 1 + i_RST $end
$var reg 1 ! o_CLK $end
$var integer 32 , c [31:0] $end
$var integer 32 - target [31:0] $end
$upscope $end
$upscope $end
$upscope $end
$enddefinitions $end
#0
$dumpvars
b1 -
b0 ,
0+
b0 *
b11 )
b0 (
0'
0&
bx %
1$
0#
0"
1!
$end
#5
b0 %
0$
#10
0!
b0 ,
b1 %
1#
#15
b10 %
0#
#20
b1 (
1'
b0 *
1!
b0 ,
b11 %
1#
#25
b100 %
0#
#30
0'
0!
b0 ,
b101 %
1#
#35
b110 %
0#
#40
b1 *
1!
b0 ,
b111 %
1#
#45
b1000 %
0#
#50
0!
b0 ,
b1001 %
1#
#55
b1010 %
0#
#60
b10 *
1!
b0 ,
b1011 %
1#
#65
b1100 %
0#
#70
0!
b0 ,
b1101 %
1#
#75
b1110 %
0#
#80
b11 *
1!
b0 ,
b1111 %
1#
#85
b10000 %
0#
#90
0!
b0 ,
b10001 %
1#
#95
b10010 %
0#
#100
1&
b100 *
1!
b0 ,
b10011 %
1#
#105
b10100 %
0#
#110
0!
b0 ,
b10101 %
1#
#115
b10110 %
0#
#120
1"
b10 (
1!
b0 ,
b10111 %
1#
#125
b11000 %
0#
#130
0!
b0 ,
b11001 %
1#
#135
b11010 %
0#
#140
b0 (
1!
b0 ,
b11011 %
1#
#145
b11100 %
0#
#150
0!
b0 ,
b11101 %
1#
#155
b11110 %
0#
#160
0&
b0 *
b1 (
1'
1!
b0 ,
b11111 %
1#
#165
b100000 %
0#
#170
0'
0!
b0 ,
b100001 %
1#
#175
b100010 %
0#
#180
b1 *
1!
b0 ,
b100011 %
1#
#185
b100100 %
0#
#190
0!
b0 ,
b100101 %
1#
#195
b100110 %
0#
#200
b10 *
1!
b0 ,
b100111 %
1#
#205
b101000 %
0#
#210
0!
b0 ,
b101001 %
1#
#215
b101010 %
0#
#220
b11 *
1!
b0 ,
b101011 %
1#
#225
b101100 %
0#
#230
0!
b0 ,
b101101 %
1#
#235
b101110 %
0#
#240
1&
b100 *
1!
b0 ,
b101111 %
1#
#245
b110000 %
0#
#250
0!
b0 ,
b110001 %
1#
#255
b110010 %
0#
#260
0"
b10 (
1!
b0 ,
b110011 %
1#
#265
b110100 %
0#
#270
0!
b0 ,
b110101 %
1#
#275
b110110 %
0#
#280
b0 (
1!
b0 ,
b110111 %
1#
#285
b111000 %
0#
#290
0!
b0 ,
b111001 %
1#
#295
b111010 %
0#
#300
0&
b0 *
b1 (
1'
1!
b0 ,
b111011 %
1#
#305
b111100 %
0#
#310
0'
0!
b0 ,
b111101 %
1#
#315
b111110 %
0#
#320
b1 *
1!
b0 ,
b111111 %
1#
#325
b1000000 %
0#
#330
0!
b0 ,
b1000001 %
1#
#335
b1000010 %
0#
#340
b10 *
1!
b0 ,
b1000011 %
1#
#345
b1000100 %
0#
#350
0!
b0 ,
b1000101 %
1#
#355
b1000110 %
0#
#360
b11 *
1!
b0 ,
b1000111 %
1#
#365
b1001000 %
0#
#370
0!
b0 ,
b1001001 %
1#
#375
b1001010 %
0#
#380
1&
b100 *
1!
b0 ,
b1001011 %
1#
#385
b1001100 %
0#
#390
0!
b0 ,
b1001101 %
1#
#395
b1001110 %
0#
#400
1"
b10 (
1!
b0 ,
b1001111 %
1#
#405
b1010000 %
0#
#410
0!
b0 ,
b1010001 %
1#
#415
b1010010 %
0#
#420
b0 (
1!
b0 ,
b1010011 %
1#
#425
b1010100 %
0#
#430
0!
b0 ,
b1010101 %
1#
#435
b1010110 %
0#
#440
0&
b0 *
b1 (
1'
1!
b0 ,
b1010111 %
1#
#445
b1011000 %
0#
#450
0'
0!
b0 ,
b1011001 %
1#
#455
b1011010 %
0#
#460
b1 *
1!
b0 ,
b1011011 %
1#
#465
b1011100 %
0#
#470
0!
b0 ,
b1011101 %
1#
#475
b1011110 %
0#
#480
b10 *
1!
b0 ,
b1011111 %
1#
#485
b1100000 %
0#
#490
0!
b0 ,
b1100001 %
1#
#495
b1100010 %
0#
#500
b11 *
1!
b0 ,
b1100011 %
1#
#505
b1100100 %
0#
#510
0!
b0 ,
b1100101 %
1#
#515
b1100110 %
0#
#520
1&
b100 *
1!
b0 ,
b1100111 %
1#
#525
b1101000 %
0#
#530
0!
b0 ,
b1101001 %
1#
#535
b1101010 %
0#
#540
0"
b10 (
1!
b0 ,
b1101011 %
1#
#545
b1101100 %
0#
#550
0!
b0 ,
b1101101 %
1#
#555
b1101110 %
0#
#560
b0 (
1!
b0 ,
b1101111 %
1#
#565
b1110000 %
0#
#570
0!
b0 ,
b1110001 %
1#
#575
b1110010 %
0#
#580
0&
b0 *
b1 (
1'
1!
b0 ,
b1110011 %
1#
#585
b1110100 %
0#
#590
0'
0!
b0 ,
b1110101 %
1#
#595
b1110110 %
0#
#600
b1 *
1!
b0 ,
b1110111 %
1#
#605
b1111000 %
0#
#610
0!
b0 ,
b1111001 %
1#
#615
b1111010 %
0#
#620
b10 *
1!
b0 ,
b1111011 %
1#
#625
b1111100 %
0#
#630
0!
b0 ,
b1111101 %
1#
#635
b1111110 %
0#
#640
b11 *
1!
b0 ,
b1111111 %
1#
#645
b10000000 %
0#
#650
0!
b0 ,
b10000001 %
1#
#655
b10000010 %
0#
#660
1&
b100 *
1!
b0 ,
b10000011 %
1#
#665
b10000100 %
0#
#670
0!
b0 ,
b10000101 %
1#
#675
b10000110 %
0#
#680
1"
b10 (
1!
b0 ,
b10000111 %
1#
#685
b10001000 %
0#
#690
0!
b0 ,
b10001001 %
1#
#695
b10001010 %
0#
#700
b0 (
1!
b0 ,
b10001011 %
1#
#705
b10001100 %
0#
#710
0!
b0 ,
b10001101 %
1#
#715
b10001110 %
0#
#720
0&
b0 *
b1 (
1'
1!
b0 ,
b10001111 %
1#
#725
b10010000 %
0#
#730
0'
0!
b0 ,
b10010001 %
1#
#735
b10010010 %
0#
#740
b1 *
1!
b0 ,
b10010011 %
1#
#745
b10010100 %
0#
#750
0!
b0 ,
b10010101 %
1#
#755
b10010110 %
0#
#760
b10 *
1!
b0 ,
b10010111 %
1#
#765
b10011000 %
0#
#770
0!
b0 ,
b10011001 %
1#
#775
b10011010 %
0#
#780
b11 *
1!
b0 ,
b10011011 %
1#
#785
b10011100 %
0#
#790
0!
b0 ,
b10011101 %
1#
#795
b10011110 %
0#
#800
1&
b100 *
1!
b0 ,
b10011111 %
1#
#805
b10100000 %
0#
#810
0!
b0 ,
b10100001 %
1#
#815
b10100010 %
0#
#820
0"
b10 (
1!
b0 ,
b10100011 %
1#
#825
b10100100 %
0#
#830
0!
b0 ,
b10100101 %
1#
#835
b10100110 %
0#
#840
b0 (
1!
b0 ,
b10100111 %
1#
#845
b10101000 %
0#
#850
0!
b0 ,
b10101001 %
1#
#855
b10101010 %
0#
#860
0&
b0 *
b1 (
1'
1!
b0 ,
b10101011 %
1#
#865
b10101100 %
0#
#870
0'
0!
b0 ,
b10101101 %
1#
#875
b10101110 %
0#
#880
b1 *
1!
b0 ,
b10101111 %
1#
#885
b10110000 %
0#
#890
0!
b0 ,
b10110001 %
1#
#895
b10110010 %
0#
#900
b10 *
1!
b0 ,
b10110011 %
1#
#905
b10110100 %
0#
#910
0!
b0 ,
b10110101 %
1#
#915
b10110110 %
0#
#920
b11 *
1!
b0 ,
b10110111 %
1#
#925
b10111000 %
0#
#930
0!
b0 ,
b10111001 %
1#
#935
b10111010 %
0#
#940
1&
b100 *
1!
b0 ,
b10111011 %
1#
#945
b10111100 %
0#
#950
0!
b0 ,
b10111101 %
1#
#955
b10111110 %
0#
#960
1"
b10 (
1!
b0 ,
b10111111 %
1#
#965
b11000000 %
0#
#970
0!
b0 ,
b11000001 %
1#
#975
b11000010 %
0#
#980
b0 (
1!
b0 ,
b11000011 %
1#
#985
b11000100 %
0#
#990
0!
b0 ,
b11000101 %
1#
#995
b11000110 %
0#
#1000
0&
b0 *
b1 (
1'
1!
b0 ,
b11000111 %
1#
#1005
b11001000 %
0#
#1010
0'
0!
b0 ,
b11001001 %
1#
#1015
b11001010 %
0#
#1020
b1 *
1!
b0 ,
b11001011 %
1#
#1025
b11001100 %
0#
#1030
0!
b0 ,
b11001101 %
1#
#1035
b11001110 %
0#
#1040
b10 *
1!
b0 ,
b11001111 %
1#
#1045
b11010000 %
0#
#1050
0!
b0 ,
b11010001 %
1#
#1055
b11010010 %
0#
#1060
b11 *
1!
b0 ,
b11010011 %
1#
#1065
b11010100 %
0#
#1070
0!
b0 ,
b11010101 %
1#
#1075
b11010110 %
0#
#1080
1&
b100 *
1!
b0 ,
b11010111 %
1#
#1085
b11011000 %
0#
#1090
0!
b0 ,
b11011001 %
1#
#1095
b11011010 %
0#
#1100
0"
b10 (
1!
b0 ,
b11011011 %
1#
#1105
b11011100 %
0#
#1110
0!
b0 ,
b11011101 %
1#
#1115
b11011110 %
0#
#1120
b0 (
1!
b0 ,
b11011111 %
1#
#1125
b11100000 %
0#
#1130
0!
b0 ,
b11100001 %
1#
#1135
b11100010 %
0#
#1140
0&
b0 *
b1 (
1'
1!
b0 ,
b11100011 %
1#
#1145
b11100100 %
0#
#1150
0'
0!
b0 ,
b11100101 %
1#
#1155
b11100110 %
0#
#1160
b1 *
1!
b0 ,
b11100111 %
1#
#1165
b11101000 %
0#
#1170
0!
b0 ,
b11101001 %
1#
#1175
b11101010 %
0#
#1180
b10 *
1!
b0 ,
b11101011 %
1#
#1185
b11101100 %
0#
#1190
0!
b0 ,
b11101101 %
1#
#1195
b11101110 %
0#
#1200
b11 *
1!
b0 ,
b11101111 %
1#
#1205
b11110000 %
0#
#1210
0!
b0 ,
b11110001 %
1#
#1215
b11110010 %
0#
#1220
1&
b100 *
1!
b0 ,
b11110011 %
1#
#1225
b11110100 %
0#
#1230
0!
b0 ,
b11110101 %
1#
#1235
b11110110 %
0#
#1240
1"
b10 (
1!
b0 ,
b11110111 %
1#
#1245
b11111000 %
0#
#1250
0!
b0 ,
b11111001 %
1#
#1255
b11111010 %
0#
#1260
b0 (
1!
b0 ,
b11111011 %
1#
#1265
b11111100 %
0#
#1270
0!
b0 ,
b11111101 %
1#
#1275
b11111110 %
0#
#1280
0&
b0 *
b1 (
1'
1!
b0 ,
b11111111 %
1#
#1285
b100000000 %
0#
#1290
0'
0!
b0 ,
b100000001 %
1#
#1295
b100000010 %
0#
#1300
b1 *
1!
b0 ,
b100000011 %
1#
#1305
b100000100 %
0#
#1310
0!
b0 ,
b100000101 %
1#
#1315
b100000110 %
0#
#1320
b10 *
1!
b0 ,
b100000111 %
1#
#1325
b100001000 %
0#
#1330
0!
b0 ,
b100001001 %
1#
#1335
b100001010 %
0#
#1340
b11 *
1!
b0 ,
b100001011 %
1#
#1345
b100001100 %
0#
#1350
0!
b0 ,
b100001101 %
1#
#1355
b100001110 %
0#
#1360
1&
b100 *
1!
b0 ,
b100001111 %
1#
#1365
b100010000 %
0#
#1370
0!
b0 ,
b100010001 %
1#
#1375
b100010010 %
0#
#1380
0"
b10 (
1!
b0 ,
b100010011 %
1#
#1385
b100010100 %
0#
#1390
0!
b0 ,
b100010101 %
1#
#1395
b100010110 %
0#
#1400
b0 (
1!
b0 ,
b100010111 %
1#
#1405
b100011000 %
0#
#1410
0!
b0 ,
b100011001 %
1#
#1415
b100011010 %
0#
#1420
0&
b0 *
b1 (
1'
1!
b0 ,
b100011011 %
1#
#1425
b100011100 %
0#
#1430
0'
0!
b0 ,
b100011101 %
1#
#1435
b100011110 %
0#
#1440
b1 *
1!
b0 ,
b100011111 %
1#
#1445
b100100000 %
0#
#1450
0!
b0 ,
b100100001 %
1#
#1455
b100100010 %
0#
#1460
b10 *
1!
b0 ,
b100100011 %
1#
#1465
b100100100 %
0#
#1470
0!
b0 ,
b100100101 %
1#
#1475
b100100110 %
0#
#1480
b11 *
1!
b0 ,
b100100111 %
1#
#1485
b100101000 %
0#
#1490
0!
b0 ,
b100101001 %
1#
#1495
b100101010 %
0#
#1500
1&
b100 *
1!
b0 ,
b100101011 %
1#
#1505
b100101100 %
0#
#1510
0!
b0 ,
b100101101 %
1#
#1515
b100101110 %
0#
#1520
1"
b10 (
1!
b0 ,
b100101111 %
1#
#1525
b100110000 %
0#
#1530
0!
b0 ,
b100110001 %
1#
#1535
b100110010 %
0#
#1540
b0 (
1!
b0 ,
b100110011 %
1#
#1545
b100110100 %
0#
#1550
0!
b0 ,
b100110101 %
1#
#1555
b100110110 %
0#
#1560
0&
b0 *
b1 (
1'
1!
b0 ,
b100110111 %
1#
#1565
b100111000 %
0#
#1570
0'
0!
b0 ,
b100111001 %
1#
#1575
b100111010 %
0#
#1580
b1 *
1!
b0 ,
b100111011 %
1#
#1585
b100111100 %
0#
#1590
0!
b0 ,
b100111101 %
1#
#1595
b100111110 %
0#
#1600
b10 *
1!
b0 ,
b100111111 %
1#
#1605
b101000000 %
0#
#1610
0!
b0 ,
b101000001 %
1#
#1615
b101000010 %
0#
#1620
b11 *
1!
b0 ,
b101000011 %
1#
#1625
b101000100 %
0#
#1630
0!
b0 ,
b101000101 %
1#
#1635
b101000110 %
0#
#1640
1&
b100 *
1!
b0 ,
b101000111 %
1#
#1645
b101001000 %
0#
#1650
0!
b0 ,
b101001001 %
1#
#1655
b101001010 %
0#
#1660
0"
b10 (
1!
b0 ,
b101001011 %
1#
#1665
b101001100 %
0#
#1670
0!
b0 ,
b101001101 %
1#
#1675
b101001110 %
0#
#1680
b0 (
1!
b0 ,
b101001111 %
1#
#1685
b101010000 %
0#
#1690
0!
b0 ,
b101010001 %
1#
#1695
b101010010 %
0#
#1700
0&
b0 *
b1 (
1'
1!
b0 ,
b101010011 %
1#
#1705
b101010100 %
0#
#1710
0'
0!
b0 ,
b101010101 %
1#
#1715
b101010110 %
0#
#1720
b1 *
1!
b0 ,
b101010111 %
1#
#1725
b101011000 %
0#
#1730
0!
b0 ,
b101011001 %
1#
#1735
b101011010 %
0#
#1740
b10 *
1!
b0 ,
b101011011 %
1#
#1745
b101011100 %
0#
#1750
0!
b0 ,
b101011101 %
1#
#1755
b101011110 %
0#
#1760
b11 *
1!
b0 ,
b101011111 %
1#
#1765
b101100000 %
0#
#1770
0!
b0 ,
b101100001 %
1#
#1775
b101100010 %
0#
#1780
1&
b100 *
1!
b0 ,
b101100011 %
1#
#1785
b101100100 %
0#
#1790
0!
b0 ,
b101100101 %
1#
#1795
b101100110 %
0#
#1800
1"
b10 (
1!
b0 ,
b101100111 %
1#
#1805
b101101000 %
0#
#1810
0!
b0 ,
b101101001 %
1#
#1815
b101101010 %
0#
#1820
b0 (
1!
b0 ,
b101101011 %
1#
#1825
b101101100 %
0#
#1830
0!
b0 ,
b101101101 %
1#
#1835
b101101110 %
0#
#1840
0&
b0 *
b1 (
1'
1!
b0 ,
b101101111 %
1#
#1845
b101110000 %
0#
#1850
0'
0!
b0 ,
b101110001 %
1#
#1855
b101110010 %
0#
#1860
b1 *
1!
b0 ,
b101110011 %
1#
#1865
b101110100 %
0#
#1870
0!
b0 ,
b101110101 %
1#
#1875
b101110110 %
0#
#1880
b10 *
1!
b0 ,
b101110111 %
1#
#1885
b101111000 %
0#
#1890
0!
b0 ,
b101111001 %
1#
#1895
b101111010 %
0#
#1900
b11 *
1!
b0 ,
b101111011 %
1#
#1905
b101111100 %
0#
#1910
0!
b0 ,
b101111101 %
1#
#1915
b101111110 %
0#
#1920
1&
b100 *
1!
b0 ,
b101111111 %
1#
#1925
b110000000 %
0#
#1930
0!
b0 ,
b110000001 %
1#
#1935
b110000010 %
0#
#1940
0"
b10 (
1!
b0 ,
b110000011 %
1#
#1945
b110000100 %
0#
#1950
0!
b0 ,
b110000101 %
1#
#1955
b110000110 %
0#
#1960
b0 (
1!
b0 ,
b110000111 %
1#
#1965
b110001000 %
0#
#1970
0!
b0 ,
b110001001 %
1#
#1975
b110001010 %
0#
#1980
0&
b0 *
b1 (
1'
1!
b0 ,
b110001011 %
1#
#1985
b110001100 %
0#
#1990
0'
0!
b0 ,
b110001101 %
1#
#1995
b110001110 %
0#
#2000
b1 *
1!
b0 ,
b110001111 %
1#
#2005
b110010000 %
0#
#2010
0!
b0 ,
b110010001 %
1#
#2015
b110010010 %
0#
#2020
b10 *
1!
b0 ,
b110010011 %
1#
#2025
b110010100 %
0#
#2030
0!
b0 ,
b110010101 %
1#
#2035
b110010110 %
0#
#2040
b11 *
1!
b0 ,
b110010111 %
1#
#2045
b110011000 %
0#
#2050
0!
b0 ,
b110011001 %
1#
#2055
b110011010 %
0#
#2060
1&
b100 *
1!
b0 ,
b110011011 %
1#
#2065
b110011100 %
0#
#2070
0!
b0 ,
b110011101 %
1#
#2075
b110011110 %
0#
#2080
1"
b10 (
1!
b0 ,
b110011111 %
1#
#2085
b110100000 %
0#
#2090
0!
b0 ,
b110100001 %
1#
#2095
b110100010 %
0#
#2100
b0 (
1!
b0 ,
b110100011 %
1#
#2105
b110100100 %
0#
#2110
0!
b0 ,
b110100101 %
1#
#2115
b110100110 %
0#
#2120
0&
b0 *
b1 (
1'
1!
b0 ,
b110100111 %
1#
#2125
b110101000 %
0#
#2130
0'
0!
b0 ,
b110101001 %
1#
#2135
b110101010 %
0#
#2140
b1 *
1!
b0 ,
b110101011 %
1#
#2145
b110101100 %
0#
#2150
0!
b0 ,
b110101101 %
1#
#2155
b110101110 %
0#
#2160
b10 *
1!
b0 ,
b110101111 %
1#
#2165
b110110000 %
0#
#2170
0!
b0 ,
b110110001 %
1#
#2175
b110110010 %
0#
#2180
b11 *
1!
b0 ,
b110110011 %
1#
#2185
b110110100 %
0#
#2190
0!
b0 ,
b110110101 %
1#
#2195
b110110110 %
0#
#2200
1&
b100 *
1!
b0 ,
b110110111 %
1#
#2205
b110111000 %
0#
#2210
0!
b0 ,
b110111001 %
1#
#2215
b110111010 %
0#
#2220
0"
b10 (
1!
b0 ,
b110111011 %
1#
#2225
b110111100 %
0#
#2230
0!
b0 ,
b110111101 %
1#
#2235
b110111110 %
0#
#2240
b0 (
1!
b0 ,
b110111111 %
1#
#2245
b111000000 %
0#
#2250
0!
b0 ,
b111000001 %
1#
#2255
b111000010 %
0#
#2260
0&
b0 *
b1 (
1'
1!
b0 ,
b111000011 %
1#
#2265
b111000100 %
0#
#2270
0'
0!
b0 ,
b111000101 %
1#
#2275
b111000110 %
0#
#2280
b1 *
1!
b0 ,
b111000111 %
1#
#2285
b111001000 %
0#
#2290
0!
b0 ,
b111001001 %
1#
#2295
b111001010 %
0#
#2300
b10 *
1!
b0 ,
b111001011 %
1#
#2305
b111001100 %
0#
#2310
0!
b0 ,
b111001101 %
1#
#2315
b111001110 %
0#
#2320
b11 *
1!
b0 ,
b111001111 %
1#
#2325
b111010000 %
0#
#2330
0!
b0 ,
b111010001 %
1#
#2335
b111010010 %
0#
#2340
1&
b100 *
1!
b0 ,
b111010011 %
1#
#2345
b111010100 %
0#
#2350
0!
b0 ,
b111010101 %
1#
#2355
b111010110 %
0#
#2360
1"
b10 (
1!
b0 ,
b111010111 %
1#
#2365
b111011000 %
0#
#2370
0!
b0 ,
b111011001 %
1#
#2375
b111011010 %
0#
#2380
b0 (
1!
b0 ,
b111011011 %
1#
#2385
b111011100 %
0#
#2390
0!
b0 ,
b111011101 %
1#
#2395
b111011110 %
0#
#2400
0&
b0 *
b1 (
1'
1!
b0 ,
b111011111 %
1#
#2405
b111100000 %
0#
#2410
0'
0!
b0 ,
b111100001 %
1#
#2415
b111100010 %
0#
#2420
b1 *
1!
b0 ,
b111100011 %
1#
#2425
b111100100 %
0#
#2430
0!
b0 ,
b111100101 %
1#
#2435
b111100110 %
0#
#2440
b10 *
1!
b0 ,
b111100111 %
1#
#2445
b111101000 %
0#
#2450
0!
b0 ,
b111101001 %
1#
#2455
b111101010 %
0#
#2460
b11 *
1!
b0 ,
b111101011 %
1#
#2465
b111101100 %
0#
#2470
0!
b0 ,
b111101101 %
1#
#2475
b111101110 %
0#
#2480
1&
b100 *
1!
b0 ,
b111101111 %
1#
#2485
b111110000 %
0#
#2490
0!
b0 ,
b111110001 %
1#
#2495
b111110010 %
0#
#2500
0"
b10 (
1!
b0 ,
b111110011 %
1#
#2505
b111110100 %
0#
#2510
0!
b0 ,
b111110101 %
1#
#2515
b111110110 %
0#
#2520
b0 (
1!
b0 ,
b111110111 %
1#
#2525
b111111000 %
0#
#2530
0!
b0 ,
b111111001 %
1#
#2535
b111111010 %
0#
#2540
0&
b0 *
b1 (
1'
1!
b0 ,
b111111011 %
1#
#2545
b111111100 %
0#
#2550
0'
0!
b0 ,
b111111101 %
1#
#2555
b111111110 %
0#
#2560
b1 *
1!
b0 ,
b111111111 %
1#
#2565
b1000000000 %
0#
#2570
0!
b0 ,
b1000000001 %
1#
#2575
b1000000010 %
0#
#2580
b10 *
1!
b0 ,
b1000000011 %
1#
#2585
b1000000100 %
0#
#2590
0!
b0 ,
b1000000101 %
1#
#2595
b1000000110 %
0#
#2600
b11 *
1!
b0 ,
b1000000111 %
1#
#2605
b1000001000 %
0#
#2610
0!
b0 ,
b1000001001 %
1#
#2615
b1000001010 %
0#
#2620
1&
b100 *
1!
b0 ,
b1000001011 %
1#
#2625
b1000001100 %
0#
#2630
0!
b0 ,
b1000001101 %
1#
#2635
b1000001110 %
0#
#2640
1"
b10 (
1!
b0 ,
b1000001111 %
1#
#2645
b1000010000 %
0#
#2650
0!
b0 ,
b1000010001 %
1#
#2655
b1000010010 %
0#
#2660
b0 (
1!
b0 ,
b1000010011 %
1#
#2665
b1000010100 %
0#
#2670
0!
b0 ,
b1000010101 %
1#
#2675
b1000010110 %
0#
#2680
0&
b0 *
b1 (
1'
1!
b0 ,
b1000010111 %
1#
#2685
b1000011000 %
0#
#2690
0'
0!
b0 ,
b1000011001 %
1#
#2695
b1000011010 %
0#
#2700
b1 *
1!
b0 ,
b1000011011 %
1#
#2705
b1000011100 %
0#
#2710
0!
b0 ,
b1000011101 %
1#
#2715
b1000011110 %
0#
#2720
b10 *
1!
b0 ,
b1000011111 %
1#
#2725
b1000100000 %
0#
#2730
0!
b0 ,
b1000100001 %
1#
#2735
b1000100010 %
0#
#2740
b11 *
1!
b0 ,
b1000100011 %
1#
#2745
b1000100100 %
0#
#2750
0!
b0 ,
b1000100101 %
1#
#2755
b1000100110 %
0#
#2760
1&
b100 *
1!
b0 ,
b1000100111 %
1#
#2765
b1000101000 %
0#
#2770
0!
b0 ,
b1000101001 %
1#
#2775
b1000101010 %
0#
#2780
0"
b10 (
1!
b0 ,
b1000101011 %
1#
#2785
b1000101100 %
0#
#2790
0!
b0 ,
b1000101101 %
1#
#2795
b1000101110 %
0#
#2800
b0 (
1!
b0 ,
b1000101111 %
1#
#2805
b1000110000 %
0#
#2810
0!
b0 ,
b1000110001 %
1#
#2815
b1000110010 %
0#
#2820
0&
b0 *
b1 (
1'
1!
b0 ,
b1000110011 %
1#
#2825
b1000110100 %
0#
#2830
0'
0!
b0 ,
b1000110101 %
1#
#2835
b1000110110 %
0#
#2840
b1 *
1!
b0 ,
b1000110111 %
1#
#2845
b1000111000 %
0#
#2850
0!
b0 ,
b1000111001 %
1#
#2855
b1000111010 %
0#
#2860
b10 *
1!
b0 ,
b1000111011 %
1#
#2865
b1000111100 %
0#
#2870
0!
b0 ,
b1000111101 %
1#
#2875
b1000111110 %
0#
#2880
b11 *
1!
b0 ,
b1000111111 %
1#
#2885
b1001000000 %
0#
#2890
0!
b0 ,
b1001000001 %
1#
#2895
b1001000010 %
0#
#2900
1&
b100 *
1!
b0 ,
b1001000011 %
1#
#2905
b1001000100 %
0#
#2910
0!
b0 ,
b1001000101 %
1#
#2915
b1001000110 %
0#
#2920
1"
b10 (
1!
b0 ,
b1001000111 %
1#
#2925
b1001001000 %
0#
#2930
0!
b0 ,
b1001001001 %
1#
#2935
b1001001010 %
0#
#2940
b0 (
1!
b0 ,
b1001001011 %
1#
#2945
b1001001100 %
0#
#2950
0!
b0 ,
b1001001101 %
1#
#2955
b1001001110 %
0#
#2960
0&
b0 *
b1 (
1'
1!
b0 ,
b1001001111 %
1#
#2965
b1001010000 %
0#
#2970
0'
0!
b0 ,
b1001010001 %
1#
#2975
b1001010010 %
0#
#2980
b1 *
1!
b0 ,
b1001010011 %
1#
#2985
b1001010100 %
0#
#2990
0!
b0 ,
b1001010101 %
1#
#2995
b1001010110 %
0#
#3000
b10 *
1!
b0 ,
b1001010111 %
1#
#3005
b1001011000 %
0#
