time_divider_advanced/src/time_divider_advanced.v
`timescale 1ns/1ps
/***************************************
晶振频率 fc = 100MHz
输出频率 fo = 1kHz（根据需要可以设为任意值）
控制参数 K  = (fo*2^N)/fc = 2147483648
参数 N = 2^32,(32为计数器的位宽)
****************************************/
module div(
    input clk,
    input rst,
    output reg clk_out
    );

    reg [31:0] cnt;

always @(posedge clk or posedge rst) 
    if(rst)
        cnt <= 0;
    else
        cnt <= cnt + 32'd2147483648;  //计数器步长K

always @(posedge clk or posedge rst)
    if(rst)
        clk_out <= 1'b0;
    else if(cnt < 32'h7FFF_FFFF)
        clk_out <= 1'b0;
    else
        clk_out <= 1'b1;

endmodule

time_divider_advanced/src/time_divider_advanced_tb.v
`timescale 1ns/1ps
/***************************************
晶振频率 fc = 100MHz
输出频率 fo = 1kHz（根据需要可以设为任意值）
控制参数 K  = (fo*2^N)/fc = 42950
参数 N = 2^32,(32为计数器的位宽)
****************************************/
module div_tb();
    reg clk;
    reg rst;
    wire clk_out;
    div inst (.clk(clk),.rst(rst),.clk_out(clk_out));
    integer i;
    initial begin
        clk=0;
        rst=0;
        #5
        rst=1;
        #5
        rst=0;
    end
    initial begin
        for (i = 0;i<100;i=i+1) begin
            #5
            clk=1;
            #5
            clk=0;
        end
    end
    initial begin   
        $dumpfile("./build/wave.vcd");  // 指定VCD文件的名字为wave.vcd，仿真信息将记录到此文件
        $dumpvars(0, div_tb);  // 指定层次数为0，则tb_code 模块及其下面各层次的所有信号将被记录
        #10000 $finish;
    end
endmodule

time_divider_advanced/build/wave.vcd
$date
	Sat Jan  1 12:15:16 2022
$end
$version
	Icarus Verilog
$end
$timescale
	1ps
$end
$scope module div_tb $end
$var wire 1 ! clk_out $end
$var reg 1 " clk $end
$var reg 1 # rst $end
$var integer 32 $ i [31:0] $end
$scope module inst $end
$var wire 1 " clk $end
$var wire 1 # rst $end
$var reg 1 ! clk_out $end
$var reg 32 % cnt [31:0] $end
$upscope $end
$upscope $end
$enddefinitions $end
#0
$dumpvars
bx %
b0 $
0#
0"
x!
$end
#5000
b0 %
0!
1"
1#
#10000
b1 $
0"
0#
#15000
b10000000000000000000000000000000 %
1"
#20000
b10 $
0"
#25000
b0 %
1!
1"
#30000
b11 $
0"
#35000
0!
b10000000000000000000000000000000 %
1"
#40000
b100 $
0"
#45000
b0 %
1!
1"
#50000
b101 $
0"
#55000
0!
b10000000000000000000000000000000 %
1"
#60000
b110 $
0"
#65000
b0 %
1!
1"
#70000
b111 $
0"
#75000
0!
b10000000000000000000000000000000 %
1"
#80000
b1000 $
0"
#85000
b0 %
1!
1"
#90000
b1001 $
0"
#95000
0!
b10000000000000000000000000000000 %
1"
#100000
b1010 $
0"
#105000
b0 %
1!
1"
#110000
b1011 $
0"
#115000
0!
b10000000000000000000000000000000 %
1"
#120000
b1100 $
0"
#125000
b0 %
1!
1"
#130000
b1101 $
0"
#135000
0!
b10000000000000000000000000000000 %
1"
#140000
b1110 $
0"
#145000
b0 %
1!
1"
#150000
b1111 $
0"
#155000
0!
b10000000000000000000000000000000 %
1"
#160000
b10000 $
0"
#165000
b0 %
1!
1"
#170000
b10001 $
0"
#175000
0!
b10000000000000000000000000000000 %
1"
#180000
b10010 $
0"
#185000
b0 %
1!
1"
#190000
b10011 $
0"
#195000
0!
b10000000000000000000000000000000 %
1"
#200000
b10100 $
0"
#205000
b0 %
1!
1"
#210000
b10101 $
0"
#215000
0!
b10000000000000000000000000000000 %
1"
#220000
b10110 $
0"
#225000
b0 %
1!
1"
#230000
b10111 $
0"
#235000
0!
b10000000000000000000000000000000 %
1"
#240000
b11000 $
0"
#245000
b0 %
1!
1"
#250000
b11001 $
0"
#255000
0!
b10000000000000000000000000000000 %
1"
#260000
b11010 $
0"
#265000
b0 %
1!
1"
#270000
b11011 $
0"
#275000
0!
b10000000000000000000000000000000 %
1"
#280000
b11100 $
0"
#285000
b0 %
1!
1"
#290000
b11101 $
0"
#295000
0!
b10000000000000000000000000000000 %
1"
#300000
b11110 $
0"
#305000
b0 %
1!
1"
#310000
b11111 $
0"
#315000
0!
b10000000000000000000000000000000 %
1"
#320000
b100000 $
0"
#325000
b0 %
1!
1"
#330000
b100001 $
0"
#335000
0!
b10000000000000000000000000000000 %
1"
#340000
b100010 $
0"
#345000
b0 %
1!
1"
#350000
b100011 $
0"
#355000
0!
b10000000000000000000000000000000 %
1"
#360000
b100100 $
0"
#365000
b0 %
1!
1"
#370000
b100101 $
0"
#375000
0!
b10000000000000000000000000000000 %
1"
#380000
b100110 $
0"
#385000
b0 %
1!
1"
#390000
b100111 $
0"
#395000
0!
b10000000000000000000000000000000 %
1"
#400000
b101000 $
0"
#405000
b0 %
1!
1"
#410000
b101001 $
0"
#415000
0!
b10000000000000000000000000000000 %
1"
#420000
b101010 $
0"
#425000
b0 %
1!
1"
#430000
b101011 $
0"
#435000
0!
b10000000000000000000000000000000 %
1"
#440000
b101100 $
0"
#445000
b0 %
1!
1"
#450000
b101101 $
0"
#455000
0!
b10000000000000000000000000000000 %
1"
#460000
b101110 $
0"
#465000
b0 %
1!
1"
#470000
b101111 $
0"
#475000
0!
b10000000000000000000000000000000 %
1"
#480000
b110000 $
0"
#485000
b0 %
1!
1"
#490000
b110001 $
0"
#495000
0!
b10000000000000000000000000000000 %
1"
#500000
b110010 $
0"
#505000
b0 %
1!
1"
#510000
b110011 $
0"
#515000
0!
b10000000000000000000000000000000 %
1"
#520000
b110100 $
0"
#525000
b0 %
1!
1"
#530000
b110101 $
0"
#535000
0!
b10000000000000000000000000000000 %
1"
#540000
b110110 $
0"
#545000
b0 %
1!
1"
#550000
b110111 $
0"
#555000
0!
b10000000000000000000000000000000 %
1"
#560000
b111000 $
0"
#565000
b0 %
1!
1"
#570000
b111001 $
0"
#575000
0!
b10000000000000000000000000000000 %
1"
#580000
b111010 $
0"
#585000
b0 %
1!
1"
#590000
b111011 $
0"
#595000
0!
b10000000000000000000000000000000 %
1"
#600000
b111100 $
0"
#605000
b0 %
1!
1"
#610000
b111101 $
0"
#615000
0!
b10000000000000000000000000000000 %
1"
#620000
b111110 $
0"
#625000
b0 %
1!
1"
#630000
b111111 $
0"
#635000
0!
b10000000000000000000000000000000 %
1"
#640000
b1000000 $
0"
#645000
b0 %
1!
1"
#650000
b1000001 $
0"
#655000
0!
b10000000000000000000000000000000 %
1"
#660000
b1000010 $
0"
#665000
b0 %
1!
1"
#670000
b1000011 $
0"
#675000
0!
b10000000000000000000000000000000 %
1"
#680000
b1000100 $
0"
#685000
b0 %
1!
1"
#690000
b1000101 $
0"
#695000
0!
b10000000000000000000000000000000 %
1"
#700000
b1000110 $
0"
#705000
b0 %
1!
1"
#710000
b1000111 $
0"
#715000
0!
b10000000000000000000000000000000 %
1"
#720000
b1001000 $
0"
#725000
b0 %
1!
1"
#730000
b1001001 $
0"
#735000
0!
b10000000000000000000000000000000 %
1"
#740000
b1001010 $
0"
#745000
b0 %
1!
1"
#750000
b1001011 $
0"
#755000
0!
b10000000000000000000000000000000 %
1"
#760000
b1001100 $
0"
#765000
b0 %
1!
1"
#770000
b1001101 $
0"
#775000
0!
b10000000000000000000000000000000 %
1"
#780000
b1001110 $
0"
#785000
b0 %
1!
1"
#790000
b1001111 $
0"
#795000
0!
b10000000000000000000000000000000 %
1"
#800000
b1010000 $
0"
#805000
b0 %
1!
1"
#810000
b1010001 $
0"
#815000
0!
b10000000000000000000000000000000 %
1"
#820000
b1010010 $
0"
#825000
b0 %
1!
1"
#830000
b1010011 $
0"
#835000
0!
b10000000000000000000000000000000 %
1"
#840000
b1010100 $
0"
#845000
b0 %
1!
1"
#850000
b1010101 $
0"
#855000
0!
b10000000000000000000000000000000 %
1"
#860000
b1010110 $
0"
#865000
b0 %
1!
1"
#870000
b1010111 $
0"
#875000
0!
b10000000000000000000000000000000 %
1"
#880000
b1011000 $
0"
#885000
b0 %
1!
1"
#890000
b1011001 $
0"
#895000
0!
b10000000000000000000000000000000 %
1"
#900000
b1011010 $
0"
#905000
b0 %
1!
1"
#910000
b1011011 $
0"
#915000
0!
b10000000000000000000000000000000 %
1"
#920000
b1011100 $
0"
#925000
b0 %
1!
1"
#930000
b1011101 $
0"
#935000
0!
b10000000000000000000000000000000 %
1"
#940000
b1011110 $
0"
#945000
b0 %
1!
1"
#950000
b1011111 $
0"
#955000
0!
b10000000000000000000000000000000 %
1"
#960000
b1100000 $
0"
#965000
b0 %
1!
1"
#970000
b1100001 $
0"
#975000
0!
b10000000000000000000000000000000 %
1"
#980000
b1100010 $
0"
#985000
b0 %
1!
1"
#990000
b1100011 $
0"
#995000
0!
b10000000000000000000000000000000 %
1"
#1000000
b1100100 $
0"
