comprehensive/src/time_divider.v
module time_divider 
#(
    parameter ratio=2
)
(
    input i_clk,
    input rst_n,
    output o_clk
);
    //registers definitions
    reg [31:0]count;
    integer lim=ratio/2;
    //combinational circuits
    assign o_clk=count>=lim?1'b1:1'b0;
    //counting
    always @(posedge i_clk or negedge rst_n) begin
        if(!rst_n) begin
            count<=32'b0;
        end
        else begin
            if(count<lim)begin
                count<=count+1;
            end
            else begin
                count<=32'b0;
            end
        end
    end
endmodule

I2C_driver/src/I2C_frame_output.v
//control the I2C_byte_output to output a data frame to manipulate the register
//data frame 
module I2C_frame_output
#(
    parameter slave_addr=16'h40 //default address of the slave board
)
(
    //control signals
    input i_clk, //the global clock signal to generate the I2C clk
    input i_rst_n, //reset signal enables when low,only once after power up
    input [7:0]i_register_addr, //the address of the register to manipulate
    input [7:0]i_data, //the data to send 
    input i_start, //posedge to start sending
    output o_complete, //high when complete
    //I2C interfac
    output reg io_SDA, //the signal line of I2C
    output reg o_SCL //the clk signal for I2C
);
//=======local parameters definition
    localparam state_idle = 30;
    localparam state_start = 29;
    localparam state_slave_h = 28;
    localparam state_slave_l = 22;
    localparam state_rw1 = 21;
    localparam state_ack1 = 20;
    localparam state_reg_adr_h = 19;
    localparam state_reg_adr_l = 12;
    localparam state_ack2 = 11;
    localparam state_data_h=10;
    localparam state_data_l=3;
    localparam state_ack=2;
    localparam state_stop = 1; //reset the data,wait for the negedge of start to change to next one
    localparam state_waitforstart= 0; //wait for high level of start
    // localparam state_idle = 0;
//=======wire definition
    wire controller_clk; //generated clock for I2C controller
//======register definition
    reg out_clock; //output clock for I2C sclk
    reg [5:0]current_state;
    reg finished;
    reg rst_complete;
//=======combinational circuits
    // assign o_SCL=(i_start==1)?1:out_clk; 
    //pull the scl up when it is not sending
    assign o_complete=(current_state==state_stop)&&(rst_complete);
//=======instantiation
    //generate the clock output for the I2C
    time_divider
    #(1000000) //1kHz
    clk_generator
    (
        .i_clk(i_clk),
        .rst_n(i_rst_n),
        .o_clk(controller_clk)
    );
//======sequential logic
    //main loop for FSM switching
    always @(posedge controller_clk or negedge i_rst_n or negedge i_start) begin
        if(!i_rst_n) begin
            current_state<=state_waitforstart;
        end
        else begin
            if(current_state==state_stop) begin
                if(!i_start) begin
                    current_state=state_waitforstart;
                end
            end
            else if(current_state==state_waitforstart)begin
                if(i_start) begin
                    current_state=state_start;
                end
            end
            else current_state=current_state-1;
        end
    end
    //data and clk generate
    always @(posedge controller_clk or negedge controller_clk or negedge i_rst_n) begin
        if(!i_rst_n)begin
            io_SDA<=1;
            o_SCL<=1;
        end
        else begin
            if(controller_clk) begin
                //high level
                //update data first
                if(current_state==state_start) begin
                    //start signal
                    io_SDA<=0;
                    rst_complete <= 0;
                end
                else if (current_state>=state_slave_h&&current_state<=state_slave_l) begin
                    //slave address
                    io_SDA<=io_SDA<=slave_addr[current_state-22];
                end
                else if (current_state==state_ack1||current_state==state_ack2) begin
                    //acknoknowledge
                    io_SDA<=1'bz;
                end
                else if (current_state==state_rw1) begin
                    //read write control
                    io_SDA<=0; //write enable
                end
                else if(current_state<=state_reg_adr_h&&current_state>=state_reg_adr_l) begin
                    //register address
                    io_SDA<=i_register_addr[current_state-12];
                end
                else if(current_state<=state_data_h&&current_state>=state_data_l) begin
                    //output data
                    io_SDA<=i_data[current_state-3];
                end
                else if(current_state==state_stop||current_state==state_idle)begin
                    //stop
                    io_SDA<=1;
                    rst_complete <=1;
                end
                //update clock
                o_SCL=0;
            end
            else begin
                //low level
                o_SCL=1;
            end
        end
    end

endmodule

I2C_driver/src/servo_driver.v

module servo_driver (
    //control signals
    input i_clk, //clock for servo controller
    input i_rst_n, //reset signal enables when low
    //I2C frame output interface
    output io_SDA,
    output o_SCL
);
//======parameter definitions
    //states definitnions
    localparam state_set_mode_sleep=0;
    localparam state_setf=1;
    localparam state_set_mode_run=2;
    localparam state_update = 3;
    localparam state_send_on_h = 4;
    localparam state_send_on_l = 5;
    localparam state_send_off_h = 6;
    localparam state_send_off_l = 7;
    localparam state_wait = 8;
    //data frme definitions
    //mode setting
    localparam mode_reg_addr = 8'h00;
    localparam mode_sleep_data = 8'h10;
    localparam mode_run_data = 8'h00;
    //frequency setting
    localparam frequency_reg_addr = 8'hfe;
    localparam frequency_data = 8'h79; //50Hz
    //data setting
    localparam pwm0_on_h_data = 8'h00;
    localparam pwm0_on_l_data = 8'h00;
    localparam pwm0_off_h_data = 8'h00;
    localparam pwm0_off_l_data = 8'hd8;
    //reg addr setting
    localparam pwm0_on_l_addr = 8'h0A;
    localparam pwm0_on_h_addr = 8'h0B;
    localparam pwm0_off_l_addr = 8'h0C;
    localparam pwm0_off_h_addr = 8'h0D;

//======register definitions
    reg [3:0] current_state;
    reg [3:0] next_state; //for the waiting state
    reg start_flag;
    reg [7:0] gen_register_addr;
    reg [7:0] gen_data;
//======wire definitions
    wire controller_clk;
    wire complete; //compelete signal from frame output
//======instantiation
    //generate the clk signal for controller 100Hz
    time_divider
    #(1000000)
    controller_clk_generator
    (
        .i_clk(i_clk),
        .rst_n(i_rst_n),
        .o_clk(controller_clk)
    );
    I2C_frame_output
    I2C_driver
    (
        .i_clk(i_clk),
        .i_rst_n(i_rst_n),
        .i_register_addr(gen_register_addr),
        .i_data(gen_data),
        .i_start(start_flag),
        .o_complete(complete),
        .io_SDA(io_SDA),
        .o_SCL(o_SCL)
    );
//======sequencial circuit
    //for mst
    always @(posedge i_clk or negedge i_rst_n or posedge complete) begin
        if(!i_rst_n) begin
            current_state=state_set_mode_sleep;
            start_flag=0;
        end
        else begin
            case (current_state)
                state_set_mode_sleep: begin
                    gen_data=mode_sleep_data;
                    gen_register_addr=mode_reg_addr;
                    $display("gen_data:%h gen_register:%h",gen_data,gen_register_addr);
                    next_state=state_setf;
                    send_byte;
                end
                state_setf: begin
                    gen_data=frequency_data;
                    gen_register_addr=frequency_reg_addr;
                    $display("gen_data:%h gen_register:%h",gen_data,gen_register_addr);
                    next_state=state_set_mode_run;
                    send_byte;
                end
                state_set_mode_run: begin
                    gen_data=mode_run_data;
                    gen_register_addr=mode_reg_addr;
                    $display("gen_data:%h gen_register:%h",gen_data,gen_register_addr);
                    next_state=state_update;
                    send_byte;
                end
                state_update: begin
                    current_state=state_send_on_h;
                end
                state_send_on_h:begin
                    gen_data=pwm0_on_h_data;
                    gen_register_addr=pwm0_on_h_addr;
                    $display("gen_data:%h gen_register:%h",gen_data,gen_register_addr);
                    next_state=state_send_on_l;
                    send_byte;
                end
                state_send_on_l:begin
                    gen_data=pwm0_on_l_data;
                    gen_register_addr=pwm0_on_l_addr;
                    $display("gen_data:%h gen_register:%h",gen_data,gen_register_addr);
                    next_state=state_send_off_h;
                    send_byte;
                end
                state_send_off_h:begin
                    gen_data=pwm0_off_h_data;
                    gen_register_addr=pwm0_off_h_addr;
                    $display("gen_data:%h gen_register:%h",gen_data,gen_register_addr);
                    next_state=state_send_off_l;
                    send_byte;
                end
                state_send_off_l:begin 
                    gen_data=pwm0_off_l_data;
                    gen_register_addr=pwm0_off_l_addr;
                    $display("gen_data:%h gen_register:%h",gen_data,gen_register_addr);
                    next_state=state_update;
                    send_byte;
                end
                state_wait: begin
                    if(complete)begin
                        start_flag=0;
                        current_state=next_state;
                    end
                end
                default:;
            endcase
        end
    end
//======task definitions
task send_byte;
    begin
        start_flag=1;
        current_state=state_wait;
    end
endtask
endmodule

I2C_driver/src/servo_driver_tb.v
module servo_driver_tb ();
    //control signals
    reg i_clk; //clock for servo controller
    reg i_rst_n; //reset signal enables when low
    //I2C frame output interface
    wire io_SDA;
    wire o_SCL;
    servo_driver servo_inst
    (
        .i_clk(i_clk),
        .i_rst_n(i_rst_n),
        .io_SDA(io_SDA),
        .o_SCL(o_SCL)
    );
    integer i;
    initial begin
        i_rst_n=1; 
        i_clk=0;
        #5
        i_rst_n=0;
        #5
        i_rst_n=1;
        for (i = 0;i<20000 ;i=i+1 ) begin
            #5
            i_clk=0;
            #5
            i_clk=1;
        end
    end
    initial begin   
        $dumpfile("./build/wave.vcd");  // 指定VCD文件的名字为wave.vcd，仿真信息将记录到此文件
        $dumpvars(0, servo_driver_tb);  // 指定层次数为0，则tb_code 模块及其下面各层次的所有信号将被记录
        #20000 $finish;
    end
endmodule

I2C_driver/build/wave.vcd
$date
	Mon Jan  3 21:46:53 2022
$end
$version
	Icarus Verilog
$end
$timescale
	1s
$end
$scope module servo_driver_tb $end
$var wire 1 ! o_SCL $end
$var wire 1 " io_SDA $end
$var reg 1 # i_clk $end
$var reg 1 $ i_rst_n $end
$var integer 32 % i [31:0] $end
$scope module servo_inst $end
$var wire 1 # i_clk $end
$var wire 1 $ i_rst_n $end
$var wire 1 ! o_SCL $end
$var wire 1 " io_SDA $end
$var wire 1 & controller_clk $end
$var wire 1 ' complete $end
$var reg 4 ( current_state [3:0] $end
$var reg 8 ) gen_data [7:0] $end
$var reg 8 * gen_register_addr [7:0] $end
$var reg 4 + next_state [3:0] $end
$var reg 1 , start_flag $end
$scope module I2C_driver $end
$var wire 1 # i_clk $end
$var wire 8 - i_data [7:0] $end
$var wire 8 . i_register_addr [7:0] $end
$var wire 1 $ i_rst_n $end
$var wire 1 , i_start $end
$var wire 1 ' o_complete $end
$var wire 1 / controller_clk $end
$var reg 6 0 current_state [5:0] $end
$var reg 1 " io_SDA $end
$var reg 1 ! o_SCL $end
$var reg 1 1 rst_complete $end
$scope module clk_generator $end
$var wire 1 # i_clk $end
$var wire 1 $ rst_n $end
$var reg 32 2 count [31:0] $end
$var reg 1 / o_clk $end
$var integer 32 3 lim [31:0] $end
$upscope $end
$upscope $end
$scope module controller_clk_generator $end
$var wire 1 # i_clk $end
$var wire 1 $ rst_n $end
$var reg 32 4 count [31:0] $end
$var reg 1 & o_clk $end
$var integer 32 5 lim [31:0] $end
$upscope $end
$scope task send_byte $end
$upscope $end
$upscope $end
$upscope $end
$enddefinitions $end
#0
$dumpvars
b1111010000100100000 5
bx 4
b1100001101010000 3
bx 2
x1
bx 0
0/
bx .
bx -
x,
bx +
bx *
bx )
bx (
x'
0&
bx %
1$
0#
x"
x!
$end
#5
0'
b0 4
b0 2
b0 0
1!
1"
0,
b0 (
0$
#10
b0 %
1$
#20
b1 2
b1 4
b1000 (
1,
b1 +
b0 *
b0 .
b10000 )
b10000 -
b1 %
1#
#25
0#
#30
b10 4
b10 2
b10 %
1#
#35
0#
#40
b11 2
b11 4
b11 %
1#
#45
0#
#50
b100 4
b100 2
b100 %
1#
#55
0#
#60
b101 2
b101 4
b101 %
1#
#65
0#
#70
b110 4
b110 2
b110 %
1#
#75
0#
#80
b111 2
b111 4
b111 %
1#
#85
0#
#90
b1000 4
b1000 2
b1000 %
1#
#95
0#
#100
b1001 2
b1001 4
b1001 %
1#
#105
0#
#110
b1010 4
b1010 2
b1010 %
1#
#115
0#
#120
b1011 2
b1011 4
b1011 %
1#
#125
0#
#130
b1100 4
b1100 2
b1100 %
1#
#135
0#
#140
b1101 2
b1101 4
b1101 %
1#
#145
0#
#150
b1110 4
b1110 2
b1110 %
1#
#155
0#
#160
b1111 2
b1111 4
b1111 %
1#
#165
0#
#170
b10000 4
b10000 2
b10000 %
1#
#175
0#
#180
b10001 2
b10001 4
b10001 %
1#
#185
0#
#190
b10010 4
b10010 2
b10010 %
1#
#195
0#
#200
b10011 2
b10011 4
b10011 %
1#
#205
0#
#210
b10100 4
b10100 2
b10100 %
1#
#215
0#
#220
b10101 2
b10101 4
b10101 %
1#
#225
0#
#230
b10110 4
b10110 2
b10110 %
1#
#235
0#
#240
b10111 2
b10111 4
b10111 %
1#
#245
0#
#250
b11000 4
b11000 2
b11000 %
1#
#255
0#
#260
b11001 2
b11001 4
b11001 %
1#
#265
0#
#270
b11010 4
b11010 2
b11010 %
1#
#275
0#
#280
b11011 2
b11011 4
b11011 %
1#
#285
0#
#290
b11100 4
b11100 2
b11100 %
1#
#295
0#
#300
b11101 2
b11101 4
b11101 %
1#
#305
0#
#310
b11110 4
b11110 2
b11110 %
1#
#315
0#
#320
b11111 2
b11111 4
b11111 %
1#
#325
0#
#330
b100000 4
b100000 2
b100000 %
1#
#335
0#
#340
b100001 2
b100001 4
b100001 %
1#
#345
0#
#350
b100010 4
b100010 2
b100010 %
1#
#355
0#
#360
b100011 2
b100011 4
b100011 %
1#
#365
0#
#370
b100100 4
b100100 2
b100100 %
1#
#375
0#
#380
b100101 2
b100101 4
b100101 %
1#
#385
0#
#390
b100110 4
b100110 2
b100110 %
1#
#395
0#
#400
b100111 2
b100111 4
b100111 %
1#
#405
0#
#410
b101000 4
b101000 2
b101000 %
1#
#415
0#
#420
b101001 2
b101001 4
b101001 %
1#
#425
0#
#430
b101010 4
b101010 2
b101010 %
1#
#435
0#
#440
b101011 2
b101011 4
b101011 %
1#
#445
0#
#450
b101100 4
b101100 2
b101100 %
1#
#455
0#
#460
b101101 2
b101101 4
b101101 %
1#
#465
0#
#470
b101110 4
b101110 2
b101110 %
1#
#475
0#
#480
b101111 2
b101111 4
b101111 %
1#
#485
0#
#490
b110000 4
b110000 2
b110000 %
1#
#495
0#
#500
b110001 2
b110001 4
b110001 %
1#
#505
0#
#510
b110010 4
b110010 2
b110010 %
1#
#515
0#
#520
b110011 2
b110011 4
b110011 %
1#
#525
0#
#530
b110100 4
b110100 2
b110100 %
1#
#535
0#
#540
b110101 2
b110101 4
b110101 %
1#
#545
0#
#550
b110110 4
b110110 2
b110110 %
1#
#555
0#
#560
b110111 2
b110111 4
b110111 %
1#
#565
0#
#570
b111000 4
b111000 2
b111000 %
1#
#575
0#
#580
b111001 2
b111001 4
b111001 %
1#
#585
0#
#590
b111010 4
b111010 2
b111010 %
1#
#595
0#
#600
b111011 2
b111011 4
b111011 %
1#
#605
0#
#610
b111100 4
b111100 2
b111100 %
1#
#615
0#
#620
b111101 2
b111101 4
b111101 %
1#
#625
0#
#630
b111110 4
b111110 2
b111110 %
1#
#635
0#
#640
b111111 2
b111111 4
b111111 %
1#
#645
0#
#650
b1000000 4
b1000000 2
b1000000 %
1#
#655
0#
#660
b1000001 2
b1000001 4
b1000001 %
1#
#665
0#
#670
b1000010 4
b1000010 2
b1000010 %
1#
#675
0#
#680
b1000011 2
b1000011 4
b1000011 %
1#
#685
0#
#690
b1000100 4
b1000100 2
b1000100 %
1#
#695
0#
#700
b1000101 2
b1000101 4
b1000101 %
1#
#705
0#
#710
b1000110 4
b1000110 2
b1000110 %
1#
#715
0#
#720
b1000111 2
b1000111 4
b1000111 %
1#
#725
0#
#730
b1001000 4
b1001000 2
b1001000 %
1#
#735
0#
#740
b1001001 2
b1001001 4
b1001001 %
1#
#745
0#
#750
b1001010 4
b1001010 2
b1001010 %
1#
#755
0#
#760
b1001011 2
b1001011 4
b1001011 %
1#
#765
0#
#770
b1001100 4
b1001100 2
b1001100 %
1#
#775
0#
#780
b1001101 2
b1001101 4
b1001101 %
1#
#785
0#
#790
b1001110 4
b1001110 2
b1001110 %
1#
#795
0#
#800
b1001111 2
b1001111 4
b1001111 %
1#
#805
0#
#810
b1010000 4
b1010000 2
b1010000 %
1#
#815
0#
#820
b1010001 2
b1010001 4
b1010001 %
1#
#825
0#
#830
b1010010 4
b1010010 2
b1010010 %
1#
#835
0#
#840
b1010011 2
b1010011 4
b1010011 %
1#
#845
0#
#850
b1010100 4
b1010100 2
b1010100 %
1#
#855
0#
#860
b1010101 2
b1010101 4
b1010101 %
1#
#865
0#
#870
b1010110 4
b1010110 2
b1010110 %
1#
#875
0#
#880
b1010111 2
b1010111 4
b1010111 %
1#
#885
0#
#890
b1011000 4
b1011000 2
b1011000 %
1#
#895
0#
#900
b1011001 2
b1011001 4
b1011001 %
1#
#905
0#
#910
b1011010 4
b1011010 2
b1011010 %
1#
#915
0#
#920
b1011011 2
b1011011 4
b1011011 %
1#
#925
0#
#930
b1011100 4
b1011100 2
b1011100 %
1#
#935
0#
#940
b1011101 2
b1011101 4
b1011101 %
1#
#945
0#
#950
b1011110 4
b1011110 2
b1011110 %
1#
#955
0#
#960
b1011111 2
b1011111 4
b1011111 %
1#
#965
0#
#970
b1100000 4
b1100000 2
b1100000 %
1#
#975
0#
#980
b1100001 2
b1100001 4
b1100001 %
1#
#985
0#
#990
b1100010 4
b1100010 2
b1100010 %
1#
#995
0#
#1000
b1100011 2
b1100011 4
b1100011 %
1#
#1005
0#
#1010
b1100100 4
b1100100 2
b1100100 %
1#
#1015
0#
#1020
b1100101 2
b1100101 4
b1100101 %
1#
#1025
0#
#1030
b1100110 4
b1100110 2
b1100110 %
1#
#1035
0#
#1040
b1100111 2
b1100111 4
b1100111 %
1#
#1045
0#
#1050
b1101000 4
b1101000 2
b1101000 %
1#
#1055
0#
#1060
b1101001 2
b1101001 4
b1101001 %
1#
#1065
0#
#1070
b1101010 4
b1101010 2
b1101010 %
1#
#1075
0#
#1080
b1101011 2
b1101011 4
b1101011 %
1#
#1085
0#
#1090
b1101100 4
b1101100 2
b1101100 %
1#
#1095
0#
#1100
b1101101 2
b1101101 4
b1101101 %
1#
#1105
0#
#1110
b1101110 4
b1101110 2
b1101110 %
1#
#1115
0#
#1120
b1101111 2
b1101111 4
b1101111 %
1#
#1125
0#
#1130
b1110000 4
b1110000 2
b1110000 %
1#
#1135
0#
#1140
b1110001 2
b1110001 4
b1110001 %
1#
#1145
0#
#1150
b1110010 4
b1110010 2
b1110010 %
1#
#1155
0#
#1160
b1110011 2
b1110011 4
b1110011 %
1#
#1165
0#
#1170
b1110100 4
b1110100 2
b1110100 %
1#
#1175
0#
#1180
b1110101 2
b1110101 4
b1110101 %
1#
#1185
0#
#1190
b1110110 4
b1110110 2
b1110110 %
1#
#1195
0#
#1200
b1110111 2
b1110111 4
b1110111 %
1#
#1205
0#
#1210
b1111000 4
b1111000 2
b1111000 %
1#
#1215
0#
#1220
b1111001 2
b1111001 4
b1111001 %
1#
#1225
0#
#1230
b1111010 4
b1111010 2
b1111010 %
1#
#1235
0#
#1240
b1111011 2
b1111011 4
b1111011 %
1#
#1245
0#
#1250
b1111100 4
b1111100 2
b1111100 %
1#
#1255
0#
#1260
b1111101 2
b1111101 4
b1111101 %
1#
#1265
0#
#1270
b1111110 4
b1111110 2
b1111110 %
1#
#1275
0#
#1280
b1111111 2
b1111111 4
b1111111 %
1#
#1285
0#
#1290
b10000000 4
b10000000 2
b10000000 %
1#
#1295
0#
#1300
b10000001 2
b10000001 4
b10000001 %
1#
#1305
0#
#1310
b10000010 4
b10000010 2
b10000010 %
1#
#1315
0#
#1320
b10000011 2
b10000011 4
b10000011 %
1#
#1325
0#
#1330
b10000100 4
b10000100 2
b10000100 %
1#
#1335
0#
#1340
b10000101 2
b10000101 4
b10000101 %
1#
#1345
0#
#1350
b10000110 4
b10000110 2
b10000110 %
1#
#1355
0#
#1360
b10000111 2
b10000111 4
b10000111 %
1#
#1365
0#
#1370
b10001000 4
b10001000 2
b10001000 %
1#
#1375
0#
#1380
b10001001 2
b10001001 4
b10001001 %
1#
#1385
0#
#1390
b10001010 4
b10001010 2
b10001010 %
1#
#1395
0#
#1400
b10001011 2
b10001011 4
b10001011 %
1#
#1405
0#
#1410
b10001100 4
b10001100 2
b10001100 %
1#
#1415
0#
#1420
b10001101 2
b10001101 4
b10001101 %
1#
#1425
0#
#1430
b10001110 4
b10001110 2
b10001110 %
1#
#1435
0#
#1440
b10001111 2
b10001111 4
b10001111 %
1#
#1445
0#
#1450
b10010000 4
b10010000 2
b10010000 %
1#
#1455
0#
#1460
b10010001 2
b10010001 4
b10010001 %
1#
#1465
0#
#1470
b10010010 4
b10010010 2
b10010010 %
1#
#1475
0#
#1480
b10010011 2
b10010011 4
b10010011 %
1#
#1485
0#
#1490
b10010100 4
b10010100 2
b10010100 %
1#
#1495
0#
#1500
b10010101 2
b10010101 4
b10010101 %
1#
#1505
0#
#1510
b10010110 4
b10010110 2
b10010110 %
1#
#1515
0#
#1520
b10010111 2
b10010111 4
b10010111 %
1#
#1525
0#
#1530
b10011000 4
b10011000 2
b10011000 %
1#
#1535
0#
#1540
b10011001 2
b10011001 4
b10011001 %
1#
#1545
0#
#1550
b10011010 4
b10011010 2
b10011010 %
1#
#1555
0#
#1560
b10011011 2
b10011011 4
b10011011 %
1#
#1565
0#
#1570
b10011100 4
b10011100 2
b10011100 %
1#
#1575
0#
#1580
b10011101 2
b10011101 4
b10011101 %
1#
#1585
0#
#1590
b10011110 4
b10011110 2
b10011110 %
1#
#1595
0#
#1600
b10011111 2
b10011111 4
b10011111 %
1#
#1605
0#
#1610
b10100000 4
b10100000 2
b10100000 %
1#
#1615
0#
#1620
b10100001 2
b10100001 4
b10100001 %
1#
#1625
0#
#1630
b10100010 4
b10100010 2
b10100010 %
1#
#1635
0#
#1640
b10100011 2
b10100011 4
b10100011 %
1#
#1645
0#
#1650
b10100100 4
b10100100 2
b10100100 %
1#
#1655
0#
#1660
b10100101 2
b10100101 4
b10100101 %
1#
#1665
0#
#1670
b10100110 4
b10100110 2
b10100110 %
1#
#1675
0#
#1680
b10100111 2
b10100111 4
b10100111 %
1#
#1685
0#
#1690
b10101000 4
b10101000 2
b10101000 %
1#
#1695
0#
#1700
b10101001 2
b10101001 4
b10101001 %
1#
#1705
0#
#1710
b10101010 4
b10101010 2
b10101010 %
1#
#1715
0#
#1720
b10101011 2
b10101011 4
b10101011 %
1#
#1725
0#
#1730
b10101100 4
b10101100 2
b10101100 %
1#
#1735
0#
#1740
b10101101 2
b10101101 4
b10101101 %
1#
#1745
0#
#1750
b10101110 4
b10101110 2
b10101110 %
1#
#1755
0#
#1760
b10101111 2
b10101111 4
b10101111 %
1#
#1765
0#
#1770
b10110000 4
b10110000 2
b10110000 %
1#
#1775
0#
#1780
b10110001 2
b10110001 4
b10110001 %
1#
#1785
0#
#1790
b10110010 4
b10110010 2
b10110010 %
1#
#1795
0#
#1800
b10110011 2
b10110011 4
b10110011 %
1#
#1805
0#
#1810
b10110100 4
b10110100 2
b10110100 %
1#
#1815
0#
#1820
b10110101 2
b10110101 4
b10110101 %
1#
#1825
0#
#1830
b10110110 4
b10110110 2
b10110110 %
1#
#1835
0#
#1840
b10110111 2
b10110111 4
b10110111 %
1#
#1845
0#
#1850
b10111000 4
b10111000 2
b10111000 %
1#
#1855
0#
#1860
b10111001 2
b10111001 4
b10111001 %
1#
#1865
0#
#1870
b10111010 4
b10111010 2
b10111010 %
1#
#1875
0#
#1880
b10111011 2
b10111011 4
b10111011 %
1#
#1885
0#
#1890
b10111100 4
b10111100 2
b10111100 %
1#
#1895
0#
#1900
b10111101 2
b10111101 4
b10111101 %
1#
#1905
0#
#1910
b10111110 4
b10111110 2
b10111110 %
1#
#1915
0#
#1920
b10111111 2
b10111111 4
b10111111 %
1#
#1925
0#
#1930
b11000000 4
b11000000 2
b11000000 %
1#
#1935
0#
#1940
b11000001 2
b11000001 4
b11000001 %
1#
#1945
0#
#1950
b11000010 4
b11000010 2
b11000010 %
1#
#1955
0#
#1960
b11000011 2
b11000011 4
b11000011 %
1#
#1965
0#
#1970
b11000100 4
b11000100 2
b11000100 %
1#
#1975
0#
#1980
b11000101 2
b11000101 4
b11000101 %
1#
#1985
0#
#1990
b11000110 4
b11000110 2
b11000110 %
1#
#1995
0#
#2000
b11000111 2
b11000111 4
b11000111 %
1#
#2005
0#
#2010
b11001000 4
b11001000 2
b11001000 %
1#
#2015
0#
#2020
b11001001 2
b11001001 4
b11001001 %
1#
#2025
0#
#2030
b11001010 4
b11001010 2
b11001010 %
1#
#2035
0#
#2040
b11001011 2
b11001011 4
b11001011 %
1#
#2045
0#
#2050
b11001100 4
b11001100 2
b11001100 %
1#
#2055
0#
#2060
b11001101 2
b11001101 4
b11001101 %
1#
#2065
0#
#2070
b11001110 4
b11001110 2
b11001110 %
1#
#2075
0#
#2080
b11001111 2
b11001111 4
b11001111 %
1#
#2085
0#
#2090
b11010000 4
b11010000 2
b11010000 %
1#
#2095
0#
#2100
b11010001 2
b11010001 4
b11010001 %
1#
#2105
0#
#2110
b11010010 4
b11010010 2
b11010010 %
1#
#2115
0#
#2120
b11010011 2
b11010011 4
b11010011 %
1#
#2125
0#
#2130
b11010100 4
b11010100 2
b11010100 %
1#
#2135
0#
#2140
b11010101 2
b11010101 4
b11010101 %
1#
#2145
0#
#2150
b11010110 4
b11010110 2
b11010110 %
1#
#2155
0#
#2160
b11010111 2
b11010111 4
b11010111 %
1#
#2165
0#
#2170
b11011000 4
b11011000 2
b11011000 %
1#
#2175
0#
#2180
b11011001 2
b11011001 4
b11011001 %
1#
#2185
0#
#2190
b11011010 4
b11011010 2
b11011010 %
1#
#2195
0#
#2200
b11011011 2
b11011011 4
b11011011 %
1#
#2205
0#
#2210
b11011100 4
b11011100 2
b11011100 %
1#
#2215
0#
#2220
b11011101 2
b11011101 4
b11011101 %
1#
#2225
0#
#2230
b11011110 4
b11011110 2
b11011110 %
1#
#2235
0#
#2240
b11011111 2
b11011111 4
b11011111 %
1#
#2245
0#
#2250
b11100000 4
b11100000 2
b11100000 %
1#
#2255
0#
#2260
b11100001 2
b11100001 4
b11100001 %
1#
#2265
0#
#2270
b11100010 4
b11100010 2
b11100010 %
1#
#2275
0#
#2280
b11100011 2
b11100011 4
b11100011 %
1#
#2285
0#
#2290
b11100100 4
b11100100 2
b11100100 %
1#
#2295
0#
#2300
b11100101 2
b11100101 4
b11100101 %
1#
#2305
0#
#2310
b11100110 4
b11100110 2
b11100110 %
1#
#2315
0#
#2320
b11100111 2
b11100111 4
b11100111 %
1#
#2325
0#
#2330
b11101000 4
b11101000 2
b11101000 %
1#
#2335
0#
#2340
b11101001 2
b11101001 4
b11101001 %
1#
#2345
0#
#2350
b11101010 4
b11101010 2
b11101010 %
1#
#2355
0#
#2360
b11101011 2
b11101011 4
b11101011 %
1#
#2365
0#
#2370
b11101100 4
b11101100 2
b11101100 %
1#
#2375
0#
#2380
b11101101 2
b11101101 4
b11101101 %
1#
#2385
0#
#2390
b11101110 4
b11101110 2
b11101110 %
1#
#2395
0#
#2400
b11101111 2
b11101111 4
b11101111 %
1#
#2405
0#
#2410
b11110000 4
b11110000 2
b11110000 %
1#
#2415
0#
#2420
b11110001 2
b11110001 4
b11110001 %
1#
#2425
0#
#2430
b11110010 4
b11110010 2
b11110010 %
1#
#2435
0#
#2440
b11110011 2
b11110011 4
b11110011 %
1#
#2445
0#
#2450
b11110100 4
b11110100 2
b11110100 %
1#
#2455
0#
#2460
b11110101 2
b11110101 4
b11110101 %
1#
#2465
0#
#2470
b11110110 4
b11110110 2
b11110110 %
1#
#2475
0#
#2480
b11110111 2
b11110111 4
b11110111 %
1#
#2485
0#
#2490
b11111000 4
b11111000 2
b11111000 %
1#
#2495
0#
#2500
b11111001 2
b11111001 4
b11111001 %
1#
#2505
0#
#2510
b11111010 4
b11111010 2
b11111010 %
1#
#2515
0#
#2520
b11111011 2
b11111011 4
b11111011 %
1#
#2525
0#
#2530
b11111100 4
b11111100 2
b11111100 %
1#
#2535
0#
#2540
b11111101 2
b11111101 4
b11111101 %
1#
#2545
0#
#2550
b11111110 4
b11111110 2
b11111110 %
1#
#2555
0#
#2560
b11111111 2
b11111111 4
b11111111 %
1#
#2565
0#
#2570
b100000000 4
b100000000 2
b100000000 %
1#
#2575
0#
#2580
b100000001 2
b100000001 4
b100000001 %
1#
#2585
0#
#2590
b100000010 4
b100000010 2
b100000010 %
1#
#2595
0#
#2600
b100000011 2
b100000011 4
b100000011 %
1#
#2605
0#
#2610
b100000100 4
b100000100 2
b100000100 %
1#
#2615
0#
#2620
b100000101 2
b100000101 4
b100000101 %
1#
#2625
0#
#2630
b100000110 4
b100000110 2
b100000110 %
1#
#2635
0#
#2640
b100000111 2
b100000111 4
b100000111 %
1#
#2645
0#
#2650
b100001000 4
b100001000 2
b100001000 %
1#
#2655
0#
#2660
b100001001 2
b100001001 4
b100001001 %
1#
#2665
0#
#2670
b100001010 4
b100001010 2
b100001010 %
1#
#2675
0#
#2680
b100001011 2
b100001011 4
b100001011 %
1#
#2685
0#
#2690
b100001100 4
b100001100 2
b100001100 %
1#
#2695
0#
#2700
b100001101 2
b100001101 4
b100001101 %
1#
#2705
0#
#2710
b100001110 4
b100001110 2
b100001110 %
1#
#2715
0#
#2720
b100001111 2
b100001111 4
b100001111 %
1#
#2725
0#
#2730
b100010000 4
b100010000 2
b100010000 %
1#
#2735
0#
#2740
b100010001 2
b100010001 4
b100010001 %
1#
#2745
0#
#2750
b100010010 4
b100010010 2
b100010010 %
1#
#2755
0#
#2760
b100010011 2
b100010011 4
b100010011 %
1#
#2765
0#
#2770
b100010100 4
b100010100 2
b100010100 %
1#
#2775
0#
#2780
b100010101 2
b100010101 4
b100010101 %
1#
#2785
0#
#2790
b100010110 4
b100010110 2
b100010110 %
1#
#2795
0#
#2800
b100010111 2
b100010111 4
b100010111 %
1#
#2805
0#
#2810
b100011000 4
b100011000 2
b100011000 %
1#
#2815
0#
#2820
b100011001 2
b100011001 4
b100011001 %
1#
#2825
0#
#2830
b100011010 4
b100011010 2
b100011010 %
1#
#2835
0#
#2840
b100011011 2
b100011011 4
b100011011 %
1#
#2845
0#
#2850
b100011100 4
b100011100 2
b100011100 %
1#
#2855
0#
#2860
b100011101 2
b100011101 4
b100011101 %
1#
#2865
0#
#2870
b100011110 4
b100011110 2
b100011110 %
1#
#2875
0#
#2880
b100011111 2
b100011111 4
b100011111 %
1#
#2885
0#
#2890
b100100000 4
b100100000 2
b100100000 %
1#
#2895
0#
#2900
b100100001 2
b100100001 4
b100100001 %
1#
#2905
0#
#2910
b100100010 4
b100100010 2
b100100010 %
1#
#2915
0#
#2920
b100100011 2
b100100011 4
b100100011 %
1#
#2925
0#
#2930
b100100100 4
b100100100 2
b100100100 %
1#
