comprehensive/src/time_divider.v
module time_divider 
#(
    parameter ratio=2
)
(
    input i_clk,
    input rst_n,
    output o_clk
);
    //registers definitions
    reg [31:0]count;
    integer lim=ratio/2;
    //combinational circuits
    assign o_clk=count>=lim?1'b1:1'b0;
    //counting
    always @(posedge i_clk or negedge rst_n) begin
        if(!rst_n) begin
            count<=32'b0;
        end
        else begin
            if(count<lim)begin
                count<=count+1;
            end
            else begin
                count<=32'b0;
            end
        end
    end
endmodule

I2C_driver/src/I2C_frame_output.v
//control the I2C_byte_output to output a data frame to manipulate the register
//data frame 
module I2C_frame_output
#(
    parameter slave_addr=16'h40 //default address of the slave board
)
(
    //control signals
    input i_clk, //the global clock signal to generate the I2C clk
    input i_rst_n, //reset signal enables when low,only once after power up
    input [7:0]i_register_addr, //the address of the register to manipulate
    input [7:0]i_data, //the data to send 
    input i_start, //posedge to start sending
    output o_complete, //high when complete
    //I2C interfac
    output reg io_SDA, //the signal line of I2C
    output reg o_SCL //the clk signal for I2C
);
//=======local parameters definition
    localparam state_idle = 30;
    localparam state_start = 29;
    localparam state_slave_h = 28;
    localparam state_slave_l = 22;
    localparam state_rw1 = 21;
    localparam state_ack1 = 20;
    localparam state_reg_adr_h = 19;
    localparam state_reg_adr_l = 12;
    localparam state_ack2 = 11;
    localparam state_data_h=10;
    localparam state_data_l=3;
    localparam state_ack=2;
    localparam state_stop = 1; //reset the data,wait for the negedge of start to change to next one
    localparam state_waitforstart= 0; //wait for high level of start
    // localparam state_idle = 0;
//=======wire definition
    wire controller_clk; //generated clock for I2C controller
//======register definition
    reg out_clock; //output clock for I2C sclk
    reg [5:0]current_state;
    reg finished;
    reg rst_complete;
//=======combinational circuits
    // assign o_SCL=(i_start==1)?1:out_clk; 
    //pull the scl up when it is not sending
    assign o_complete=(current_state==state_stop)&&(rst_complete);
//=======instantiation
    //generate the clock output for the I2C
    time_divider
    #(2) //1 for test
    clk_generator
    (
        .i_clk(i_clk),
        .rst_n(i_rst_n),
        .o_clk(controller_clk
)
    );
//======sequential logic
    //main loop for FSM switching
    always @(posedge controller_clk or negedge i_rst_n or negedge i_start) begin
        if(!i_rst_n) begin
            current_state<=state_waitforstart;
        end
        else begin
            if(current_state==state_stop) begin
                if(!i_start) begin
                    current_state=state_waitforstart;
                end
            end
            else if(current_state==state_waitforstart)begin
                if(i_start) begin
                    current_state=state_start;
                end
            end
            else current_state=current_state-1;
        end
    end
    //data and clk generate
    always @(controller_clk) begin
        if(!i_rst_n)begin
            io_SDA<=1;
            o_SCL<=1;
        end
        else begin
            if(controller_clk) begin
                //high level
                //update data first
                if(current_state==state_start) begin
                    //start signal
                    io_SDA<=0;
                    rst_complete <= 0;
                end
                else if (current_state>=state_slave_h&&current_state<=state_slave_l) begin
                    //slave address
                    io_SDA<=io_SDA<=slave_addr[current_state-22];
                end
                else if (current_state==state_ack1||current_state==state_ack2) begin
                    //acknoknowledge
                    io_SDA<=1'bz;
                end
                else if (current_state==state_rw1) begin
                    //read write control
                    io_SDA<=0; //write enable
                end
                else if(current_state<=state_reg_adr_h&&current_state>=state_reg_adr_l) begin
                    //register address
                    io_SDA<=i_register_addr[current_state-12];
                end
                else if(current_state<=state_data_h&&current_state>=state_data_l) begin
                    //output data
                    io_SDA<=i_data[current_state-3];
                end
                else if(current_state==state_stop||current_state==state_idle)begin
                    //stop
                    io_SDA<=1;
                    rst_complete <=1;
                end
                //update clock
                o_SCL=0;
            end
            else begin
                //low level
                o_SCL=1;
            end
        end
    end

endmodule

I2C_driver/src/servo_driver.v

module servo_driver (
    //control signals
    input i_clk, //clock for servo controller
    input i_rst_n, //reset signal enables when low
    //I2C frame output interface
    output io_SDA,
    output o_SCL
);
//======parameter definitions
    //states definitnions
    localparam state_set_mode_sleep=0;
    localparam state_setf=1;
    localparam state_set_mode_run=2;
    localparam state_update = 3;
    localparam state_send_on_h = 4;
    localparam state_send_on_l = 5;
    localparam state_send_off_h = 6;
    localparam state_send_off_l = 7;
    localparam state_wait = 8;
    //data frme definitions
    //mode setting
    localparam mode_reg_addr = 8'h00;
    localparam mode_sleep_data = 8'h10;
    localparam mode_run_data = 8'h00;
    //frequency setting
    localparam frequency_reg_addr = 8'hfe;
    localparam frequency_data = 8'h79; //50Hz
    //data setting
    localparam pwm0_on_h_data = 8'h00;
    localparam pwm0_on_l_data = 8'h00;
    localparam pwm0_off_h_data = 8'h00;
    localparam pwm0_off_l_data = 8'hd8;
    //reg addr setting
    localparam pwm0_on_l_addr = 8'd6;
    localparam pwm0_on_h_addr = 8'd7;
    localparam pwm0_off_l_addr = 8'd8;
    localparam pwm0_off_h_addr = 8'd9;

//======register definitions
    reg [3:0] current_state;
    reg [3:0] next_state; //for the waiting state
    reg start_flag;
    reg [7:0] gen_register_addr;
    reg [7:0] gen_data;
//======wire definitions
    wire controller_clk;
    wire complete; //compelete signal from frame output
//======instantiation
    //generate the clk signal for controller
    time_divider
    #(2)
    controller_clk_generator
    (
        .i_clk(i_clk),
        .rst_n(i_rst_n),
        .o_clk(controller_clk)
    );
    I2C_frame_output
    I2C_driver
    (
        .i_clk(i_clk),
        .i_rst_n(i_rst_n),
        .i_register_addr(gen_register_addr),
        .i_data(gen_data),
        .i_start(start_flag),
        .o_complete(complete),
        .io_SDA(io_SDA),
        .o_SCL(o_SCL)
    );
//======sequencial circuit
    //for mst
    always @(posedge i_clk or negedge i_rst_n) begin
        if(!i_rst_n) begin
            current_state=state_set_mode_sleep;
            start_flag=0;
        end
        else begin
            case (current_state)
                state_set_mode_sleep: begin
                    gen_data=mode_sleep_data;
                    gen_register_addr=mode_reg_addr;
                    send_byte;
                    current_state=state_setf;
                end
                state_setf: begin
                    gen_data=frequency_data;
                    gen_register_addr=frequency_reg_addr;
                    send_byte;
                    current_state=state_set_mode_run;
                end
                state_set_mode_run: begin
                    gen_data=mode_run_data;
                    gen_register_addr=mode_reg_addr;
                    send_byte;
                    current_state=state_update;
                end
                state_update: begin
                    current_state=state_send_on_h;
                end
                state_send_on_h:begin
                    gen_data=pwm0_on_h_data;
                    gen_register_addr=pwm0_on_h_addr;
                    send_byte;
                    current_state=state_send_on_l;
                end
                state_send_on_l:begin
                    gen_data=pwm0_on_l_data;
                    gen_register_addr=pwm0_on_l_addr;
                    send_byte;
                    current_state=state_send_off_h;
                end
                state_send_off_h:begin
                    gen_data=pwm0_off_h_data;
                    gen_register_addr=pwm0_off_h_addr;
                    send_byte;
                    current_state=state_send_off_l;
                end
                state_send_off_l:begin
                    gen_data=pwm0_on_l_data;
                    gen_register_addr=pwm0_on_l_addr;
                    send_byte;
                    current_state=state_update;
                end
                default:;
            endcase
        end
    end
//======task definitions
task send_byte;
    begin
        start_flag=1;
        @(posedge complete)
        @(posedge i_clk)
        start_flag=0;
    end
endtask
endmodule

I2C_driver/src/servo_driver_tb.v
module servo_driver_tb ();
    //control signals
    reg i_clk; //clock for servo controller
    reg i_rst_n; //reset signal enables when low
    //I2C frame output interface
    wire io_SDA;
    wire o_SCL;
    servo_driver servo_inst
    (
        .i_clk(i_clk),
        .i_rst_n(i_rst_n),
        .io_SDA(io_SDA),
        .o_SCL(o_SCL)
    );
    integer i;
    initial begin
        i_rst_n=1;
        i_clk=0;
        #5
        i_rst_n=0;
        #5
        i_rst_n=1;
        for (i = 0;i<600 ;i=i+1 ) begin
            #5
            i_clk=0;
            #5
            i_clk=1;
        end
    end
    initial begin   
        $dumpfile("./build/wave.vcd");  // 指定VCD文件的名字为wave.vcd，仿真信息将记录到此文件
        $dumpvars(0, servo_driver_tb);  // 指定层次数为0，则tb_code 模块及其下面各层次的所有信号将被记录
        #10000 $finish;
    end
endmodule

I2C_driver/build/wave.vcd
$date
	Mon Jan  3 20:15:33 2022
$end
$version
	Icarus Verilog
$end
$timescale
	1s
$end
$scope module servo_driver_tb $end
$var wire 1 ! o_SCL $end
$var wire 1 " io_SDA $end
$var reg 1 # i_clk $end
$var reg 1 $ i_rst_n $end
$var integer 32 % i [31:0] $end
$scope module servo_inst $end
$var wire 1 # i_clk $end
$var wire 1 $ i_rst_n $end
$var wire 1 ! o_SCL $end
$var wire 1 " io_SDA $end
$var wire 1 & controller_clk $end
$var wire 1 ' complete $end
$var reg 4 ( current_state [3:0] $end
$var reg 8 ) gen_data [7:0] $end
$var reg 8 * gen_register_addr [7:0] $end
$var reg 1 + start_flag $end
$scope module I2C_driver $end
$var wire 1 # i_clk $end
$var wire 8 , i_data [7:0] $end
$var wire 8 - i_register_addr [7:0] $end
$var wire 1 $ i_rst_n $end
$var wire 1 + i_start $end
$var wire 1 ' o_complete $end
$var wire 1 . controller_clk $end
$var reg 6 / current_state [5:0] $end
$var reg 1 " io_SDA $end
$var reg 1 ! o_SCL $end
$var reg 1 0 rst_complete $end
$scope module clk_generator $end
$var wire 1 # i_clk $end
$var wire 1 $ rst_n $end
$var wire 1 . o_clk $end
$var reg 32 1 count [31:0] $end
$var integer 32 2 lim [31:0] $end
$upscope $end
$upscope $end
$scope module controller_clk_generator $end
$var wire 1 # i_clk $end
$var wire 1 $ rst_n $end
$var wire 1 & o_clk $end
$var reg 32 3 count [31:0] $end
$var integer 32 4 lim [31:0] $end
$upscope $end
$scope task send_byte $end
$upscope $end
$upscope $end
$upscope $end
$enddefinitions $end
#0
$dumpvars
b1 4
bx 3
b1 2
bx 1
x0
bx /
x.
bx -
bx ,
x+
bx *
bx )
bx (
x'
x&
bx %
1$
0#
x"
1!
$end
#5
1"
0&
0.
0'
b0 3
b0 1
b0 /
0+
b0 (
0$
#10
b0 %
1$
#20
b11101 /
0!
1.
1&
b1 1
b1 3
1+
b0 *
b0 -
b10000 )
b10000 ,
b1 %
1#
#25
0#
#30
1!
0&
0.
b0 3
b0 1
b10 %
1#
#35
0#
#40
00
0"
b11100 /
0!
1.
1&
b1 1
b1 3
b11 %
1#
#45
0#
#50
1!
0&
0.
b0 3
b0 1
b100 %
1#
#55
0#
#60
b11011 /
0!
1.
1&
b1 1
b1 3
b101 %
1#
#65
0#
#70
1!
0&
0.
b0 3
b0 1
b110 %
1#
#75
0#
#80
b11010 /
0!
1.
1&
b1 1
b1 3
b111 %
1#
#85
0#
#90
1!
0&
0.
b0 3
b0 1
b1000 %
1#
#95
0#
#100
b11001 /
0!
1.
1&
b1 1
b1 3
b1001 %
1#
#105
0#
#110
1!
0&
0.
b0 3
b0 1
b1010 %
1#
#115
0#
#120
b11000 /
0!
1.
1&
b1 1
b1 3
b1011 %
1#
#125
0#
#130
1!
0&
0.
b0 3
b0 1
b1100 %
1#
#135
0#
#140
b10111 /
0!
1.
1&
b1 1
b1 3
b1101 %
1#
#145
0#
#150
1!
0&
0.
b0 3
b0 1
b1110 %
1#
#155
0#
#160
b10110 /
0!
1.
1&
b1 1
b1 3
b1111 %
1#
#165
0#
#170
1!
0&
0.
b0 3
b0 1
b10000 %
1#
#175
0#
#180
b10101 /
0!
1.
1&
b1 1
b1 3
b10001 %
1#
#185
0#
#190
1!
0&
0.
b0 3
b0 1
b10010 %
1#
#195
0#
#200
b10100 /
0!
1.
1&
b1 1
b1 3
b10011 %
1#
#205
0#
#210
1!
0&
0.
b0 3
b0 1
b10100 %
1#
#215
0#
#220
z"
b10011 /
0!
1.
1&
b1 1
b1 3
b10101 %
1#
#225
0#
#230
1!
0&
0.
b0 3
b0 1
b10110 %
1#
#235
0#
#240
0"
b10010 /
0!
1.
1&
b1 1
b1 3
b10111 %
1#
#245
0#
#250
1!
0&
0.
b0 3
b0 1
b11000 %
1#
#255
0#
#260
b10001 /
0!
1.
1&
b1 1
b1 3
b11001 %
1#
#265
0#
#270
1!
0&
0.
b0 3
b0 1
b11010 %
1#
#275
0#
#280
b10000 /
0!
1.
1&
b1 1
b1 3
b11011 %
1#
#285
0#
#290
1!
0&
0.
b0 3
b0 1
b11100 %
1#
#295
0#
#300
b1111 /
0!
1.
1&
b1 1
b1 3
b11101 %
1#
#305
0#
#310
1!
0&
0.
b0 3
b0 1
b11110 %
1#
#315
0#
#320
b1110 /
0!
1.
1&
b1 1
b1 3
b11111 %
1#
#325
0#
#330
1!
0&
0.
b0 3
b0 1
b100000 %
1#
#335
0#
#340
b1101 /
0!
1.
1&
b1 1
b1 3
b100001 %
1#
#345
0#
#350
1!
0&
0.
b0 3
b0 1
b100010 %
1#
#355
0#
#360
b1100 /
0!
1.
1&
b1 1
b1 3
b100011 %
1#
#365
0#
#370
1!
0&
0.
b0 3
b0 1
b100100 %
1#
#375
0#
#380
b1011 /
0!
1.
1&
b1 1
b1 3
b100101 %
1#
#385
0#
#390
1!
0&
0.
b0 3
b0 1
b100110 %
1#
#395
0#
#400
z"
b1010 /
0!
1.
1&
b1 1
b1 3
b100111 %
1#
#405
0#
#410
1!
0&
0.
b0 3
b0 1
b101000 %
1#
#415
0#
#420
0"
b1001 /
0!
1.
1&
b1 1
b1 3
b101001 %
1#
#425
0#
#430
1!
0&
0.
b0 3
b0 1
b101010 %
1#
#435
0#
#440
b1000 /
0!
1.
1&
b1 1
b1 3
b101011 %
1#
#445
0#
#450
1!
0&
0.
b0 3
b0 1
b101100 %
1#
#455
0#
#460
b111 /
0!
1.
1&
b1 1
b1 3
b101101 %
1#
#465
0#
#470
1!
0&
0.
b0 3
b0 1
b101110 %
1#
#475
0#
#480
1"
b110 /
0!
1.
1&
b1 1
b1 3
b101111 %
1#
#485
0#
#490
1!
0&
0.
b0 3
b0 1
b110000 %
1#
#495
0#
#500
0"
b101 /
0!
1.
1&
b1 1
b1 3
b110001 %
1#
#505
0#
#510
1!
0&
0.
b0 3
b0 1
b110010 %
1#
#515
0#
#520
b100 /
0!
1.
1&
b1 1
b1 3
b110011 %
1#
#525
0#
#530
1!
0&
0.
b0 3
b0 1
b110100 %
1#
#535
0#
#540
b11 /
0!
1.
1&
b1 1
b1 3
b110101 %
1#
#545
0#
#550
1!
0&
0.
b0 3
b0 1
b110110 %
1#
#555
0#
#560
b10 /
0!
1.
1&
b1 1
b1 3
b110111 %
1#
#565
0#
#570
1!
0&
0.
b0 3
b0 1
b111000 %
1#
#575
0#
#580
b1 /
0!
1.
1&
b1 1
b1 3
b111001 %
1#
#585
0#
#590
1!
0&
0.
b0 3
b0 1
b111010 %
1#
#595
0#
#600
1'
10
1"
0!
1.
1&
b1 1
b1 3
b111011 %
1#
#605
0#
#610
1!
0&
0.
b0 3
b0 1
0'
b0 /
b1 (
0+
b111100 %
1#
#615
0#
#620
b11101 /
0!
1.
1&
b1 1
b1 3
1+
b11111110 *
b11111110 -
b1111001 )
b1111001 ,
b111101 %
1#
#625
0#
#630
1!
0&
0.
b0 3
b0 1
b111110 %
1#
#635
0#
#640
00
0"
b11100 /
0!
1.
1&
b1 1
b1 3
b111111 %
1#
#645
0#
#650
1!
0&
0.
b0 3
b0 1
b1000000 %
1#
#655
0#
#660
b11011 /
0!
1.
1&
b1 1
b1 3
b1000001 %
1#
#665
0#
#670
1!
0&
0.
b0 3
b0 1
b1000010 %
1#
#675
0#
#680
b11010 /
0!
1.
1&
b1 1
b1 3
b1000011 %
1#
#685
0#
#690
1!
0&
0.
b0 3
b0 1
b1000100 %
1#
#695
0#
#700
b11001 /
0!
1.
1&
b1 1
b1 3
b1000101 %
1#
#705
0#
#710
1!
0&
0.
b0 3
b0 1
b1000110 %
1#
#715
0#
#720
b11000 /
0!
1.
1&
b1 1
b1 3
b1000111 %
1#
#725
0#
#730
1!
0&
0.
b0 3
b0 1
b1001000 %
1#
#735
0#
#740
b10111 /
0!
1.
1&
b1 1
b1 3
b1001001 %
1#
#745
0#
#750
1!
0&
0.
b0 3
b0 1
b1001010 %
1#
#755
0#
#760
b10110 /
0!
1.
1&
b1 1
b1 3
b1001011 %
1#
#765
0#
#770
1!
0&
0.
b0 3
b0 1
b1001100 %
1#
#775
0#
#780
b10101 /
0!
1.
1&
b1 1
b1 3
b1001101 %
1#
#785
0#
#790
1!
0&
0.
b0 3
b0 1
b1001110 %
1#
#795
0#
#800
b10100 /
0!
1.
1&
b1 1
b1 3
b1001111 %
1#
#805
0#
#810
1!
0&
0.
b0 3
b0 1
b1010000 %
1#
#815
0#
#820
z"
b10011 /
0!
1.
1&
b1 1
b1 3
b1010001 %
1#
#825
0#
#830
1!
0&
0.
b0 3
b0 1
b1010010 %
1#
#835
0#
#840
1"
b10010 /
0!
1.
1&
b1 1
b1 3
b1010011 %
1#
#845
0#
#850
1!
0&
0.
b0 3
b0 1
b1010100 %
1#
#855
0#
#860
b10001 /
0!
1.
1&
b1 1
b1 3
b1010101 %
1#
#865
0#
#870
1!
0&
0.
b0 3
b0 1
b1010110 %
1#
#875
0#
#880
b10000 /
0!
1.
1&
b1 1
b1 3
b1010111 %
1#
#885
0#
#890
1!
0&
0.
b0 3
b0 1
b1011000 %
1#
#895
0#
#900
b1111 /
0!
1.
1&
b1 1
b1 3
b1011001 %
1#
#905
0#
#910
1!
0&
0.
b0 3
b0 1
b1011010 %
1#
#915
0#
#920
b1110 /
0!
1.
1&
b1 1
b1 3
b1011011 %
1#
#925
0#
#930
1!
0&
0.
b0 3
b0 1
b1011100 %
1#
#935
0#
#940
b1101 /
0!
1.
1&
b1 1
b1 3
b1011101 %
1#
#945
0#
#950
1!
0&
0.
b0 3
b0 1
b1011110 %
1#
#955
0#
#960
b1100 /
0!
1.
1&
b1 1
b1 3
b1011111 %
1#
#965
0#
#970
1!
0&
0.
b0 3
b0 1
b1100000 %
1#
#975
0#
#980
0"
b1011 /
0!
1.
1&
b1 1
b1 3
b1100001 %
1#
#985
0#
#990
1!
0&
0.
b0 3
b0 1
b1100010 %
1#
#995
0#
#1000
z"
b1010 /
0!
1.
1&
b1 1
b1 3
b1100011 %
1#
#1005
0#
#1010
1!
0&
0.
b0 3
b0 1
b1100100 %
1#
#1015
0#
#1020
0"
b1001 /
0!
1.
1&
b1 1
b1 3
b1100101 %
1#
#1025
0#
#1030
1!
0&
0.
b0 3
b0 1
b1100110 %
1#
#1035
0#
#1040
1"
b1000 /
0!
1.
1&
b1 1
b1 3
b1100111 %
1#
#1045
0#
#1050
1!
0&
0.
b0 3
b0 1
b1101000 %
1#
#1055
0#
#1060
b111 /
0!
1.
1&
b1 1
b1 3
b1101001 %
1#
#1065
0#
#1070
1!
0&
0.
b0 3
b0 1
b1101010 %
1#
#1075
0#
#1080
b110 /
0!
1.
1&
b1 1
b1 3
b1101011 %
1#
#1085
0#
#1090
1!
0&
0.
b0 3
b0 1
b1101100 %
1#
#1095
0#
#1100
b101 /
0!
1.
1&
b1 1
b1 3
b1101101 %
1#
#1105
0#
#1110
1!
0&
0.
b0 3
b0 1
b1101110 %
1#
#1115
0#
#1120
0"
b100 /
0!
1.
1&
b1 1
b1 3
b1101111 %
1#
#1125
0#
#1130
1!
0&
0.
b0 3
b0 1
b1110000 %
1#
#1135
0#
#1140
b11 /
0!
1.
1&
b1 1
b1 3
b1110001 %
1#
#1145
0#
#1150
1!
0&
0.
b0 3
b0 1
b1110010 %
1#
#1155
0#
#1160
1"
b10 /
0!
1.
1&
b1 1
b1 3
b1110011 %
1#
#1165
0#
#1170
1!
0&
0.
b0 3
b0 1
b1110100 %
1#
#1175
0#
#1180
b1 /
0!
1.
1&
b1 1
b1 3
b1110101 %
1#
#1185
0#
#1190
1!
0&
0.
b0 3
b0 1
b1110110 %
1#
#1195
0#
#1200
1'
10
0!
1.
1&
b1 1
b1 3
b1110111 %
1#
#1205
0#
#1210
1!
0&
0.
b0 3
b0 1
0'
b0 /
b10 (
0+
b1111000 %
1#
#1215
0#
#1220
b11101 /
0!
1.
1&
b1 1
b1 3
1+
b0 *
b0 -
b0 )
b0 ,
b1111001 %
1#
#1225
0#
#1230
1!
0&
0.
b0 3
b0 1
b1111010 %
1#
#1235
0#
#1240
00
0"
b11100 /
0!
1.
1&
b1 1
b1 3
b1111011 %
1#
#1245
0#
#1250
1!
0&
0.
b0 3
b0 1
b1111100 %
1#
#1255
0#
#1260
b11011 /
0!
1.
1&
b1 1
b1 3
b1111101 %
1#
#1265
0#
#1270
1!
0&
0.
b0 3
b0 1
b1111110 %
1#
#1275
0#
#1280
b11010 /
0!
1.
1&
b1 1
b1 3
b1111111 %
1#
#1285
0#
#1290
1!
0&
0.
b0 3
b0 1
b10000000 %
1#
#1295
0#
#1300
b11001 /
0!
1.
1&
b1 1
b1 3
b10000001 %
1#
#1305
0#
#1310
1!
0&
0.
b0 3
b0 1
b10000010 %
1#
#1315
0#
#1320
b11000 /
0!
1.
1&
b1 1
b1 3
b10000011 %
1#
#1325
0#
#1330
1!
0&
0.
b0 3
b0 1
b10000100 %
1#
#1335
0#
#1340
b10111 /
0!
1.
1&
b1 1
b1 3
b10000101 %
1#
#1345
0#
#1350
1!
0&
0.
b0 3
b0 1
b10000110 %
1#
#1355
0#
#1360
b10110 /
0!
1.
1&
b1 1
b1 3
b10000111 %
1#
#1365
0#
#1370
1!
0&
0.
b0 3
b0 1
b10001000 %
1#
#1375
0#
#1380
b10101 /
0!
1.
1&
b1 1
b1 3
b10001001 %
1#
#1385
0#
#1390
1!
0&
0.
b0 3
b0 1
b10001010 %
1#
#1395
0#
#1400
b10100 /
0!
1.
1&
b1 1
b1 3
b10001011 %
1#
#1405
0#
#1410
1!
0&
0.
b0 3
b0 1
b10001100 %
1#
#1415
0#
#1420
z"
b10011 /
0!
1.
1&
b1 1
b1 3
b10001101 %
1#
#1425
0#
#1430
1!
0&
0.
b0 3
b0 1
b10001110 %
1#
#1435
0#
#1440
0"
b10010 /
0!
1.
1&
b1 1
b1 3
b10001111 %
1#
#1445
0#
#1450
1!
0&
0.
b0 3
b0 1
b10010000 %
1#
#1455
0#
#1460
b10001 /
0!
1.
1&
b1 1
b1 3
b10010001 %
1#
#1465
0#
#1470
1!
0&
0.
b0 3
b0 1
b10010010 %
1#
#1475
0#
#1480
b10000 /
0!
1.
1&
b1 1
b1 3
b10010011 %
1#
#1485
0#
#1490
1!
0&
0.
b0 3
b0 1
b10010100 %
1#
#1495
0#
#1500
b1111 /
0!
1.
1&
b1 1
b1 3
b10010101 %
1#
#1505
0#
#1510
1!
0&
0.
b0 3
b0 1
b10010110 %
1#
#1515
0#
#1520
b1110 /
0!
1.
1&
b1 1
b1 3
b10010111 %
1#
#1525
0#
#1530
1!
0&
0.
b0 3
b0 1
b10011000 %
1#
#1535
0#
#1540
b1101 /
0!
1.
1&
b1 1
b1 3
b10011001 %
1#
#1545
0#
#1550
1!
0&
0.
b0 3
b0 1
b10011010 %
1#
#1555
0#
#1560
b1100 /
0!
1.
1&
b1 1
b1 3
b10011011 %
1#
#1565
0#
#1570
1!
0&
0.
b0 3
b0 1
b10011100 %
1#
#1575
0#
#1580
b1011 /
0!
1.
1&
b1 1
b1 3
b10011101 %
1#
#1585
0#
#1590
1!
0&
0.
b0 3
b0 1
b10011110 %
1#
#1595
0#
#1600
z"
b1010 /
0!
1.
1&
b1 1
b1 3
b10011111 %
1#
#1605
0#
#1610
1!
0&
0.
b0 3
b0 1
b10100000 %
1#
#1615
0#
#1620
0"
b1001 /
0!
1.
1&
b1 1
b1 3
b10100001 %
1#
#1625
0#
#1630
1!
0&
0.
b0 3
b0 1
b10100010 %
1#
#1635
0#
#1640
b1000 /
0!
1.
1&
b1 1
b1 3
b10100011 %
1#
#1645
0#
#1650
1!
0&
0.
b0 3
b0 1
b10100100 %
1#
#1655
0#
#1660
b111 /
0!
1.
1&
b1 1
b1 3
b10100101 %
1#
#1665
0#
#1670
1!
0&
0.
b0 3
b0 1
b10100110 %
1#
#1675
0#
#1680
b110 /
0!
1.
1&
b1 1
b1 3
b10100111 %
1#
#1685
0#
#1690
1!
0&
0.
b0 3
b0 1
b10101000 %
1#
#1695
0#
#1700
b101 /
0!
1.
1&
b1 1
b1 3
b10101001 %
1#
#1705
0#
#1710
1!
0&
0.
b0 3
b0 1
b10101010 %
1#
#1715
0#
#1720
b100 /
0!
1.
1&
b1 1
b1 3
b10101011 %
1#
#1725
0#
#1730
1!
0&
0.
b0 3
b0 1
b10101100 %
1#
#1735
0#
#1740
b11 /
0!
1.
1&
b1 1
b1 3
b10101101 %
1#
#1745
0#
#1750
1!
0&
0.
b0 3
b0 1
b10101110 %
1#
#1755
0#
#1760
b10 /
0!
1.
1&
b1 1
b1 3
b10101111 %
1#
#1765
0#
#1770
1!
0&
0.
b0 3
b0 1
b10110000 %
1#
#1775
0#
#1780
b1 /
0!
1.
1&
b1 1
b1 3
b10110001 %
1#
#1785
0#
#1790
1!
0&
0.
b0 3
b0 1
b10110010 %
1#
#1795
0#
#1800
1'
10
1"
0!
1.
1&
b1 1
b1 3
b10110011 %
1#
#1805
0#
#1810
1!
0&
0.
b0 3
b0 1
0'
b0 /
b11 (
0+
b10110100 %
1#
#1815
0#
#1820
0!
1.
1&
b1 1
b1 3
b100 (
b10110101 %
1#
#1825
0#
#1830
1!
0&
0.
b0 3
b0 1
1+
b111 *
b111 -
b10110110 %
1#
#1835
0#
#1840
b11101 /
0!
1.
1&
b1 1
b1 3
b10110111 %
1#
#1845
0#
#1850
1!
0&
0.
b0 3
b0 1
b10111000 %
1#
#1855
0#
#1860
00
0"
b11100 /
0!
1.
1&
b1 1
b1 3
b10111001 %
1#
#1865
0#
#1870
1!
0&
0.
b0 3
b0 1
b10111010 %
1#
#1875
0#
#1880
b11011 /
0!
1.
1&
b1 1
b1 3
b10111011 %
1#
#1885
0#
#1890
1!
0&
0.
b0 3
b0 1
b10111100 %
1#
#1895
0#
#1900
b11010 /
0!
1.
1&
b1 1
b1 3
b10111101 %
1#
#1905
0#
#1910
1!
0&
0.
b0 3
b0 1
b10111110 %
1#
#1915
0#
#1920
b11001 /
0!
1.
1&
b1 1
b1 3
b10111111 %
1#
#1925
0#
#1930
1!
0&
0.
b0 3
b0 1
b11000000 %
1#
#1935
0#
#1940
b11000 /
0!
1.
1&
b1 1
b1 3
b11000001 %
1#
#1945
0#
#1950
1!
0&
0.
b0 3
b0 1
b11000010 %
1#
#1955
0#
#1960
b10111 /
0!
1.
1&
b1 1
b1 3
b11000011 %
1#
#1965
0#
#1970
1!
0&
0.
b0 3
b0 1
b11000100 %
1#
#1975
0#
#1980
b10110 /
0!
1.
1&
b1 1
b1 3
b11000101 %
1#
#1985
0#
#1990
1!
0&
0.
b0 3
b0 1
b11000110 %
1#
#1995
0#
#2000
b10101 /
0!
1.
1&
b1 1
b1 3
b11000111 %
1#
#2005
0#
#2010
1!
0&
0.
b0 3
b0 1
b11001000 %
1#
#2015
0#
#2020
b10100 /
0!
1.
1&
b1 1
b1 3
b11001001 %
1#
#2025
0#
#2030
1!
0&
0.
b0 3
b0 1
b11001010 %
1#
#2035
0#
#2040
z"
b10011 /
0!
1.
1&
b1 1
b1 3
b11001011 %
1#
#2045
0#
#2050
1!
0&
0.
b0 3
b0 1
b11001100 %
1#
#2055
0#
#2060
0"
b10010 /
0!
1.
1&
b1 1
b1 3
b11001101 %
1#
#2065
0#
#2070
1!
0&
0.
b0 3
b0 1
b11001110 %
1#
#2075
0#
#2080
b10001 /
0!
1.
1&
b1 1
b1 3
b11001111 %
1#
#2085
0#
#2090
1!
0&
0.
b0 3
b0 1
b11010000 %
1#
#2095
0#
#2100
b10000 /
0!
1.
1&
b1 1
b1 3
b11010001 %
1#
#2105
0#
#2110
1!
0&
0.
b0 3
b0 1
b11010010 %
1#
#2115
0#
#2120
b1111 /
0!
1.
1&
b1 1
b1 3
b11010011 %
1#
#2125
0#
#2130
1!
0&
0.
b0 3
b0 1
b11010100 %
1#
#2135
0#
#2140
b1110 /
0!
1.
1&
b1 1
b1 3
b11010101 %
1#
#2145
0#
#2150
1!
0&
0.
b0 3
b0 1
b11010110 %
1#
#2155
0#
#2160
1"
b1101 /
0!
1.
1&
b1 1
b1 3
b11010111 %
1#
#2165
0#
#2170
1!
0&
0.
b0 3
b0 1
b11011000 %
1#
#2175
0#
#2180
b1100 /
0!
1.
1&
b1 1
b1 3
b11011001 %
1#
#2185
0#
#2190
1!
0&
0.
b0 3
b0 1
b11011010 %
1#
#2195
0#
#2200
b1011 /
0!
1.
1&
b1 1
b1 3
b11011011 %
1#
#2205
0#
#2210
1!
0&
0.
b0 3
b0 1
b11011100 %
1#
#2215
0#
#2220
z"
b1010 /
0!
1.
1&
b1 1
b1 3
b11011101 %
1#
#2225
0#
#2230
1!
0&
0.
b0 3
b0 1
b11011110 %
1#
#2235
0#
#2240
0"
b1001 /
0!
1.
1&
b1 1
b1 3
b11011111 %
1#
#2245
0#
#2250
1!
0&
0.
b0 3
b0 1
b11100000 %
1#
#2255
0#
#2260
b1000 /
0!
1.
1&
b1 1
b1 3
b11100001 %
1#
#2265
0#
#2270
1!
0&
0.
b0 3
b0 1
b11100010 %
1#
#2275
0#
#2280
b111 /
0!
1.
1&
b1 1
b1 3
b11100011 %
1#
#2285
0#
#2290
1!
0&
0.
b0 3
b0 1
b11100100 %
1#
#2295
0#
#2300
b110 /
0!
1.
1&
b1 1
b1 3
b11100101 %
1#
#2305
0#
#2310
1!
0&
0.
b0 3
b0 1
b11100110 %
1#
#2315
0#
#2320
b101 /
0!
1.
1&
b1 1
b1 3
b11100111 %
1#
#2325
0#
#2330
1!
0&
0.
b0 3
b0 1
b11101000 %
1#
#2335
0#
#2340
b100 /
0!
1.
1&
b1 1
b1 3
b11101001 %
1#
#2345
0#
#2350
1!
0&
0.
b0 3
b0 1
b11101010 %
1#
#2355
0#
#2360
b11 /
0!
1.
1&
b1 1
b1 3
b11101011 %
1#
#2365
0#
#2370
1!
0&
0.
b0 3
b0 1
b11101100 %
1#
#2375
0#
#2380
b10 /
0!
1.
1&
b1 1
b1 3
b11101101 %
1#
#2385
0#
#2390
1!
0&
0.
b0 3
b0 1
b11101110 %
1#
#2395
0#
