VGA_test/vga_pineball/src/vga_driver.v
//the vga driver to display the data
module vga_driver
#(
	// VGA_1024_768_60fps_65MHz
	// Horizontal Parameter	( Pixel )
	parameter	H_DISP 	=	11'd1024, 
	parameter	H_FRONT	=	11'd24,	 
	parameter	H_SYNC 	=	11'd136,  
	parameter	H_BACK 	=	11'd160,   
	parameter	H_TOTAL	=	11'd1344, 
	// Virtical Parameter	( Line ) 
	parameter	V_DISP 	=	10'd768,  					
	parameter	V_FRONT	=	10'd3,   
	parameter	V_SYNC 	=	10'd6,    
	parameter	V_BACK 	=	10'd29,   
	parameter	V_TOTAL	=	10'd806  
)
(  	
	input			clk_vga,	// clock of 25MHz
	input			rst_n,     	// reset signal
	
	input	[11:0]	vga_data,
	output	[11:0]	vga_rgb,	// return the displayed colors to the connection
	output	reg		vga_hs,		// VGA管脚 行同步
	output	reg		vga_vs,		// VGA管脚 场同步
	
	output	[9:0]	vga_xpos,	// the X-axis of the pixel
	output	[9:0]	vga_ypos	// the Y-axis of the pixel
);	

//------------------------------------------
// 行同步信号发生器
reg [10:0] hcnt; 
always @ (posedge clk_vga or negedge rst_n)
begin
	if (!rst_n) begin
		hcnt <= 0;
		// $display("%h",vcnt);
	end
	else
		begin
        if (hcnt < H_TOTAL-1'b1)			
            hcnt <= hcnt + 1'b1;
        else
            hcnt <= 0;
		end
end 

always@(posedge clk_vga or negedge rst_n)
begin
	if(!rst_n)
		vga_hs <= 1;
	else
		begin
        if( (hcnt >= H_DISP+H_FRONT-1'b1) && (hcnt < H_DISP+H_FRONT+H_SYNC-1'b1) )
            vga_hs <= 0;       
        else
            vga_hs <= 1;
		end
end

//------------------------------------------
// 场同步信号发生器
reg [9:0] vcnt;
always @ (posedge clk_vga or negedge rst_n)
begin
	if (!rst_n) begin
		vcnt <= 0;
		// $display("%h",vcnt);
	end
	else
		begin
		if(hcnt == H_DISP-1)
			begin
			if (vcnt < V_TOTAL-1'b1)			
				vcnt <= vcnt+1'b1;
			else
				vcnt <= 0;   
			end 
		else
			vcnt <= vcnt;
		end
end

always @ (posedge clk_vga or negedge rst_n) 
begin
	if(!rst_n)
		vga_vs <= 1;
	else
		begin
		if( (vcnt >= V_DISP+V_FRONT-1'b1) && (vcnt < V_DISP+V_FRONT+V_SYNC-1'b1) )
            vga_vs <= 0;        
        else
            vga_vs <= 1;		
		end
end

//------------------------------------------
assign	vga_xpos = (hcnt < H_DISP) ? hcnt[9:0]+1'b1 : 10'd0;
assign	vga_ypos = (vcnt < V_DISP) ? vcnt[9:0]+1'b1 : 10'd0;
assign	vga_rgb 	= 	((hcnt < H_DISP) && (vcnt < V_DISP)) ? vga_data : 12'd0;

endmodule

VGA_test/vga_pineball/src/vga_display.v
//a frame render for vga display basing on the xpos and y pos
module vga_display
#(
	parameter	H_DISP 	=	10'd640,
	parameter	V_DISP 	=	10'd480 
)
(
	//control signals 
	input				clk, //clock signal
	input   			rst_n, //reset when the signal is low
	//vga interface
	input		[9:0]	vga_xpos, //input the position of the pixel
	input 		[9:0] 	vga_ypos,
	output 	reg	[11:0] 	vga_data, //output data to display
	//position data
	input [9:0] pineball_x, //position data
	input [9:0] pineball_y //position data
);

//some colors definitions
localparam RED     	 =	12'hF00;
localparam GREEN     = 	12'h0F0;
localparam BLUE      = 	12'h00F;  
localparam WHITE     = 	12'hFFF;  
localparam BLACK     = 	12'h000;  
localparam YELLOW    = 	12'h0FF;  
localparam CYAN      = 	12'haaa;  
localparam ROYAL     = 	12'hFF0;  

localparam SIZE 	 = 	3'd5;
//main loop to generate the pixel data
//update the pixel by the layer order
always@(posedge clk or negedge rst_n)
begin
	if(!rst_n)
		vga_data <= 12'h0;
	else
		begin
		//update the pineball
		if (vga_xpos >= pineball_x && vga_xpos<=pineball_x+SIZE&&vga_ypos >= pineball_y && vga_ypos<=pineball_y+SIZE)
			vga_data=RED;
		else if (vga_xpos >= 0 && vga_xpos < (H_DISP>>3))
			vga_data <= ROYAL;
		else if(vga_xpos >= (H_DISP>>3)*1 && vga_xpos < (H_DISP>>3)*2)
			vga_data <= GREEN;
		else if(vga_xpos >= (H_DISP>>3)*2 && vga_xpos < (H_DISP>>3)*3)
			vga_data <= BLUE;
		else if(vga_xpos >= (H_DISP>>3)*3 && vga_xpos < (H_DISP>>3)*4)
			vga_data <= WHITE;
		else if(vga_xpos >= (H_DISP>>3)*4 && vga_xpos < (H_DISP>>3)*5)
			vga_data <= BLACK;
		else if(vga_xpos >= (H_DISP>>3)*5 && vga_xpos < (H_DISP>>3)*6)
			vga_data <= YELLOW;
		else if(vga_xpos >= (H_DISP>>3)*6 && vga_xpos < (H_DISP>>3)*7)
			vga_data <= CYAN;
		else// if(vga_xpos >= (H_DISP<<3)*7 && vga_xpos < (H_DISP<<3)*8)
			vga_data <= ROYAL;
		end
end

//wire	[19:0]	vga_result = vga_xpos * vga_ypos;
//always@(posedge clk or negedge rst_n)
//begin
//	if(!rst_n)
//		vga_data <= 16'h0;
//	else
//		vga_data = vga_result[15:0];
//end


endmodule

VGA_test/vga_pineball/src/pine_ball_controller.v
module pineball_data 
#(
    //display region
    parameter	H_DISP 	     =	10'd640,
	parameter	V_DISP 	     =	10'd480,
    parameter   POS_BITS     =  10,
    parameter   SIZE         =  10'd5
)
(
    input clk, //clock signal
    input rst_n, //reset signal enables when low

    output [POS_BITS-1:0]pos_x, //the x-axis position of ball
    output [POS_BITS-1:0]pos_y  //the y-axis position of ball
);
    //register definations
    reg [POS_BITS-1:0]POS_X_R;
    reg [POS_BITS-1:0]POS_Y_R;
    
    //the velocity of the pineball
    reg [POS_BITS-1:0]PINEBALL_VX =10'd1;
    reg [POS_BITS-1:0]PINEBALL_VY =10'd1;

    //cobinational circuits
    assign pos_x=POS_X_R;
    assign pos_y=POS_Y_R;

    //update the data
    always @(posedge clk or negedge rst_n) begin
        if(!rst_n) begin
            //reset the data
            POS_X_R<=5;
            POS_Y_R<=5;
            PINEBALL_VX <= 10'd1;
            PINEBALL_VY <= 10'd1;
        end
        else begin
            //update the position

            if(POS_X_R+10'd5>H_DISP||POS_X_R<=1) begin
                POS_X_R=POS_X_R-PINEBALL_VX;
                PINEBALL_VX = -PINEBALL_VX;
            end
            if(POS_Y_R+10'd5>V_DISP||POS_Y_R<=1) begin
                POS_Y_R=POS_Y_R-PINEBALL_VY;
                PINEBALL_VY = -PINEBALL_VY;
            end
            POS_X_R=POS_X_R+PINEBALL_VX;
            POS_Y_R=POS_Y_R+PINEBALL_VY;
        end
    end
endmodule

VGA_test/vga_pineball/src/time_divider.v
module timedivider 
#(
    parameter ratio=2
)
(
    input i_clk,
    input rst_n,
    output o_clk
);
    //registers definitions
    reg [31:0]count;
    integer lim=ratio/2;
    //combinational circuits
    assign o_clk=count>=lim?1'b1:1'b0;
    //counting
    always @(posedge i_clk or negedge rst_n) begin
        if(!rst_n) begin
            count<=32'b0;
        end
        else begin
            if(count<lim)begin
                count<=count+1;
            end
            else begin
                count<=32'b0;
            end
        end
    end
endmodule

VGA_test/my_vga_test/src/time_divider_advanced.v
`timescale 1ns/1ps
/***************************************
晶振频率 fc = 100MHz
输出频率 fo = 1kHz（根据需要可以设为任意值）
控制参数 K  = (fo*2^N)/fc = 2791728742
参数 N = 2^32,(32为计数器的位宽)
****************************************/
module div(
    input clk,
    input rst,
    output reg clk_out
    );

    reg [31:0] cnt;

always @(posedge clk or posedge rst) 
    if(rst)
        cnt <= 0;
    else
        cnt <= cnt + 32'd1073741824;  //计数器步长K

always @(posedge clk or posedge rst)
    if(rst)
        clk_out <= 1'b0;
    else if(cnt < 32'h7FFF_FFFF)
        clk_out <= 1'b0;
    else
        clk_out <= 1'b1;

endmodule

VGA_test/vga_pineball/src/top.v
module top (
    input 			clk, //clock input
	input 			rst_n, //reset at low level
	//vga interface
	output			vga_adv_clk, 
	output			vga_blank_n, 
	output			vga_sync_n,
	//vga output to the connection
	output			vga_hs,    
	output			vga_vs,    
	output	[11:0]	vga_rgb
);
    wire	clk_vga;
    wire	sys_rst_n;
    assign	vga_adv_clk	=	~clk_vga;
    assign	vga_blank_n = 	1'b1;		
    assign	vga_sync_n 	= 	1'b0;	
	parameter	DUTY_CYCLE		=	50;
	parameter	DIVIDE_DATA		=	2;
	parameter	MULTIPLY_DATA	=	1;
	parameter	H_DISP	=	11'd640;
	parameter	H_FRONT	=	11'd16; 
	parameter	H_SYNC 	=	11'd96;  
	parameter	H_BACK 	=	11'd48;   
	parameter	H_TOTAL	=	11'd800; 	
	parameter	V_DISP 	=	10'd480;  					
	parameter	V_FRONT	=	10'd10;  
	parameter	V_SYNC 	=	10'd2;   
	parameter	V_BACK 	=	10'd33;   
	parameter	V_TOTAL	=	10'd525;


//generate clock of 25MHz for vga
div div_inst(.clk(clk),.rst(~rst_n),.clk_out(clk_vga));
//-----------------------------data------------------
//-----------------------------
//data definitions
wire	[9:0]	pineball_x;
wire	[9:0]	pineball_y;
wire pineball_clk;
//generate clock signal for position generating
timedivider #(10000000)
time_div_for_pineball
(
	.i_clk(clk),
	.rst_n(rst_n),
	.o_clk(pineball_clk)
);
//generate pineball position data
pineball_data
#(
	.H_DISP 	(H_DISP),
	.V_DISP 	(V_DISP) 
)
pineball_controller
(
	.clk(pineball_clk),
	.rst_n(rst_n),
	.pos_x(pineball_x),
	.pos_y(pineball_y)
);
//-----------------------------display--------------------
//-----------------------------
//vga display instantiation
wire	[9:0]	vga_xpos;
wire	[9:0]	vga_ypos;
wire	[11:0]	vga_data;
//generate vga data based on the pos data
vga_display 
#(
	.H_DISP 	(H_DISP),
	.V_DISP 	(V_DISP) 
)
vga_display_inst
(
	.clk		(clk_vga), 
	.rst_n		(rst_n), 

	.vga_xpos	(vga_xpos), 
	.vga_ypos	(vga_ypos),
	.vga_data	(vga_data),

	.pineball_x	(pineball_x),
	.pineball_y	(pineball_y)
);

//----------------------------
//vga driver instantiation
vga_driver
#
(
	.H_DISP 	(H_DISP), 	
	.H_FRONT	(H_FRONT),	
	.H_SYNC 	(H_SYNC), 	
	.H_BACK 	(H_BACK), 	
	.H_TOTAL	(H_TOTAL),	
	.V_DISP 	(V_DISP), 					
	.V_FRONT	(V_FRONT),	 
	.V_SYNC 	(V_SYNC), 	
	.V_BACK 	(V_BACK), 	
	.V_TOTAL	(V_TOTAL)
)
vga_driver_inst
(  	
	.clk_vga	(clk_vga),	
	.rst_n		(rst_n),     
	
	.vga_data	(vga_data),
	.vga_rgb	(vga_rgb),	
	.vga_hs		(vga_hs),	
	.vga_vs		(vga_vs),	
	
	.vga_xpos	(vga_xpos),	
	.vga_ypos	(vga_ypos)	
);
endmodule

VGA_test/my_vga_test/src/top_tb.v
module top_tb (
);
    reg 			clk; //外部时钟
    reg 			rst_n; //低电平复位信号
    //vga interface
    wire			vga_adv_clk; 
    wire			vga_blank_n; 
    wire			vga_sync_n;
    wire			vga_hs;    
    wire			vga_vs;    
    wire	[11:0]	vga_rgb;
    top inst(
        .clk(clk),
        .rst_n(rst_n),
        .vga_adv_clk(vga_adv_clk),
        .vga_blank_n(vga_blank_n),
        .vga_sync_n(vga_sync_n),
        .vga_hs(vga_hs),
        .vga_vs(vga_vs),
        .vga_rgb(vga_rgb)
        );
    initial	begin
        clk=0;
        rst_n=1;
        #5
        rst_n=0;
        #5
        rst_n=1;
    end
    integer i;
    initial begin
        for (i = 0;i<100 ;i=i+1 ) begin
            #5
            clk=0;
            #5
            clk=1;
        end
    end
    initial begin
        $dumpfile("./build/wave.vcd");  // 指定VCD文件的名字为wave.vcd，仿真信息将记录到此文件
        $dumpvars(0, top_tb);  // 指定层次数为0，则tb_code 模块及其下面各层次的所有信号将被记录
        #10000 $finish;
    end
endmodule

VGA_test/vga_pineball/build/wave.vcd
$date
	Sun Jan  2 10:48:39 2022
$end
$version
	Icarus Verilog
$end
$timescale
	1ps
$end
$scope module top_tb $end
$var wire 1 ! vga_blank_n $end
$var wire 1 " vga_sync_n $end
$var wire 1 # vga_vs $end
$var wire 12 $ vga_rgb [11:0] $end
$var wire 1 % vga_hs $end
$var wire 1 & vga_adv_clk $end
$var reg 1 ' clk $end
$var reg 1 ( rst_n $end
$var integer 32 ) i [31:0] $end
$scope module inst $end
$var wire 1 ' clk $end
$var wire 1 ( rst_n $end
$var wire 1 & vga_adv_clk $end
$var wire 1 ! vga_blank_n $end
$var wire 1 " vga_sync_n $end
$var wire 10 * vga_ypos [9:0] $end
$var wire 10 + vga_xpos [9:0] $end
$var wire 1 # vga_vs $end
$var wire 12 , vga_rgb [11:0] $end
$var wire 1 % vga_hs $end
$var wire 12 - vga_data [11:0] $end
$var wire 10 . pineball_y [9:0] $end
$var wire 10 / pineball_x [9:0] $end
$var wire 1 0 pineball_clk $end
$var wire 1 1 clk_vga $end
$scope module div_inst $end
$var wire 1 ' clk $end
$var wire 1 2 rst $end
$var reg 1 1 clk_out $end
$var reg 32 3 cnt [31:0] $end
$upscope $end
$scope module pineball_controller $end
$var wire 10 4 pos_x [9:0] $end
$var wire 10 5 pos_y [9:0] $end
$var wire 1 ( rst_n $end
$var wire 1 0 clk $end
$var reg 10 6 PINEBALL_VX [9:0] $end
$var reg 10 7 PINEBALL_VY [9:0] $end
$var reg 10 8 POS_X_R [9:0] $end
$var reg 10 9 POS_Y_R [9:0] $end
$upscope $end
$scope module time_div_for_pineball $end
$var wire 1 ' i_clk $end
$var wire 1 ( rst_n $end
$var wire 1 0 o_clk $end
$var reg 32 : count [31:0] $end
$var integer 32 ; lim [31:0] $end
$upscope $end
$scope module vga_display_inst $end
$var wire 1 1 clk $end
$var wire 10 < pineball_x [9:0] $end
$var wire 10 = pineball_y [9:0] $end
$var wire 1 ( rst_n $end
$var wire 10 > vga_ypos [9:0] $end
$var wire 10 ? vga_xpos [9:0] $end
$var reg 12 @ vga_data [11:0] $end
$upscope $end
$scope module vga_driver_inst $end
$var wire 1 1 clk_vga $end
$var wire 1 ( rst_n $end
$var wire 12 A vga_data [11:0] $end
$var wire 10 B vga_ypos [9:0] $end
$var wire 10 C vga_xpos [9:0] $end
$var wire 12 D vga_rgb [11:0] $end
$var reg 11 E hcnt [10:0] $end
$var reg 10 F vcnt [9:0] $end
$var reg 1 % vga_hs $end
$var reg 1 # vga_vs $end
$upscope $end
$upscope $end
$upscope $end
$enddefinitions $end
#0
$dumpvars
bx F
bx E
bx D
bx C
bx B
bx A
bx @
bx ?
bx >
bx =
bx <
b10011000100101101000000 ;
bx :
bx 9
bx 8
b1 7
b1 6
bx 5
bx 4
bx 3
02
x1
x0
bx /
bx .
bx -
bx ,
bx +
bx *
b0 )
1(
0'
x&
x%
bx $
x#
0"
1!
$end
#5000
1&
00
b0 $
b0 ,
b0 D
b1 +
b1 ?
b1 C
b1 *
b1 >
b1 B
b0 3
01
b0 .
b0 5
b0 =
b0 9
b0 /
b0 4
b0 <
b0 8
b0 :
b0 -
b0 @
b0 A
b0 E
1%
b0 F
1#
12
0(
#10000
b1000000000000000000000000000000 3
b1 :
02
b1 )
1'
1(
#15000
0'
#20000
b10000000000000000000000000000000 3
b10 :
b10 )
1'
#25000
0'
#30000
b10 +
b10 ?
b10 C
b1 E
b111100000000 $
b111100000000 ,
b111100000000 D
b111100000000 -
b111100000000 @
b111100000000 A
0&
11
b11000000000000000000000000000000 3
b11 :
b11 )
1'
#35000
0'
#40000
b0 3
b100 :
b100 )
1'
#45000
0'
#50000
1&
01
b1000000000000000000000000000000 3
b101 :
b101 )
1'
#55000
0'
#60000
b10000000000000000000000000000000 3
b110 :
b110 )
1'
#65000
0'
#70000
b11 +
b11 ?
b11 C
b10 E
0&
11
b11000000000000000000000000000000 3
b111 :
b111 )
1'
#75000
0'
#80000
b0 3
b1000 :
b1000 )
1'
#85000
0'
#90000
1&
01
b1000000000000000000000000000000 3
b1001 :
b1001 )
1'
#95000
0'
#100000
b10000000000000000000000000000000 3
b1010 :
b1010 )
1'
#105000
0'
#110000
b100 +
b100 ?
b100 C
b11 E
0&
11
b11000000000000000000000000000000 3
b1011 :
b1011 )
1'
#115000
0'
#120000
b0 3
b1100 :
b1100 )
1'
#125000
0'
#130000
1&
01
b1000000000000000000000000000000 3
b1101 :
b1101 )
1'
#135000
0'
#140000
b10000000000000000000000000000000 3
b1110 :
b1110 )
1'
#145000
0'
#150000
b101 +
b101 ?
b101 C
b100 E
0&
11
b11000000000000000000000000000000 3
b1111 :
b1111 )
1'
#155000
0'
#160000
b0 3
b10000 :
b10000 )
1'
#165000
0'
#170000
1&
01
b1000000000000000000000000000000 3
b10001 :
b10001 )
1'
#175000
0'
#180000
b10000000000000000000000000000000 3
b10010 :
b10010 )
1'
#185000
0'
#190000
b110 +
b110 ?
b110 C
b101 E
0&
11
b11000000000000000000000000000000 3
b10011 :
b10011 )
1'
#195000
0'
#200000
b0 3
b10100 :
b10100 )
1'
#205000
0'
#210000
1&
01
b1000000000000000000000000000000 3
b10101 :
b10101 )
1'
#215000
0'
#220000
b10000000000000000000000000000000 3
b10110 :
b10110 )
1'
#225000
0'
#230000
b111 +
b111 ?
b111 C
b111111110000 $
b111111110000 ,
b111111110000 D
b111111110000 -
b111111110000 @
b111111110000 A
b110 E
0&
11
b11000000000000000000000000000000 3
b10111 :
b10111 )
1'
#235000
0'
#240000
b0 3
b11000 :
b11000 )
1'
#245000
0'
#250000
1&
01
b1000000000000000000000000000000 3
b11001 :
b11001 )
1'
#255000
0'
#260000
b10000000000000000000000000000000 3
b11010 :
b11010 )
1'
#265000
0'
#270000
b1000 +
b1000 ?
b1000 C
b111 E
0&
11
b11000000000000000000000000000000 3
b11011 :
b11011 )
1'
#275000
0'
#280000
b0 3
b11100 :
b11100 )
1'
#285000
0'
#290000
1&
01
b1000000000000000000000000000000 3
b11101 :
b11101 )
1'
#295000
0'
#300000
b10000000000000000000000000000000 3
b11110 :
b11110 )
1'
#305000
0'
#310000
b1001 +
b1001 ?
b1001 C
b1000 E
0&
11
b11000000000000000000000000000000 3
b11111 :
b11111 )
1'
#315000
0'
#320000
b0 3
b100000 :
b100000 )
1'
#325000
0'
#330000
1&
01
b1000000000000000000000000000000 3
b100001 :
b100001 )
1'
#335000
0'
#340000
b10000000000000000000000000000000 3
b100010 :
b100010 )
1'
#345000
0'
#350000
b1010 +
b1010 ?
b1010 C
b1001 E
0&
11
b11000000000000000000000000000000 3
b100011 :
b100011 )
1'
#355000
0'
#360000
b0 3
b100100 :
b100100 )
1'
#365000
0'
#370000
1&
01
b1000000000000000000000000000000 3
b100101 :
b100101 )
1'
#375000
0'
#380000
b10000000000000000000000000000000 3
b100110 :
b100110 )
1'
#385000
0'
#390000
b1011 +
b1011 ?
b1011 C
b1010 E
0&
11
b11000000000000000000000000000000 3
b100111 :
b100111 )
1'
#395000
0'
#400000
b0 3
b101000 :
b101000 )
1'
#405000
0'
#410000
1&
01
b1000000000000000000000000000000 3
b101001 :
b101001 )
1'
#415000
0'
#420000
b10000000000000000000000000000000 3
b101010 :
b101010 )
1'
#425000
0'
#430000
b1100 +
b1100 ?
b1100 C
b1011 E
0&
11
b11000000000000000000000000000000 3
b101011 :
b101011 )
1'
#435000
0'
#440000
b0 3
b101100 :
b101100 )
1'
#445000
0'
#450000
1&
01
b1000000000000000000000000000000 3
b101101 :
b101101 )
1'
#455000
0'
#460000
b10000000000000000000000000000000 3
b101110 :
b101110 )
1'
#465000
0'
#470000
b1101 +
b1101 ?
b1101 C
b1100 E
0&
11
b11000000000000000000000000000000 3
b101111 :
b101111 )
1'
#475000
0'
#480000
b0 3
b110000 :
b110000 )
1'
#485000
0'
#490000
1&
01
b1000000000000000000000000000000 3
b110001 :
b110001 )
1'
#495000
0'
#500000
b10000000000000000000000000000000 3
b110010 :
b110010 )
1'
#505000
0'
#510000
b1110 +
b1110 ?
b1110 C
b1101 E
0&
11
b11000000000000000000000000000000 3
b110011 :
b110011 )
1'
#515000
0'
#520000
b0 3
b110100 :
b110100 )
1'
#525000
0'
#530000
1&
01
b1000000000000000000000000000000 3
b110101 :
b110101 )
1'
#535000
0'
#540000
b10000000000000000000000000000000 3
b110110 :
b110110 )
1'
#545000
0'
#550000
b1111 +
b1111 ?
b1111 C
b1110 E
0&
11
b11000000000000000000000000000000 3
b110111 :
b110111 )
1'
#555000
0'
#560000
b0 3
b111000 :
b111000 )
1'
#565000
0'
#570000
1&
01
b1000000000000000000000000000000 3
b111001 :
b111001 )
1'
#575000
0'
#580000
b10000000000000000000000000000000 3
b111010 :
b111010 )
1'
#585000
0'
#590000
b10000 +
b10000 ?
b10000 C
b1111 E
0&
11
b11000000000000000000000000000000 3
b111011 :
b111011 )
1'
#595000
0'
#600000
b0 3
b111100 :
b111100 )
1'
#605000
0'
#610000
1&
01
b1000000000000000000000000000000 3
b111101 :
b111101 )
1'
#615000
0'
#620000
b10000000000000000000000000000000 3
b111110 :
b111110 )
1'
#625000
0'
#630000
b10001 +
b10001 ?
b10001 C
b10000 E
0&
11
b11000000000000000000000000000000 3
b111111 :
b111111 )
1'
#635000
0'
#640000
b0 3
b1000000 :
b1000000 )
1'
#645000
0'
#650000
1&
01
b1000000000000000000000000000000 3
b1000001 :
b1000001 )
1'
#655000
0'
#660000
b10000000000000000000000000000000 3
b1000010 :
b1000010 )
1'
#665000
0'
#670000
b10010 +
b10010 ?
b10010 C
b10001 E
0&
11
b11000000000000000000000000000000 3
b1000011 :
b1000011 )
1'
#675000
0'
#680000
b0 3
b1000100 :
b1000100 )
1'
#685000
0'
#690000
1&
01
b1000000000000000000000000000000 3
b1000101 :
b1000101 )
1'
#695000
0'
#700000
b10000000000000000000000000000000 3
b1000110 :
b1000110 )
1'
#705000
0'
#710000
b10011 +
b10011 ?
b10011 C
b10010 E
0&
11
b11000000000000000000000000000000 3
b1000111 :
b1000111 )
1'
#715000
0'
#720000
b0 3
b1001000 :
b1001000 )
1'
#725000
0'
#730000
1&
01
b1000000000000000000000000000000 3
b1001001 :
b1001001 )
1'
#735000
0'
#740000
b10000000000000000000000000000000 3
b1001010 :
b1001010 )
1'
#745000
0'
#750000
b10100 +
b10100 ?
b10100 C
b10011 E
0&
11
b11000000000000000000000000000000 3
b1001011 :
b1001011 )
1'
#755000
0'
#760000
b0 3
b1001100 :
b1001100 )
1'
#765000
0'
#770000
1&
01
b1000000000000000000000000000000 3
b1001101 :
b1001101 )
1'
#775000
0'
#780000
b10000000000000000000000000000000 3
b1001110 :
b1001110 )
1'
#785000
0'
#790000
b10101 +
b10101 ?
b10101 C
b10100 E
0&
11
b11000000000000000000000000000000 3
b1001111 :
b1001111 )
1'
#795000
0'
#800000
b0 3
b1010000 :
b1010000 )
1'
#805000
0'
#810000
1&
01
b1000000000000000000000000000000 3
b1010001 :
b1010001 )
1'
#815000
0'
#820000
b10000000000000000000000000000000 3
b1010010 :
b1010010 )
1'
#825000
0'
#830000
b10110 +
b10110 ?
b10110 C
b10101 E
0&
11
b11000000000000000000000000000000 3
b1010011 :
b1010011 )
1'
#835000
0'
#840000
b0 3
b1010100 :
b1010100 )
1'
#845000
0'
#850000
1&
01
b1000000000000000000000000000000 3
b1010101 :
b1010101 )
1'
#855000
0'
#860000
b10000000000000000000000000000000 3
b1010110 :
b1010110 )
1'
#865000
0'
#870000
b10111 +
b10111 ?
b10111 C
b10110 E
0&
11
b11000000000000000000000000000000 3
b1010111 :
b1010111 )
1'
#875000
0'
#880000
b0 3
b1011000 :
b1011000 )
1'
#885000
0'
#890000
1&
01
b1000000000000000000000000000000 3
b1011001 :
b1011001 )
1'
#895000
0'
#900000
b10000000000000000000000000000000 3
b1011010 :
b1011010 )
1'
#905000
0'
#910000
b11000 +
b11000 ?
b11000 C
b10111 E
0&
11
b11000000000000000000000000000000 3
b1011011 :
b1011011 )
1'
#915000
0'
#920000
b0 3
b1011100 :
b1011100 )
1'
#925000
0'
#930000
1&
01
b1000000000000000000000000000000 3
b1011101 :
b1011101 )
1'
#935000
0'
#940000
b10000000000000000000000000000000 3
b1011110 :
b1011110 )
1'
#945000
0'
#950000
b11001 +
b11001 ?
b11001 C
b11000 E
0&
11
b11000000000000000000000000000000 3
b1011111 :
b1011111 )
1'
#955000
0'
#960000
b0 3
b1100000 :
b1100000 )
1'
#965000
0'
#970000
1&
01
b1000000000000000000000000000000 3
b1100001 :
b1100001 )
1'
#975000
0'
#980000
b10000000000000000000000000000000 3
b1100010 :
b1100010 )
1'
#985000
0'
#990000
b11010 +
b11010 ?
b11010 C
b11001 E
0&
11
b11000000000000000000000000000000 3
b1100011 :
b1100011 )
1'
#995000
0'
#1000000
b0 3
b1100100 :
b1100100 )
1'
