pwm_driver/src/time_divider.v
module time_divider 
#(
    parameter ratio=2
)
(
    input i_clk,
    input rst_n,
    output reg o_clk=0
);
    //registers definitions
    reg [31:0]count;
    integer lim=ratio/2;
    //counting
    always @(posedge i_clk or negedge rst_n) begin
        if(!rst_n) begin
            count<=32'b0;
        end
        else begin
            if(count<lim)begin
                count<=count+1;
            end
            else begin
                count<=32'b0;
                o_clk<=~o_clk;
            end
        end
    end
endmodule

pwm_driver/src/pwm_driver.v
module pwm_driver
(
    input i_clk,
    input i_rst_n,
    input [12:0]data=12'd50, //50 to 250
    output o_signal
);
    wire gen_clk;
    reg [12:0]counter;
    time_divider 
    #(1000) div_inst
    (
        .i_clk(i_clk),
        .rst_n(i_rst_n),
        .o_clk(gen_clk)
    );
    assign o_signal=(counter>=0&&counter<=data)?1:0;
    always @(posedge gen_clk or negedge i_rst_n) begin
        if(!i_rst_n) begin
            counter=0;
        end
        else begin
            if(counter==2000) begin
                counter=0;
            end
            else begin
                counter=counter+1;
            end
        end
    end
endmodule

pwm_driver/src/pwm_driver_tb.v
module pwm_driver_tb();
    reg i_clk;
    reg i_rst_n;
    reg [12:0]data; //50 to 250
    wire o_signal;
    pwm_driver inst(.i_clk(i_clk),.i_rst_n(i_rst_n),.data(data),.o_signal(o_signal));
    integer i;
    initial begin
        data=12'd50;
        i_clk=0;
        i_rst_n=1;
        #5
        i_rst_n=0;
        #5
        i_rst_n=1;
        for (i = 0;i<20000;i=i+1) begin
            #5
            i_clk=1;
            #5
            i_clk=0;
        end
    end
    initial begin   
        $dumpfile("./build/wave.vcd");  // 指定VCD文件的名字为wave.vcd，仿真信息将记录到此文件
        $dumpvars(0, pwm_driver_tb);  // 指定层次数为0，则tb_code 模块及其下面各层次的所有信号将被记录
        #100000 $finish;
    end
endmodule

pwm_driver/build/wave.vcd
$date
	Thu Jan  6 14:36:57 2022
$end
$version
	Icarus Verilog
$end
$timescale
	1s
$end
$scope module pwm_driver_tb $end
$var wire 1 ! o_signal $end
$var reg 13 " data [12:0] $end
$var reg 1 # i_clk $end
$var reg 1 $ i_rst_n $end
$var integer 32 % i [31:0] $end
$scope module inst $end
$var wire 13 & data [12:0] $end
$var wire 1 # i_clk $end
$var wire 1 $ i_rst_n $end
$var wire 1 ! o_signal $end
$var wire 1 ' gen_clk $end
$var reg 13 ( counter [12:0] $end
$scope module div_inst $end
$var wire 1 # i_clk $end
$var wire 1 $ rst_n $end
$var reg 32 ) count [31:0] $end
$var reg 1 ' o_clk $end
$var integer 32 * lim [31:0] $end
$upscope $end
$upscope $end
$upscope $end
$enddefinitions $end
#0
$dumpvars
b10 *
bx )
bx (
0'
b110010 &
bx %
1$
0#
b110010 "
x!
$end
#5
b0 )
1!
b0 (
0$
#10
b0 %
1$
#15
b1 )
1#
#20
b1 %
0#
#25
b10 )
1#
#30
b10 %
0#
#35
b1 (
1'
b0 )
1#
#40
b11 %
0#
#45
b1 )
1#
#50
b100 %
0#
#55
b10 )
1#
#60
b101 %
0#
#65
0'
b0 )
1#
#70
b110 %
0#
#75
b1 )
1#
#80
b111 %
0#
#85
b10 )
1#
#90
b1000 %
0#
#95
b10 (
1'
b0 )
1#
#100
b1001 %
0#
#105
b1 )
1#
#110
b1010 %
0#
#115
b10 )
1#
#120
b1011 %
0#
#125
0'
b0 )
1#
#130
b1100 %
0#
#135
b1 )
1#
#140
b1101 %
0#
#145
b10 )
1#
#150
b1110 %
0#
#155
b11 (
1'
b0 )
1#
#160
b1111 %
0#
#165
b1 )
1#
#170
b10000 %
0#
#175
b10 )
1#
#180
b10001 %
0#
#185
0'
b0 )
1#
#190
b10010 %
0#
#195
b1 )
1#
#200
b10011 %
0#
#205
b10 )
1#
#210
b10100 %
0#
#215
b100 (
1'
b0 )
1#
#220
b10101 %
0#
#225
b1 )
1#
#230
b10110 %
0#
#235
b10 )
1#
#240
b10111 %
0#
#245
0'
b0 )
1#
#250
b11000 %
0#
#255
b1 )
1#
#260
b11001 %
0#
#265
b10 )
1#
#270
b11010 %
0#
#275
b101 (
1'
b0 )
1#
#280
b11011 %
0#
#285
b1 )
1#
#290
b11100 %
0#
#295
b10 )
1#
#300
b11101 %
0#
#305
0'
b0 )
1#
#310
b11110 %
0#
#315
b1 )
1#
#320
b11111 %
0#
#325
b10 )
1#
#330
b100000 %
0#
#335
b110 (
1'
b0 )
1#
#340
b100001 %
0#
#345
b1 )
1#
#350
b100010 %
0#
#355
b10 )
1#
#360
b100011 %
0#
#365
0'
b0 )
1#
#370
b100100 %
0#
#375
b1 )
1#
#380
b100101 %
0#
#385
b10 )
1#
#390
b100110 %
0#
#395
b111 (
1'
b0 )
1#
#400
b100111 %
0#
#405
b1 )
1#
#410
b101000 %
0#
#415
b10 )
1#
#420
b101001 %
0#
#425
0'
b0 )
1#
#430
b101010 %
0#
#435
b1 )
1#
#440
b101011 %
0#
#445
b10 )
1#
#450
b101100 %
0#
#455
b1000 (
1'
b0 )
1#
#460
b101101 %
0#
#465
b1 )
1#
#470
b101110 %
0#
#475
b10 )
1#
#480
b101111 %
0#
#485
0'
b0 )
1#
#490
b110000 %
0#
#495
b1 )
1#
#500
b110001 %
0#
#505
b10 )
1#
#510
b110010 %
0#
#515
b1001 (
1'
b0 )
1#
#520
b110011 %
0#
#525
b1 )
1#
#530
b110100 %
0#
#535
b10 )
1#
#540
b110101 %
0#
#545
0'
b0 )
1#
#550
b110110 %
0#
#555
b1 )
1#
#560
b110111 %
0#
#565
b10 )
1#
#570
b111000 %
0#
#575
b1010 (
1'
b0 )
1#
#580
b111001 %
0#
#585
b1 )
1#
#590
b111010 %
0#
#595
b10 )
1#
#600
b111011 %
0#
#605
0'
b0 )
1#
#610
b111100 %
0#
#615
b1 )
1#
#620
b111101 %
0#
#625
b10 )
1#
#630
b111110 %
0#
#635
b1011 (
1'
b0 )
1#
#640
b111111 %
0#
#645
b1 )
1#
#650
b1000000 %
0#
#655
b10 )
1#
#660
b1000001 %
0#
#665
0'
b0 )
1#
#670
b1000010 %
0#
#675
b1 )
1#
#680
b1000011 %
0#
#685
b10 )
1#
#690
b1000100 %
0#
#695
b1100 (
1'
b0 )
1#
#700
b1000101 %
0#
#705
b1 )
1#
#710
b1000110 %
0#
#715
b10 )
1#
#720
b1000111 %
0#
#725
0'
b0 )
1#
#730
b1001000 %
0#
#735
b1 )
1#
#740
b1001001 %
0#
#745
b10 )
1#
#750
b1001010 %
0#
#755
b1101 (
1'
b0 )
1#
#760
b1001011 %
0#
#765
b1 )
1#
#770
b1001100 %
0#
#775
b10 )
1#
#780
b1001101 %
0#
#785
0'
b0 )
1#
#790
b1001110 %
0#
#795
b1 )
1#
#800
b1001111 %
0#
#805
b10 )
1#
#810
b1010000 %
0#
#815
b1110 (
1'
b0 )
1#
#820
b1010001 %
0#
#825
b1 )
1#
#830
b1010010 %
0#
#835
b10 )
1#
#840
b1010011 %
0#
#845
0'
b0 )
1#
#850
b1010100 %
0#
#855
b1 )
1#
#860
b1010101 %
0#
#865
b10 )
1#
#870
b1010110 %
0#
#875
b1111 (
1'
b0 )
1#
#880
b1010111 %
0#
#885
b1 )
1#
#890
b1011000 %
0#
#895
b10 )
1#
#900
b1011001 %
0#
#905
0'
b0 )
1#
#910
b1011010 %
0#
#915
b1 )
1#
#920
b1011011 %
0#
#925
b10 )
1#
#930
b1011100 %
0#
#935
b10000 (
1'
b0 )
1#
#940
b1011101 %
0#
#945
b1 )
1#
#950
b1011110 %
0#
#955
b10 )
1#
#960
b1011111 %
0#
#965
0'
b0 )
1#
#970
b1100000 %
0#
#975
b1 )
1#
#980
b1100001 %
0#
#985
b10 )
1#
#990
b1100010 %
0#
#995
b10001 (
1'
b0 )
1#
#1000
b1100011 %
0#
#1005
b1 )
1#
#1010
b1100100 %
0#
#1015
b10 )
1#
#1020
b1100101 %
0#
#1025
0'
b0 )
1#
#1030
b1100110 %
0#
#1035
b1 )
1#
#1040
b1100111 %
0#
#1045
b10 )
1#
#1050
b1101000 %
0#
#1055
b10010 (
1'
b0 )
1#
#1060
b1101001 %
0#
#1065
b1 )
1#
#1070
b1101010 %
0#
#1075
b10 )
1#
#1080
b1101011 %
0#
#1085
0'
b0 )
1#
#1090
b1101100 %
0#
#1095
b1 )
1#
#1100
b1101101 %
0#
#1105
b10 )
1#
#1110
b1101110 %
0#
#1115
b10011 (
1'
b0 )
1#
#1120
b1101111 %
0#
#1125
b1 )
1#
#1130
b1110000 %
0#
#1135
b10 )
1#
#1140
b1110001 %
0#
#1145
0'
b0 )
1#
#1150
b1110010 %
0#
#1155
b1 )
1#
#1160
b1110011 %
0#
#1165
b10 )
1#
#1170
b1110100 %
0#
#1175
b10100 (
1'
b0 )
1#
#1180
b1110101 %
0#
#1185
b1 )
1#
#1190
b1110110 %
0#
#1195
b10 )
1#
#1200
b1110111 %
0#
#1205
0'
b0 )
1#
#1210
b1111000 %
0#
#1215
b1 )
1#
#1220
b1111001 %
0#
#1225
b10 )
1#
#1230
b1111010 %
0#
#1235
b10101 (
1'
b0 )
1#
#1240
b1111011 %
0#
#1245
b1 )
1#
#1250
b1111100 %
0#
#1255
b10 )
1#
#1260
b1111101 %
0#
#1265
0'
b0 )
1#
#1270
b1111110 %
0#
#1275
b1 )
1#
#1280
b1111111 %
0#
#1285
b10 )
1#
#1290
b10000000 %
0#
#1295
b10110 (
1'
b0 )
1#
#1300
b10000001 %
0#
#1305
b1 )
1#
#1310
b10000010 %
0#
#1315
b10 )
1#
#1320
b10000011 %
0#
#1325
0'
b0 )
1#
#1330
b10000100 %
0#
#1335
b1 )
1#
#1340
b10000101 %
0#
#1345
b10 )
1#
#1350
b10000110 %
0#
#1355
b10111 (
1'
b0 )
1#
#1360
b10000111 %
0#
#1365
b1 )
1#
#1370
b10001000 %
0#
#1375
b10 )
1#
#1380
b10001001 %
0#
#1385
0'
b0 )
1#
#1390
b10001010 %
0#
#1395
b1 )
1#
#1400
b10001011 %
0#
#1405
b10 )
1#
#1410
b10001100 %
0#
#1415
b11000 (
1'
b0 )
1#
#1420
b10001101 %
0#
#1425
b1 )
1#
#1430
b10001110 %
0#
#1435
b10 )
1#
#1440
b10001111 %
0#
#1445
0'
b0 )
1#
#1450
b10010000 %
0#
#1455
b1 )
1#
#1460
b10010001 %
0#
#1465
b10 )
1#
#1470
b10010010 %
0#
#1475
b11001 (
1'
b0 )
1#
#1480
b10010011 %
0#
#1485
b1 )
1#
#1490
b10010100 %
0#
#1495
b10 )
1#
#1500
b10010101 %
0#
#1505
0'
b0 )
1#
#1510
b10010110 %
0#
#1515
b1 )
1#
#1520
b10010111 %
0#
#1525
b10 )
1#
#1530
b10011000 %
0#
#1535
b11010 (
1'
b0 )
1#
#1540
b10011001 %
0#
#1545
b1 )
1#
#1550
b10011010 %
0#
#1555
b10 )
1#
#1560
b10011011 %
0#
#1565
0'
b0 )
1#
#1570
b10011100 %
0#
#1575
b1 )
1#
#1580
b10011101 %
0#
#1585
b10 )
1#
#1590
b10011110 %
0#
#1595
b11011 (
1'
b0 )
1#
#1600
b10011111 %
0#
#1605
b1 )
1#
#1610
b10100000 %
0#
#1615
b10 )
1#
#1620
b10100001 %
0#
#1625
0'
b0 )
1#
#1630
b10100010 %
0#
#1635
b1 )
1#
#1640
b10100011 %
0#
#1645
b10 )
1#
#1650
b10100100 %
0#
#1655
b11100 (
1'
b0 )
1#
#1660
b10100101 %
0#
#1665
b1 )
1#
#1670
b10100110 %
0#
#1675
b10 )
1#
#1680
b10100111 %
0#
#1685
0'
b0 )
1#
#1690
b10101000 %
0#
#1695
b1 )
1#
#1700
b10101001 %
0#
#1705
b10 )
1#
#1710
b10101010 %
0#
#1715
b11101 (
1'
b0 )
1#
#1720
b10101011 %
0#
#1725
b1 )
1#
#1730
b10101100 %
0#
#1735
b10 )
1#
#1740
b10101101 %
0#
#1745
0'
b0 )
1#
#1750
b10101110 %
0#
#1755
b1 )
1#
#1760
b10101111 %
0#
#1765
b10 )
1#
#1770
b10110000 %
0#
#1775
b11110 (
1'
b0 )
1#
#1780
b10110001 %
0#
#1785
b1 )
1#
#1790
b10110010 %
0#
#1795
b10 )
1#
#1800
b10110011 %
0#
#1805
0'
b0 )
1#
#1810
b10110100 %
0#
#1815
b1 )
1#
#1820
b10110101 %
0#
#1825
b10 )
1#
#1830
b10110110 %
0#
#1835
b11111 (
1'
b0 )
1#
#1840
b10110111 %
0#
#1845
b1 )
1#
#1850
b10111000 %
0#
#1855
b10 )
1#
#1860
b10111001 %
0#
#1865
0'
b0 )
1#
#1870
b10111010 %
0#
#1875
b1 )
1#
#1880
b10111011 %
0#
#1885
b10 )
1#
#1890
b10111100 %
0#
#1895
b100000 (
1'
b0 )
1#
#1900
b10111101 %
0#
#1905
b1 )
1#
#1910
b10111110 %
0#
#1915
b10 )
1#
#1920
b10111111 %
0#
#1925
0'
b0 )
1#
#1930
b11000000 %
0#
#1935
b1 )
1#
#1940
b11000001 %
0#
#1945
b10 )
1#
#1950
b11000010 %
0#
#1955
b100001 (
1'
b0 )
1#
#1960
b11000011 %
0#
#1965
b1 )
1#
#1970
b11000100 %
0#
#1975
b10 )
1#
#1980
b11000101 %
0#
#1985
0'
b0 )
1#
#1990
b11000110 %
0#
#1995
b1 )
1#
#2000
b11000111 %
0#
#2005
b10 )
1#
#2010
b11001000 %
0#
#2015
b100010 (
1'
b0 )
1#
#2020
b11001001 %
0#
#2025
b1 )
1#
#2030
b11001010 %
0#
#2035
b10 )
1#
#2040
b11001011 %
0#
#2045
0'
b0 )
1#
#2050
b11001100 %
0#
#2055
b1 )
1#
#2060
b11001101 %
0#
#2065
b10 )
1#
#2070
b11001110 %
0#
#2075
b100011 (
1'
b0 )
1#
#2080
b11001111 %
0#
#2085
b1 )
1#
#2090
b11010000 %
0#
#2095
b10 )
1#
#2100
b11010001 %
0#
#2105
0'
b0 )
1#
#2110
b11010010 %
0#
#2115
b1 )
1#
#2120
b11010011 %
0#
#2125
b10 )
1#
#2130
b11010100 %
0#
#2135
b100100 (
1'
b0 )
1#
#2140
b11010101 %
0#
#2145
b1 )
1#
#2150
b11010110 %
0#
#2155
b10 )
1#
#2160
b11010111 %
0#
#2165
0'
b0 )
1#
#2170
b11011000 %
0#
#2175
b1 )
1#
#2180
b11011001 %
0#
#2185
b10 )
1#
#2190
b11011010 %
0#
#2195
b100101 (
1'
b0 )
1#
#2200
b11011011 %
0#
#2205
b1 )
1#
#2210
b11011100 %
0#
#2215
b10 )
1#
#2220
b11011101 %
0#
#2225
0'
b0 )
1#
#2230
b11011110 %
0#
#2235
b1 )
1#
#2240
b11011111 %
0#
#2245
b10 )
1#
#2250
b11100000 %
0#
#2255
b100110 (
1'
b0 )
1#
#2260
b11100001 %
0#
#2265
b1 )
1#
#2270
b11100010 %
0#
#2275
b10 )
1#
#2280
b11100011 %
0#
#2285
0'
b0 )
1#
#2290
b11100100 %
0#
#2295
b1 )
1#
#2300
b11100101 %
0#
#2305
b10 )
1#
#2310
b11100110 %
0#
#2315
b100111 (
1'
b0 )
1#
#2320
b11100111 %
0#
#2325
b1 )
1#
#2330
b11101000 %
0#
#2335
b10 )
1#
#2340
b11101001 %
0#
#2345
0'
b0 )
1#
#2350
b11101010 %
0#
#2355
b1 )
1#
#2360
b11101011 %
0#
#2365
b10 )
1#
#2370
b11101100 %
0#
#2375
b101000 (
1'
b0 )
1#
#2380
b11101101 %
0#
#2385
b1 )
1#
#2390
b11101110 %
0#
#2395
b10 )
1#
#2400
b11101111 %
0#
#2405
0'
b0 )
1#
#2410
b11110000 %
0#
#2415
b1 )
1#
#2420
b11110001 %
0#
#2425
b10 )
1#
#2430
b11110010 %
0#
#2435
b101001 (
1'
b0 )
1#
#2440
b11110011 %
0#
#2445
b1 )
1#
#2450
b11110100 %
0#
#2455
b10 )
1#
#2460
b11110101 %
0#
#2465
0'
b0 )
1#
#2470
b11110110 %
0#
#2475
b1 )
1#
#2480
b11110111 %
0#
#2485
b10 )
1#
#2490
b11111000 %
0#
#2495
b101010 (
1'
b0 )
1#
#2500
b11111001 %
0#
#2505
b1 )
1#
#2510
b11111010 %
0#
#2515
b10 )
1#
#2520
b11111011 %
0#
#2525
0'
b0 )
1#
#2530
b11111100 %
0#
#2535
b1 )
1#
#2540
b11111101 %
0#
#2545
b10 )
1#
#2550
b11111110 %
0#
#2555
b101011 (
1'
b0 )
1#
#2560
b11111111 %
0#
#2565
b1 )
1#
#2570
b100000000 %
0#
#2575
b10 )
1#
#2580
b100000001 %
0#
#2585
0'
b0 )
1#
#2590
b100000010 %
0#
#2595
b1 )
1#
#2600
b100000011 %
0#
#2605
b10 )
1#
#2610
b100000100 %
0#
#2615
b101100 (
1'
b0 )
1#
#2620
b100000101 %
0#
#2625
b1 )
1#
#2630
b100000110 %
0#
#2635
b10 )
1#
#2640
b100000111 %
0#
#2645
0'
b0 )
1#
#2650
b100001000 %
0#
#2655
b1 )
1#
#2660
b100001001 %
0#
#2665
b10 )
1#
#2670
b100001010 %
0#
#2675
b101101 (
1'
b0 )
1#
#2680
b100001011 %
0#
#2685
b1 )
1#
#2690
b100001100 %
0#
#2695
b10 )
1#
#2700
b100001101 %
0#
#2705
0'
b0 )
1#
#2710
b100001110 %
0#
#2715
b1 )
1#
#2720
b100001111 %
0#
#2725
b10 )
1#
#2730
b100010000 %
0#
#2735
b101110 (
1'
b0 )
1#
#2740
b100010001 %
0#
#2745
b1 )
1#
#2750
b100010010 %
0#
#2755
b10 )
1#
#2760
b100010011 %
0#
#2765
0'
b0 )
1#
#2770
b100010100 %
0#
#2775
b1 )
1#
#2780
b100010101 %
0#
#2785
b10 )
1#
#2790
b100010110 %
0#
#2795
b101111 (
1'
b0 )
1#
#2800
b100010111 %
0#
#2805
b1 )
1#
#2810
b100011000 %
0#
#2815
b10 )
1#
#2820
b100011001 %
0#
#2825
0'
b0 )
1#
#2830
b100011010 %
0#
#2835
b1 )
1#
#2840
b100011011 %
0#
#2845
b10 )
1#
#2850
b100011100 %
0#
#2855
b110000 (
1'
b0 )
1#
#2860
b100011101 %
0#
#2865
b1 )
1#
#2870
b100011110 %
0#
#2875
b10 )
1#
#2880
b100011111 %
0#
#2885
0'
b0 )
1#
#2890
b100100000 %
0#
#2895
b1 )
1#
#2900
b100100001 %
0#
#2905
b10 )
1#
#2910
b100100010 %
0#
#2915
b110001 (
1'
b0 )
1#
#2920
b100100011 %
0#
#2925
b1 )
1#
#2930
b100100100 %
0#
#2935
b10 )
1#
#2940
b100100101 %
0#
#2945
0'
b0 )
1#
#2950
b100100110 %
0#
#2955
b1 )
1#
#2960
b100100111 %
0#
#2965
b10 )
1#
#2970
b100101000 %
0#
#2975
b110010 (
1'
b0 )
1#
#2980
b100101001 %
0#
#2985
b1 )
1#
#2990
b100101010 %
0#
#2995
b10 )
1#
#3000
b100101011 %
0#
#3005
0'
b0 )
1#
#3010
b100101100 %
0#
#3015
b1 )
1#
#3020
b100101101 %
0#
#3025
b10 )
1#
#3030
b100101110 %
0#
#3035
0!
b110011 (
1'
b0 )
1#
#3040
b100101111 %
0#
#3045
b1 )
1#
#3050
b100110000 %
0#
#3055
b10 )
1#
#3060
b100110001 %
0#
#3065
0'
b0 )
1#
#3070
b100110010 %
0#
#3075
b1 )
1#
#3080
b100110011 %
0#
#3085
b10 )
1#
#3090
b100110100 %
0#
#3095
b110100 (
1'
b0 )
1#
#3100
b100110101 %
0#
#3105
b1 )
1#
#3110
b100110110 %
0#
#3115
b10 )
1#
#3120
b100110111 %
0#
#3125
0'
b0 )
1#
#3130
b100111000 %
0#
#3135
b1 )
1#
#3140
b100111001 %
0#
#3145
b10 )
1#
#3150
b100111010 %
0#
#3155
b110101 (
1'
b0 )
1#
#3160
b100111011 %
0#
#3165
b1 )
1#
#3170
b100111100 %
0#
#3175
b10 )
1#
#3180
b100111101 %
0#
#3185
0'
b0 )
1#
#3190
b100111110 %
0#
#3195
b1 )
1#
#3200
b100111111 %
0#
#3205
b10 )
1#
#3210
b101000000 %
0#
#3215
b110110 (
1'
b0 )
1#
#3220
b101000001 %
0#
#3225
b1 )
1#
#3230
b101000010 %
0#
#3235
b10 )
1#
#3240
b101000011 %
0#
#3245
0'
b0 )
1#
#3250
b101000100 %
0#
#3255
b1 )
1#
#3260
b101000101 %
0#
#3265
b10 )
1#
#3270
b101000110 %
0#
#3275
b110111 (
1'
b0 )
1#
#3280
b101000111 %
0#
#3285
b1 )
1#
#3290
b101001000 %
0#
#3295
b10 )
1#
#3300
b101001001 %
0#
#3305
0'
b0 )
1#
#3310
b101001010 %
0#
#3315
b1 )
1#
#3320
b101001011 %
0#
#3325
b10 )
1#
#3330
b101001100 %
0#
#3335
b111000 (
1'
b0 )
1#
#3340
b101001101 %
0#
#3345
b1 )
1#
#3350
b101001110 %
0#
#3355
b10 )
1#
#3360
b101001111 %
0#
#3365
0'
b0 )
1#
#3370
b101010000 %
0#
#3375
b1 )
1#
#3380
b101010001 %
0#
#3385
b10 )
1#
#3390
b101010010 %
0#
#3395
b111001 (
1'
b0 )
1#
#3400
b101010011 %
0#
#3405
b1 )
1#
#3410
b101010100 %
0#
#3415
b10 )
1#
#3420
b101010101 %
0#
#3425
0'
b0 )
1#
#3430
b101010110 %
0#
#3435
b1 )
1#
#3440
b101010111 %
0#
#3445
b10 )
1#
#3450
b101011000 %
0#
#3455
b111010 (
1'
b0 )
1#
#3460
b101011001 %
0#
#3465
b1 )
1#
#3470
b101011010 %
0#
#3475
b10 )
1#
#3480
b101011011 %
0#
#3485
0'
b0 )
1#
#3490
b101011100 %
0#
#3495
b1 )
1#
#3500
b101011101 %
0#
#3505
b10 )
1#
#3510
b101011110 %
0#
#3515
b111011 (
1'
b0 )
1#
#3520
b101011111 %
0#
#3525
b1 )
1#
#3530
b101100000 %
0#
#3535
b10 )
1#
#3540
b101100001 %
0#
#3545
0'
b0 )
1#
#3550
b101100010 %
0#
#3555
b1 )
1#
#3560
b101100011 %
0#
#3565
b10 )
1#
#3570
b101100100 %
0#
#3575
b111100 (
1'
b0 )
1#
#3580
b101100101 %
0#
#3585
b1 )
1#
#3590
b101100110 %
0#
#3595
b10 )
1#
#3600
b101100111 %
0#
#3605
0'
b0 )
1#
#3610
b101101000 %
0#
#3615
b1 )
1#
#3620
b101101001 %
0#
#3625
b10 )
1#
#3630
b101101010 %
0#
#3635
b111101 (
1'
b0 )
1#
#3640
b101101011 %
0#
#3645
b1 )
1#
#3650
b101101100 %
0#
#3655
b10 )
1#
#3660
b101101101 %
0#
#3665
0'
b0 )
1#
#3670
b101101110 %
0#
#3675
b1 )
1#
#3680
b101101111 %
0#
#3685
b10 )
1#
#3690
b101110000 %
0#
#3695
b111110 (
1'
b0 )
1#
#3700
b101110001 %
0#
#3705
b1 )
1#
#3710
b101110010 %
0#
#3715
b10 )
1#
#3720
b101110011 %
0#
#3725
0'
b0 )
1#
#3730
b101110100 %
0#
#3735
b1 )
1#
#3740
b101110101 %
0#
#3745
b10 )
1#
#3750
b101110110 %
0#
#3755
b111111 (
1'
b0 )
1#
#3760
b101110111 %
0#
#3765
b1 )
1#
#3770
b101111000 %
0#
#3775
b10 )
1#
#3780
b101111001 %
0#
#3785
0'
b0 )
1#
#3790
b101111010 %
0#
#3795
b1 )
1#
#3800
b101111011 %
0#
#3805
b10 )
1#
#3810
b101111100 %
0#
#3815
b1000000 (
1'
b0 )
1#
#3820
b101111101 %
0#
#3825
b1 )
1#
#3830
b101111110 %
0#
#3835
b10 )
1#
#3840
b101111111 %
0#
#3845
0'
b0 )
1#
#3850
b110000000 %
0#
#3855
b1 )
1#
#3860
b110000001 %
0#
#3865
b10 )
1#
#3870
b110000010 %
0#
#3875
b1000001 (
1'
b0 )
1#
#3880
b110000011 %
0#
#3885
b1 )
1#
#3890
b110000100 %
0#
#3895
b10 )
1#
#3900
b110000101 %
0#
#3905
0'
b0 )
1#
#3910
b110000110 %
0#
#3915
b1 )
1#
#3920
b110000111 %
0#
#3925
b10 )
1#
#3930
b110001000 %
0#
#3935
b1000010 (
1'
b0 )
1#
#3940
b110001001 %
0#
#3945
b1 )
1#
#3950
b110001010 %
0#
#3955
b10 )
1#
#3960
b110001011 %
0#
#3965
0'
b0 )
1#
#3970
b110001100 %
0#
#3975
b1 )
1#
#3980
b110001101 %
0#
#3985
b10 )
1#
#3990
b110001110 %
0#
#3995
b1000011 (
1'
b0 )
1#
#4000
b110001111 %
0#
#4005
b1 )
1#
#4010
b110010000 %
0#
#4015
b10 )
1#
#4020
b110010001 %
0#
#4025
0'
b0 )
1#
#4030
b110010010 %
0#
#4035
b1 )
1#
#4040
b110010011 %
0#
#4045
b10 )
1#
#4050
b110010100 %
0#
#4055
b1000100 (
1'
b0 )
1#
#4060
b110010101 %
0#
#4065
b1 )
1#
#4070
b110010110 %
0#
#4075
b10 )
1#
#4080
b110010111 %
0#
#4085
0'
b0 )
1#
#4090
b110011000 %
0#
#4095
b1 )
1#
#4100
b110011001 %
0#
#4105
b10 )
1#
#4110
b110011010 %
0#
#4115
b1000101 (
1'
b0 )
1#
#4120
b110011011 %
0#
#4125
b1 )
1#
#4130
b110011100 %
0#
#4135
b10 )
1#
#4140
b110011101 %
0#
#4145
0'
b0 )
1#
#4150
b110011110 %
0#
#4155
b1 )
1#
#4160
b110011111 %
0#
#4165
b10 )
1#
#4170
b110100000 %
0#
#4175
b1000110 (
1'
b0 )
1#
#4180
b110100001 %
0#
#4185
b1 )
1#
#4190
b110100010 %
0#
#4195
b10 )
1#
#4200
b110100011 %
0#
#4205
0'
b0 )
1#
#4210
b110100100 %
0#
#4215
b1 )
1#
#4220
b110100101 %
0#
#4225
b10 )
1#
#4230
b110100110 %
0#
#4235
b1000111 (
1'
b0 )
1#
#4240
b110100111 %
0#
#4245
b1 )
1#
#4250
b110101000 %
0#
#4255
b10 )
1#
#4260
b110101001 %
0#
#4265
0'
b0 )
1#
#4270
b110101010 %
0#
#4275
b1 )
1#
#4280
b110101011 %
0#
#4285
b10 )
1#
#4290
b110101100 %
0#
#4295
b1001000 (
1'
b0 )
1#
#4300
b110101101 %
0#
#4305
b1 )
1#
#4310
b110101110 %
0#
#4315
b10 )
1#
#4320
b110101111 %
0#
#4325
0'
b0 )
1#
#4330
b110110000 %
0#
#4335
b1 )
1#
#4340
b110110001 %
0#
#4345
b10 )
1#
#4350
b110110010 %
0#
#4355
b1001001 (
1'
b0 )
1#
#4360
b110110011 %
0#
#4365
b1 )
1#
#4370
b110110100 %
0#
#4375
b10 )
1#
#4380
b110110101 %
0#
#4385
0'
b0 )
1#
#4390
b110110110 %
0#
#4395
b1 )
1#
#4400
b110110111 %
0#
#4405
b10 )
1#
#4410
b110111000 %
0#
#4415
b1001010 (
1'
b0 )
1#
#4420
b110111001 %
0#
#4425
b1 )
1#
#4430
b110111010 %
0#
#4435
b10 )
1#
#4440
b110111011 %
0#
#4445
0'
b0 )
1#
#4450
b110111100 %
0#
#4455
b1 )
1#
#4460
b110111101 %
0#
#4465
b10 )
1#
#4470
b110111110 %
0#
#4475
b1001011 (
1'
b0 )
1#
#4480
b110111111 %
0#
#4485
b1 )
1#
#4490
b111000000 %
0#
#4495
b10 )
1#
#4500
b111000001 %
0#
#4505
0'
b0 )
1#
#4510
b111000010 %
0#
#4515
b1 )
1#
#4520
b111000011 %
0#
#4525
b10 )
1#
#4530
b111000100 %
0#
#4535
b1001100 (
1'
b0 )
1#
#4540
b111000101 %
0#
#4545
b1 )
1#
#4550
b111000110 %
0#
#4555
b10 )
1#
#4560
b111000111 %
0#
#4565
0'
b0 )
1#
#4570
b111001000 %
0#
#4575
b1 )
1#
#4580
b111001001 %
0#
#4585
b10 )
1#
#4590
b111001010 %
0#
#4595
b1001101 (
1'
b0 )
1#
#4600
b111001011 %
0#
#4605
b1 )
1#
#4610
b111001100 %
0#
#4615
b10 )
1#
#4620
b111001101 %
0#
#4625
0'
b0 )
1#
#4630
b111001110 %
0#
#4635
b1 )
1#
#4640
b111001111 %
0#
#4645
b10 )
1#
#4650
b111010000 %
0#
#4655
b1001110 (
1'
b0 )
1#
#4660
b111010001 %
0#
#4665
b1 )
1#
#4670
b111010010 %
0#
#4675
b10 )
1#
#4680
b111010011 %
0#
#4685
0'
b0 )
1#
#4690
b111010100 %
0#
#4695
b1 )
1#
#4700
b111010101 %
0#
#4705
b10 )
1#
#4710
b111010110 %
0#
#4715
b1001111 (
1'
b0 )
1#
#4720
b111010111 %
0#
#4725
b1 )
1#
#4730
b111011000 %
0#
#4735
b10 )
1#
#4740
b111011001 %
0#
#4745
0'
b0 )
1#
#4750
b111011010 %
0#
#4755
b1 )
1#
#4760
b111011011 %
0#
#4765
b10 )
1#
#4770
b111011100 %
0#
#4775
b1010000 (
1'
b0 )
1#
#4780
b111011101 %
0#
#4785
b1 )
1#
#4790
b111011110 %
0#
#4795
b10 )
1#
#4800
b111011111 %
0#
#4805
0'
b0 )
1#
#4810
b111100000 %
0#
#4815
b1 )
1#
#4820
b111100001 %
0#
#4825
b10 )
1#
#4830
b111100010 %
0#
#4835
b1010001 (
1'
b0 )
1#
#4840
b111100011 %
0#
#4845
b1 )
1#
#4850
b111100100 %
0#
#4855
b10 )
1#
#4860
b111100101 %
0#
#4865
0'
b0 )
1#
#4870
b111100110 %
0#
#4875
b1 )
1#
#4880
b111100111 %
0#
#4885
b10 )
1#
#4890
b111101000 %
0#
#4895
b1010010 (
1'
b0 )
1#
#4900
b111101001 %
0#
#4905
b1 )
1#
#4910
b111101010 %
0#
#4915
b10 )
1#
#4920
b111101011 %
0#
#4925
0'
b0 )
1#
#4930
b111101100 %
0#
#4935
b1 )
1#
#4940
b111101101 %
0#
#4945
b10 )
1#
#4950
b111101110 %
0#
#4955
b1010011 (
1'
b0 )
1#
